Workbook

Sheet 트래블마트 통합
A1: 2026 Travel Mart Schedule + Super Event (트래블마트 캘린더 통합) | N1: Update: 2026-7-30
A2: 국가 | B2: 도시 | C2: 2026년 1월 | D2: 2026년 2월 | E2: 2026년 3월 | F2: 2026년 4월 | G2: 2026년 5월 | H2: 2026년 6월 | I2: 2026년 7월 | J2: 2026년 8월 | K2: 2026년 9월 | L2: 2026년 10월 | M2: 2026년 11월 | N2: 2026년 12월 | O2: 2027년 1월 | P2: 2027년 2월 | Q2: 2027년 3월 | R2: 2027년 4월 | S2: 2027년 5월 | T2: 2027년 6월
A3: Super Events (Sports) | D3: 2026 밀라노-코르티나 동계올림픽 (이탈리아) 2026년 2월 6일 ~ 2월 22일 | E3: Grand Prix 13-15 March 2026 상하이 27-29 March 2026 일본 | F3: Grand Prix 10-12 April 2026 바레인 17-19 April 2026 사우디 | H3: 2026 FIFA 월드컵 (미국·캐나다·멕시코) 2026년 6월 11일 ~ 7월 19일 | J3: 2026 커먼웰스 게임즈 (조호르, 말레이시아 예정) | L3: Grand Prix 9-11 October 2026 싱가포르 | N3: Grand Prix 4-6 December 2026 UAE | Q3: F1 Grand Prix 중국(상하이)·일본(스즈카) 3월 중 (예상) | T3: 2027 FIFA 여자월드컵 (브라질) 2027년 6월 24일 ~ 7월 25일
A4: Super Events (Religious & Culture) | D4: 라마단 & 이드 알 피트르 라마단: 2026년 2월 20일 ~ 3월 21일 이드: 2026년 3월 22일 중동 → 동남아 (태국·말레이시아·한국) 여행 붐 | F4: 골든위크(일본) 2026년 4월 29일 ~ 5월 5일 Qingming Festival (청명절) 중국·홍콩·대만 출발 단기 여행 증가 | G4: Wesak (부처님오신날) 인도네시아·태국·말레이시아·싱가포르 | K4: 추석 한국·중국 outbound 혼잡 일본·베트남·대만 호텔 추가 수요 발생 | M4: Diwali (빛의 축제) – 인도 및 인도계 디아스포라 인도 출발 아웃바운드 여행 증가 → 태국, 베트남, 아랍에미리트 Yi Peng Festival (라이트·랜턴 축제) - 태국 | P4: 라마단 & 이드 알 피트르 라마단: 2027년 2월 9일경 ~ 3월 10일경 (예상) 이드: 3월 11일경 중동 → 동남아·한국 여행 붐 | Q4: 이드 알 피트르 3월 11일경 (예상) 중동·인도네시아·말레이시아 장기 연휴 | R4: 골든위크(일본) 4월 29일 ~ 5월 5일 Qingming Festival (청명절) 4월 5일 중국·홍콩·대만 단기 여행 증가 | S4: Wesak (부처님오신날) 5월 중 인도네시아·태국·말레이시아·싱가포르
A5: Super Events (MICE) | C5: CES 2026 (라스베가스) | D5: MWC Barcelona 2026 | E5: GDC(San Francisco), SXSW(Austin) | F5: China Import & Export Fair | K5: ASEAN Summit 2026 — 라오스 (Vientiane) 개최 | L5: China Import & Export Fair Japan CEATEC – 일본 최대 ICT 박람회 | M5: Web Summit 2026 (리스본) APEC Summit 2026 – 싱가포르 Singapore FinTech Festival 2026 Seoul MICE Week | O5: CES 2027 (라스베이거스) 1월 상순 (예상) | Q5: MWC Barcelona 2027 (3월 상순, 예상) SXSW Austin / GDC San Francisco (3월) | R5: China Import & Export Fair (캔톤페어) 4월 중순 ~ 5월 초
A6: China Events | C6: 방학시즌 | D6: 춘절 | F6: 벗꽃축제 | G6: 국경절, 노동절 | J6: 방학시즌 | K6: 추석, 중추절 | N6: 방학시즌 | O6: 방학시즌 | P6: 춘절 (2027년 2월 6일) | R6: 벚꽃축제 | S6: 노동절 (5/1~5/5)
A7: SEA Events | D7: Chiness New Year | P7: Chinese New Year (2/6)
A8: India & Rusia
A9: 중국 | B9: 광동,화동,화북,내륙 | C9: 1차 세일즈콜 광저우, 심천 | D9: Chiness New Year | E9: 1차 세일즈 콜 베이징 | F9: 1차 세일즈 콜 청두, 시안, 중경 COTTM Beijing (보통 4월) [★★★ 최우선] 중국 outbound 전문 B2B | G9: 5/26–5/28 – ITB China 1차 Shanghai GITF (Guangzhou International Travel Fair) 5/21–23 [★★★ 최우선] 중국 outbound 최상위 B2B | I9: 2차 세일즈 콜 심천+대만+홍콩 | K9: 2차 광저우, 심천 | L9: 1차 세일즈 콜 청두, 시안, 무한 CITIE Tourism Expo 2026 Guangzhou China (September 11-13) 2026 CHINA OUTBOUND & INBOUND TRAVEL MARKET 10/14–16 (베이징) | M9: 2차 베이징 국경절 1~7일 COITM from 14-16 October in Beijing | N9: 2차 상하이 | P9: Chinese New Year (2/6) | R9: COTTM Beijing 2027 4월 중 (예상) [★★★ 최우선] 중국 outbound 전문 B2B | S9: ITB China 2027 (상하이) 5월 중 (예상) GITF Guangzhou 5월 하순 (예상) [★★★ 최우선] 중국 outbound 최상위 B2B
A10: 한국 | B10: 서울 | G10: 일산 트래블마트 5월 14~17일 | H10: 6/4–6/7 – Seoul International Travel Fair (SITF) [★ 선택] 한국 최대 여행박람회 | I10: 6/30~7/1 SITM | J10: 한국 세일즈콜 8월3~7일 | M10: Travel Show 11월 12~15일 Korea MICE Expo (KME) 11/18–11/20 [★ 선택] 한국 MICE 대표 행사 | S10: 일산 트래블마트 2027 5월 중 (예상) | T10: Seoul International Travel Fair (SITF) 2027 6월 상순 (예상) SITM 6월 말~7월 초 (예상) [★ 선택] 한국 최대 여행박람회
A11: 일본 | B11: (순환개최) | K11: 9/24–9/27 – Tourism EXPO Japan (TEJ) [★★ 중간] 일본 최대 종합 트래블쇼
A12: 대만 | B12: 타이베이 | C12: 1차 세일즈 콜 대만+홍콩 | G12: 5/22–5/25 – Taipei Tourism Expo (TTE) [★ 선택] 대만 최대 B2C, FIT 시장 강함 | I12: 2차 세일즈 콜 심천+대만+홍콩 | M12: ITF Taiwan International Travel Fair (ITF) 11월 6일 (금) ~ 11월 9일(월) | S12: Taipei Tourism Expo (TTE) 2027 5월 하순 (예상) [★ 선택] 대만 최대 B2C, FIT 시장 강함
A13: 홍콩 | B13: 홍콩 | C13: 1차 세일즈 콜 대만+홍콩 | H13: ITE Hong Kong 6월 11~14일 전후 [★★ 중간] 홍콩–광둥 outbound 중심 | I13: 2차 세일즈 콜 심천+대만+홍콩 | K13: 2차 세일즈 콜 대만+홍콩 | T13: ITE Hong Kong 2027 6월 중순 (예상) [★★ 중간] 홍콩–광둥 outbound 중심
A14: 필리핀 | B14: 세부, 마닐라 | C14: 1/28–1/30 – ASEAN Tourism Forum + TRAVEX [★★ 중간] ASEAN 10개국 공식 B2B, 관광청 네트워크 최강 | D14: 2/6–2/8 – PTAA TravelTour Expo [★★★ 최우선] 필리핀 최대 소비자+B2B, 패키지 판매에 최적 | I14: Travel Madness Expo 2026 July 10 to 12, 2026 | O14: ASEAN Tourism Forum + TRAVEX 2027 1월 하순 (예상, 개최국 순회) [★★ 중간] ASEAN 10개국 공식 B2B, 관광청 네트워킹 | P14: PTAA TravelTour Expo 2027 2월 중 (예상) [★★★ 최우선] 필리핀 최대 소비자+B2B, 패키지 판매에 최적
A15: 베트남 | B15: 호치민 하노이 | F15: Vietnam International Travel Mart HANOI [★★ 중간] 북베트남 B2B+B2C | L15: ITE HCMC 16~18 Oct [★★ 중간] 메콩 최대 B2B+B2C (Calendar 기준 9/3–9/5) | R15: VITM Hanoi 2027 (Vietnam Int'l Travel Mart) 4월 상순 (예상) [★★ 중간] 북베트남 B2B+B2C
A16: 태국 | B16: 방콕 | C16: 1/22–1/25 – Thai International Travel Fair [★★★ 최우선] 태국 최대 B2B+B2C, 태국→한국·일본 outbound 중심 | E16: 5-8 Mar Thai Teaw Thai (77th Edition) B2C | H16: TTM+ (Thailand Travel Mart Plus) 2026 예상 날짜: 2026년 6월 중 (보통 6월 둘째 주) 장소: 미정 특징: 태국 관광청(TAT) 주관 행사 | L16: Visit Japan FIT Fair #17 올해 10월16~18일 개최 | O16: Thai International Travel Fair 2027 1월 하순 (예상) [★★★ 최우선] 태국 최대 B2B+B2C | Q16: Thai Teaw Thai (B2C) 3월 상순 (예상) | T16: TTM+ (Thailand Travel Mart Plus) 2027 6월 둘째 주 (예상) 태국 관광청(TAT) 주관
A17: 말레이시아 | B17: 쿠알라룸프르, 쿠칭 | E17: MATTA Fair 3 - 5 April 2026 [★ 선택] 말레이시아 최대 B2C | J17: 8/18–8/20 – PATA Travel Mart [★★ 중간] 아시아·태평양 대표 B2B | K17: MATTA Fair [★ 선택] 말레이시아 최대 B2C | Q17: MATTA Fair 2027 (상반기) 3월 말~4월 초 (예상) [★ 선택] 말레이시아 최대 B2C
A18: 싱가포르 | B18: 마리나베이 | H18: ILTM Asia Pacific 2026 2026년 6월 29일 ~ 7월 2일 [★ 선택] 아시아 럭셔리 여행 최상위 행사 | J18: NATAS (2026년 8월 21~23일) | L18: 10/21–10/23 – ITB Asia [★★★ 최우선] 아시아 No.1 B2B 허브 | T18: ILTM Asia Pacific 2027 (싱가포르) 6월 말 (예상) [★ 선택] 아시아 럭셔리 여행 최상위 행사
A19: 인도네시아 | B19: 자카르타 | G19: BBTF (Bali & Beyond Travel Fair) 2026 날짜: 2026년 5월 28일(목) ~ 5월 30일(토) 특징: 상반기 동남아시아 일정 중 호텔 소싱에 가장 중요한 행사 | H19: Travel Meet Asia 2026 2026년 6월 23-24일 [★ 선택] 아세안 B2B 네트워크 허브 | T19: BBTF (Bali & Beyond Travel Fair) 2027 6월 중 (예상) Travel Meet Asia 2027 6월 하순 (예상) 호텔 소싱 핵심 행사
A20: 인도 | B20: 뭄바이 뉴델리 | C20: OTM (Outbound Travel Mart, Mumbai) 5-7 Feb | D20: SATTE 2026 2026.02.25 – 02.27 [★★ 중간] 남아시아 인바운드/아웃바운드 | K20: 9/2–9/4 – ITB India [★★★ 최우선] 인도 outbound 핵심 | L20: South Asia Travel & Tourism Exchange | P20: OTM Mumbai 2027 (Outbound Travel Mart) 2월 상순 (예상) SATTE 2027 (뉴델리) 2월 하순 (예상) [★★ 중간] 인도 아웃바운드 핵심
A21: 러시아 | B21: 모스크바 | E21: MITT 2026 2026년 3월 11일 ~ 3월 13일 [★★ 중간] 러시아·CIS 최대, 러시아 outbound 핵심 | K21: OTDYKH Leisure Travel Market 2026 2026년 9월 10일 ~ 9월 12일 [★ 선택] 러시아 인바운드·아웃바운드 모두 강함 | Q21: MITT Moscow 2027 3월 중 (예상) [★★ 중간] 러시아·CIS 최대, 러시아 outbound 핵심
A22: UAE | B22: Dubai | G22: Arabian Travel Market (ATM) 2026 2026년 5월 4일 ~ 5월 7일 [★★★ 최우선] 중동 최대 여행 B2B, GCC 바이어 중심 | S22: Arabian Travel Market (ATM) 2027 (Dubai) 5월 상순 (예상) [★★★ 최우선] 중동 최대 여행 B2B, GCC 바이어 중심
A23: Qatar | B23: Doha | E23: Connections Luxury Middle East 2026 2026년 3월 29일 ~ 4월 1일 [★ 선택] 초럭셔리 바이어 행사, 하이엔드 전략용 | Q23: Connections Luxury Middle East 2027 3월 말~4월 초 (예상) [★ 선택] 초럭셔리 바이어 행사
A24: 독일 | B24: 베를린 오버하우젠 | E24: ITB Berlin 2026 2026년 3월 3일(화) ~ 3월 5일(목) [★★★ 최우선] 세계 1위 여행 B2B, 글로벌 파트너 확장 필수 | F24: Germany Travel Mart (GTM) 2026 2026년 4월 19일 ~ 21일 [★ 선택] 독일 관광청 주최, 유럽 인바운드 중심 | Q24: ITB Berlin 2027 3월 상순 (예상, 통상 첫째 주 화~목) [★★★ 최우선] 세계 1위 여행 B2B, 글로벌 파트너 확장 필수 | R24: Germany Travel Mart (GTM) 2027 4월 중 (예상) [★ 선택] 독일 관광청 주최, 유럽 인바운드 중심
A25: 호주 | B25: 시드니, 애들레이드 | G25: 5/10–5/14 – Australian Tourism Exchange (ATE) [★ 선택] 오세아니아 최대 B2B | L25: Luxperience | S25: Australian Tourism Exchange (ATE) 2027 5월 중 (예상) [★ 선택] 오세아니아 최대 B2B
A26: 영국 | B26: 런던 | M26: WTM London 2026 2026.11.04 – 11.06 [★★★ 최우선] 글로벌 레저, 기술, 지속가능성
A27: 스페인 | B27: 마드리드 | C27: FITUR Madrid 2026 1월 21일 ~ 25일 [★★ 중간] 세계 3대 관광박람회, 유럽·라틴 시장 핵심 B2B | O27: FITUR Madrid 2027 1월 하순 (예상, 통상 1/20~1/24) [★★ 중간] 세계 3대 관광박람회, 유럽·라틴 핵심
A28: 미국 | B28: 플로리다주 뉴욕 | C28: NYTTravel Show | D28: NYTTravel Show | E28: NYTTravel Show | F28: NYTTravel Show | G28: IPW 2026 2026년 5월 17-21일 [★ 선택] 미국 인바운드 최대 B2B 행사 | L28: Business Travel Show America 2026 2026년 10월 14-15일 [★ 선택] 북미 코퍼레이트 트래블 대표 행사 | O28: New York Times Travel Show 2027 1월 하순 (예상) | S28: IPW 2027 (U.S. Travel Association) 5월 하순 (예상) [★ 선택] 미국 인바운드 최대 B2B
A29: 멕시코 | B29: 과달라하라 | M29: ITB Americas 2026 2026년 11월 10-12일 [★ 선택] 미주 전역 바이어 연결 허브
A30: South Africa | B30: Cape Town | F30: WTM Africa 2026 [★ 선택] 아프리카 시장 접근 | R30: WTM Africa 2027 (Cape Town) 4월 중 (예상) [★ 선택] 아프리카 시장 접근
A31: 브라질 | B31: 상파울루 | F31: WTM Latin America 2026 2026년 4월 14-16일 [★ 선택] 남미 최대 B2B, 라틴 바이어 네트워크 | R31: WTM Latin America 2027 (상파울루) 4월 중 (예상) [★ 선택] 남미 최대 B2B, 라틴 바이어 네트워크
A33: 범례 (우선순위 · FOR OMH BY AI)
A34: ★★★ 최우선 | B34: 반드시 참가 · 핵심 소싱/바이어 시장 (셀 좌측 굵은 파란선)
A35: ★★ 중간 | B35: 여력에 따라 참가 · 지역 보완용 (좌측 검정선)
A36: ★ 선택 | B36: 선택 참가 · 전략적 필요 시 (좌측 빨간선)
A37: 비고 | B37: 각 행사 셀 하단의 [우선순위] 표기와 설명은 기존 Calendar 시트에서 통합된 내용입니다. ITE HCMC는 두 자료의 일정이 상이(10/16–18 vs 9/3–5)하여 병기했습니다.
A38: ※ 2027년 상반기(O~T열) 일정은 매년 정기 개최되는 행사를 기준으로 작성한 초안입니다. "(예상)"으로 표기된 일정은 주최 측 공식 발표 전이므로 확정 시 업데이트가 필요합니다. (웹 검색 차단 상태에서 작성 · 2026-08-18)

Sheet 일정 체크리스트
A1: 2026 트래블마트 일정 체크리스트 (2027년 상반기 포함) | E1: 참가 | F1: =COUNTIF(F4:F95,TRUE)&" / "&COUNTA(D4:D95) -> 30 / 92 | G1: 진행완료 | H1: =COUNTIF(G4:G95,TRUE)&" / "&COUNTA(D4:D95) -> 20 / 92
A3: 월 | B3: 국가 | C3: 도시 | D3: 일정명 | E3: 우선순위 | F3: 참가 | G3: 진행완료 | H3: 상태 | I3: 상세 내용 | J3: 비고
A4: ='트래블마트 통합'!C$2 -> 2026년 1월 | B4: ='트래블마트 통합'!$A9 -> 중국 | C4: ='트래블마트 통합'!$B9 -> 광동,화동,화북,내륙 | D4: =IFERROR(LEFT('트래블마트 통합'!C9,FIND(CHAR(10),'트래블마트 통합'!C9)-1),'트래블마트 통합'!C9) -> 1차 세일즈콜 | E4: =IF(ISNUMBER(SEARCH("★★★",'트래블마트 통합'!C9)),"★★★",IF(ISNUMBER(SEARCH("★★",'트래블마트 통합'!C9)),"★★",IF(ISNUMBER(SEARCH("★",'트래블마트 통합'!C9)),"★","-"))) -> - | F4: TRUE | G4: TRUE | H4: =IF(AND(F4,G4),"완료",IF(G4,"진행 완료",IF(F4,"참가 예정","미정"))) -> 완료 | I4: ='트래블마트 통합'!C9 -> 1차 세일즈콜 광저우, 심천
A5: ='트래블마트 통합'!C$2 -> 2026년 1월 | B5: ='트래블마트 통합'!$A12 -> 대만 | C5: ='트래블마트 통합'!$B12 -> 타이베이 | D5: =IFERROR(LEFT('트래블마트 통합'!C12,FIND(CHAR(10),'트래블마트 통합'!C12)-1),'트래블마트 통합'!C12) -> 1차 세일즈 콜 | E5: =IF(ISNUMBER(SEARCH("★★★",'트래블마트 통합'!C12)),"★★★",IF(ISNUMBER(SEARCH("★★",'트래블마트 통합'!C12)),"★★",IF(ISNUMBER(SEARCH("★",'트래블마트 통합'!C12)),"★","-"))) -> - | F5: TRUE | G5: TRUE | H5: =IF(AND(F5,G5),"완료",IF(G5,"진행 완료",IF(F5,"참가 예정","미정"))) -> 완료 | I5: ='트래블마트 통합'!C12 -> 1차 세일즈 콜 대만+홍콩
A6: ='트래블마트 통합'!C$2 -> 2026년 1월 | B6: ='트래블마트 통합'!$A13 -> 홍콩 | C6: ='트래블마트 통합'!$B13 -> 홍콩 | D6: =IFERROR(LEFT('트래블마트 통합'!C13,FIND(CHAR(10),'트래블마트 통합'!C13)-1),'트래블마트 통합'!C13) -> 1차 세일즈 콜 | E6: =IF(ISNUMBER(SEARCH("★★★",'트래블마트 통합'!C13)),"★★★",IF(ISNUMBER(SEARCH("★★",'트래블마트 통합'!C13)),"★★",IF(ISNUMBER(SEARCH("★",'트래블마트 통합'!C13)),"★","-"))) -> - | F6: TRUE | G6: TRUE | H6: =IF(AND(F6,G6),"완료",IF(G6,"진행 완료",IF(F6,"참가 예정","미정"))) -> 완료 | I6: ='트래블마트 통합'!C13 -> 1차 세일즈 콜 대만+홍콩
A7: ='트래블마트 통합'!C$2 -> 2026년 1월 | B7: ='트래블마트 통합'!$A14 -> 필리핀 | C7: ='트래블마트 통합'!$B14 -> 세부, 마닐라 | D7: =IFERROR(LEFT('트래블마트 통합'!C14,FIND(CHAR(10),'트래블마트 통합'!C14)-1),'트래블마트 통합'!C14) -> 1/28–1/30 – ASEAN Tourism Forum + TRAVEX | E7: =IF(ISNUMBER(SEARCH("★★★",'트래블마트 통합'!C14)),"★★★",IF(ISNUMBER(SEARCH("★★",'트래블마트 통합'!C14)),"★★",IF(ISNUMBER(SEARCH("★",'트래블마트 통합'!C14)),"★","-"))) -> ★★ | F7: TRUE | G7: TRUE | H7: =IF(AND(F7,G7),"완료",IF(G7,"진행 완료",IF(F7,"참가 예정","미정"))) -> 완료 | I7: ='트래블마트 통합'!C14 -> 1/28–1/30 – ASEAN Tourism Forum + TRAVEX [★★ 중간] ASEAN 10개국 공식 B2B, 관광청 네트워크 최강
A8: ='트래블마트 통합'!C$2 -> 2026년 1월 | B8: ='트래블마트 통합'!$A16 -> 태국 | C8: ='트래블마트 통합'!$B16 -> 방콕 | D8: =IFERROR(LEFT('트래블마트 통합'!C16,FIND(CHAR(10),'트래블마트 통합'!C16)-1),'트래블마트 통합'!C16) -> 1/22–1/25 – Thai International Travel Fair | E8: =IF(ISNUMBER(SEARCH("★★★",'트래블마트 통합'!C16)),"★★★",IF(ISNUMBER(SEARCH("★★",'트래블마트 통합'!C16)),"★★",IF(ISNUMBER(SEARCH("★",'트래블마트 통합'!C16)),"★","-"))) -> ★★★ | F8: TRUE | G8: TRUE | H8: =IF(AND(F8,G8),"완료",IF(G8,"진행 완료",IF(F8,"참가 예정","미정"))) -> 완료 | I8: ='트래블마트 통합'!C16 -> 1/22–1/25 – Thai International Travel Fair [★★★ 최우선] 태국 최대 B2B+B2C, 태국→한국·일본 outbound 중심
A9: ='트래블마트 통합'!C$2 -> 2026년 1월 | B9: ='트래블마트 통합'!$A20 -> 인도 | C9: ='트래블마트 통합'!$B20 -> 뭄바이 뉴델리 | D9: =IFERROR(LEFT('트래블마트 통합'!C20,FIND(CHAR(10),'트래블마트 통합'!C20)-1),'트래블마트 통합'!C20) -> OTM (Outbound Travel Mart, Mumbai) | E9: =IF(ISNUMBER(SEARCH("★★★",'트래블마트 통합'!C20)),"★★★",IF(ISNUMBER(SEARCH("★★",'트래블마트 통합'!C20)),"★★",IF(ISNUMBER(SEARCH("★",'트래블마트 통합'!C20)),"★","-"))) -> - | F9: TRUE | G9: TRUE | H9: =IF(AND(F9,G9),"완료",IF(G9,"진행 완료",IF(F9,"참가 예정","미정"))) -> 완료 | I9: ='트래블마트 통합'!C20 -> OTM (Outbound Travel Mart, Mumbai) 5-7 Feb
A10: ='트래블마트 통합'!C$2 -> 2026년 1월 | B10: ='트래블마트 통합'!$A27 -> 스페인 | C10: ='트래블마트 통합'!$B27 -> 마드리드 | D10: =IFERROR(LEFT('트래블마트 통합'!C27,FIND(CHAR(10),'트래블마트 통합'!C27)-1),'트래블마트 통합'!C27) -> FITUR Madrid 2026 | E10: =IF(ISNUMBER(SEARCH("★★★",'트래블마트 통합'!C27)),"★★★",IF(ISNUMBER(SEARCH("★★",'트래블마트 통합'!C27)),"★★",IF(ISNUMBER(SEARCH("★",'트래블마트 통합'!C27)),"★","-"))) -> ★★ | F10: FALSE | G10: FALSE | H10: =IF(AND(F10,G10),"완료",IF(G10,"진행 완료",IF(F10,"참가 예정","미정"))) -> 미정 | I10: ='트래블마트 통합'!C27 -> FITUR Madrid 2026 1월 21일 ~ 25일 [★★ 중간] 세계 3대 관광박람회, 유럽·라틴 시장 핵심 B2B
A11: ='트래블마트 통합'!C$2 -> 2026년 1월 | B11: ='트래블마트 통합'!$A28 -> 미국 | C11: ='트래블마트 통합'!$B28 -> 플로리다주 뉴욕 | D11: =IFERROR(LEFT('트래블마트 통합'!C28,FIND(CHAR(10),'트래블마트 통합'!C28)-1),'트래블마트 통합'!C28) -> NYTTravel Show | E11: =IF(ISNUMBER(SEARCH("★★★",'트래블마트 통합'!C28)),"★★★",IF(ISNUMBER(SEARCH("★★",'트래블마트 통합'!C28)),"★★",IF(ISNUMBER(SEARCH("★",'트래블마트 통합'!C28)),"★","-"))) -> - | F11: FALSE | G11: FALSE | H11: =IF(AND(F11,G11),"완료",IF(G11,"진행 완료",IF(F11,"참가 예정","미정"))) -> 미정 | I11: ='트래블마트 통합'!C28 -> NYTTravel Show
A12: ='트래블마트 통합'!D$2 -> 2026년 2월 | B12: ='트래블마트 통합'!$A9 -> 중국 | C12: ='트래블마트 통합'!$B9 -> 광동,화동,화북,내륙 | D12: =IFERROR(LEFT('트래블마트 통합'!D9,FIND(CHAR(10),'트래블마트 통합'!D9)-1),'트래블마트 통합'!D9) -> Chiness New Year | E12: =IF(ISNUMBER(SEARCH("★★★",'트래블마트 통합'!D9)),"★★★",IF(ISNUMBER(SEARCH("★★",'트래블마트 통합'!D9)),"★★",IF(ISNUMBER(SEARCH("★",'트래블마트 통합'!D9)),"★","-"))) -> - | F12: TRUE | G12: TRUE | H12: =IF(AND(F12,G12),"완료",IF(G12,"진행 완료",IF(F12,"참가 예정","미정"))) -> 완료 | I12: ='트래블마트 통합'!D9 -> Chiness New Year
A13: ='트래블마트 통합'!D$2 -> 2026년 2월 | B13: ='트래블마트 통합'!$A14 -> 필리핀 | C13: ='트래블마트 통합'!$B14 -> 세부, 마닐라 | D13: =IFERROR(LEFT('트래블마트 통합'!D14,FIND(CHAR(10),'트래블마트 통합'!D14)-1),'트래블마트 통합'!D14) -> 2/6–2/8 – PTAA TravelTour Expo | E13: =IF(ISNUMBER(SEARCH("★★★",'트래블마트 통합'!D14)),"★★★",IF(ISNUMBER(SEARCH("★★",'트래블마트 통합'!D14)),"★★",IF(ISNUMBER(SEARCH("★",'트래블마트 통합'!D14)),"★","-"))) -> ★★★ | F13: FALSE | G13: FALSE | H13: =IF(AND(F13,G13),"완료",IF(G13,"진행 완료",IF(F13,"참가 예정","미정"))) -> 미정 | I13: ='트래블마트 통합'!D14 -> 2/6–2/8 – PTAA TravelTour Expo [★★★ 최우선] 필리핀 최대 소비자+B2B, 패키지 판매에 최적
A14: ='트래블마트 통합'!D$2 -> 2026년 2월 | B14: ='트래블마트 통합'!$A20 -> 인도 | C14: ='트래블마트 통합'!$B20 -> 뭄바이 뉴델리 | D14: =IFERROR(LEFT('트래블마트 통합'!D20,FIND(CHAR(10),'트래블마트 통합'!D20)-1),'트래블마트 통합'!D20) -> SATTE 2026 | E14: =IF(ISNUMBER(SEARCH("★★★",'트래블마트 통합'!D20)),"★★★",IF(ISNUMBER(SEARCH("★★",'트래블마트 통합'!D20)),"★★",IF(ISNUMBER(SEARCH("★",'트래블마트 통합'!D20)),"★","-"))) -> ★★ | F14: TRUE | G14: TRUE | H14: =IF(AND(F14,G14),"완료",IF(G14,"진행 완료",IF(F14,"참가 예정","미정"))) -> 완료 | I14: ='트래블마트 통합'!D20 -> SATTE 2026 2026.02.25 – 02.27 [★★ 중간] 남아시아 인바운드/아웃바운드
A15: ='트래블마트 통합'!D$2 -> 2026년 2월 | B15: ='트래블마트 통합'!$A28 -> 미국 | C15: ='트래블마트 통합'!$B28 -> 플로리다주 뉴욕 | D15: =IFERROR(LEFT('트래블마트 통합'!D28,FIND(CHAR(10),'트래블마트 통합'!D28)-1),'트래블마트 통합'!D28) -> NYTTravel Show | E15: =IF(ISNUMBER(SEARCH("★★★",'트래블마트 통합'!D28)),"★★★",IF(ISNUMBER(SEARCH("★★",'트래블마트 통합'!D28)),"★★",IF(ISNUMBER(SEARCH("★",'트래블마트 통합'!D28)),"★","-"))) -> - | F15: FALSE | G15: FALSE | H15: =IF(AND(F15,G15),"완료",IF(G15,"진행 완료",IF(F15,"참가 예정","미정"))) -> 미정 | I15: ='트래블마트 통합'!D28 -> NYTTravel Show
A16: ='트래블마트 통합'!E$2 -> 2026년 3월 | B16: ='트래블마트 통합'!$A9 -> 중국 | C16: ='트래블마트 통합'!$B9 -> 광동,화동,화북,내륙 | D16: =IFERROR(LEFT('트래블마트 통합'!E9,FIND(CHAR(10),'트래블마트 통합'!E9)-1),'트래블마트 통합'!E9) -> 1차 세일즈 콜 | E16: =IF(ISNUMBER(SEARCH("★★★",'트래블마트 통합'!E9)),"★★★",IF(ISNUMBER(SEARCH("★★",'트래블마트 통합'!E9)),"★★",IF(ISNUMBER(SEARCH("★",'트래블마트 통합'!E9)),"★","-"))) -> - | F16: TRUE | G16: TRUE | H16: =IF(AND(F16,G16),"완료",IF(G16,"진행 완료",IF(F16,"참가 예정","미정"))) -> 완료 | I16: ='트래블마트 통합'!E9 -> 1차 세일즈 콜 베이징
A17: ='트래블마트 통합'!E$2 -> 2026년 3월 | B17: ='트래블마트 통합'!$A16 -> 태국 | C17: ='트래블마트 통합'!$B16 -> 방콕 | D17: =IFERROR(LEFT('트래블마트 통합'!E16,FIND(CHAR(10),'트래블마트 통합'!E16)-1),'트래블마트 통합'!E16) -> 5-8 Mar | E17: =IF(ISNUMBER(SEARCH("★★★",'트래블마트 통합'!E16)),"★★★",IF(ISNUMBER(SEARCH("★★",'트래블마트 통합'!E16)),"★★",IF(ISNUMBER(SEARCH("★",'트래블마트 통합'!E16)),"★","-"))) -> - | F17: TRUE | G17: TRUE | H17: =IF(AND(F17,G17),"완료",IF(G17,"진행 완료",IF(F17,"참가 예정","미정"))) -> 완료 | I17: ='트래블마트 통합'!E16 -> 5-8 Mar Thai Teaw Thai (77th Edition) B2C
A18: ='트래블마트 통합'!E$2 -> 2026년 3월 | B18: ='트래블마트 통합'!$A17 -> 말레이시아 | C18: ='트래블마트 통합'!$B17 -> 쿠알라룸프르, 쿠칭 | D18: =IFERROR(LEFT('트래블마트 통합'!E17,FIND(CHAR(10),'트래블마트 통합'!E17)-1),'트래블마트 통합'!E17) -> MATTA Fair | E18: =IF(ISNUMBER(SEARCH("★★★",'트래블마트 통합'!E17)),"★★★",IF(ISNUMBER(SEARCH("★★",'트래블마트 통합'!E17)),"★★",IF(ISNUMBER(SEARCH("★",'트래블마트 통합'!E17)),"★","-"))) -> ★ | F18: FALSE | G18: FALSE | H18: =IF(AND(F18,G18),"완료",IF(G18,"진행 완료",IF(F18,"참가 예정","미정"))) -> 미정 | I18: ='트래블마트 통합'!E17 -> MATTA Fair 3 - 5 April 2026 [★ 선택] 말레이시아 최대 B2C
A19: ='트래블마트 통합'!E$2 -> 2026년 3월 | B19: ='트래블마트 통합'!$A21 -> 러시아 | C19: ='트래블마트 통합'!$B21 -> 모스크바 | D19: =IFERROR(LEFT('트래블마트 통합'!E21,FIND(CHAR(10),'트래블마트 통합'!E21)-1),'트래블마트 통합'!E21) -> MITT 2026 | E19: =IF(ISNUMBER(SEARCH("★★★",'트래블마트 통합'!E21)),"★★★",IF(ISNUMBER(SEARCH("★★",'트래블마트 통합'!E21)),"★★",IF(ISNUMBER(SEARCH("★",'트래블마트 통합'!E21)),"★","-"))) -> ★★ | F19: FALSE | G19: FALSE | H19: =IF(AND(F19,G19),"완료",IF(G19,"진행 완료",IF(F19,"참가 예정","미정"))) -> 미정 | I19: ='트래블마트 통합'!E21 -> MITT 2026 2026년 3월 11일 ~ 3월 13일 [★★ 중간] 러시아·CIS 최대, 러시아 outbound 핵심
A20: ='트래블마트 통합'!E$2 -> 2026년 3월 | B20: ='트래블마트 통합'!$A23 -> Qatar | C20: ='트래블마트 통합'!$B23 -> Doha | D20: =IFERROR(LEFT('트래블마트 통합'!E23,FIND(CHAR(10),'트래블마트 통합'!E23)-1),'트래블마트 통합'!E23) -> Connections Luxury Middle East 2026 | E20: =IF(ISNUMBER(SEARCH("★★★",'트래블마트 통합'!E23)),"★★★",IF(ISNUMBER(SEARCH("★★",'트래블마트 통합'!E23)),"★★",IF(ISNUMBER(SEARCH("★",'트래블마트 통합'!E23)),"★","-"))) -> ★ | F20: FALSE | G20: FALSE | H20: =IF(AND(F20,G20),"완료",IF(G20,"진행 완료",IF(F20,"참가 예정","미정"))) -> 미정 | I20: ='트래블마트 통합'!E23 -> Connections Luxury Middle East 2026 2026년 3월 29일 ~ 4월 1일 [★ 선택] 초럭셔리 바이어 행사, 하이엔드 전략용
A21: ='트래블마트 통합'!E$2 -> 2026년 3월 | B21: ='트래블마트 통합'!$A24 -> 독일 | C21: ='트래블마트 통합'!$B24 -> 베를린 오버하우젠 | D21: =IFERROR(LEFT('트래블마트 통합'!E24,FIND(CHAR(10),'트래블마트 통합'!E24)-1),'트래블마트 통합'!E24) -> ITB Berlin 2026 | E21: =IF(ISNUMBER(SEARCH("★★★",'트래블마트 통합'!E24)),"★★★",IF(ISNUMBER(SEARCH("★★",'트래블마트 통합'!E24)),"★★",IF(ISNUMBER(SEARCH("★",'트래블마트 통합'!E24)),"★","-"))) -> ★★★ | F21: FALSE | G21: FALSE | H21: =IF(AND(F21,G21),"완료",IF(G21,"진행 완료",IF(F21,"참가 예정","미정"))) -> 미정 | I21: ='트래블마트 통합'!E24 -> ITB Berlin 2026 2026년 3월 3일(화) ~ 3월 5일(목) [★★★ 최우선] 세계 1위 여행 B2B, 글로벌 파트너 확장 필수
A22: ='트래블마트 통합'!E$2 -> 2026년 3월 | B22: ='트래블마트 통합'!$A28 -> 미국 | C22: ='트래블마트 통합'!$B28 -> 플로리다주 뉴욕 | D22: =IFERROR(LEFT('트래블마트 통합'!E28,FIND(CHAR(10),'트래블마트 통합'!E28)-1),'트래블마트 통합'!E28) -> NYTTravel Show | E22: =IF(ISNUMBER(SEARCH("★★★",'트래블마트 통합'!E28)),"★★★",IF(ISNUMBER(SEARCH("★★",'트래블마트 통합'!E28)),"★★",IF(ISNUMBER(SEARCH("★",'트래블마트 통합'!E28)),"★","-"))) -> - | F22: FALSE | G22: FALSE | H22: =IF(AND(F22,G22),"완료",IF(G22,"진행 완료",IF(F22,"참가 예정","미정"))) -> 미정 | I22: ='트래블마트 통합'!E28 -> NYTTravel Show
A23: ='트래블마트 통합'!F$2 -> 2026년 4월 | B23: ='트래블마트 통합'!$A9 -> 중국 | C23: ='트래블마트 통합'!$B9 -> 광동,화동,화북,내륙 | D23: =IFERROR(LEFT('트래블마트 통합'!F9,FIND(CHAR(10),'트래블마트 통합'!F9)-1),'트래블마트 통합'!F9) -> 1차 세일즈 콜 | E23: =IF(ISNUMBER(SEARCH("★★★",'트래블마트 통합'!F9)),"★★★",IF(ISNUMBER(SEARCH("★★",'트래블마트 통합'!F9)),"★★",IF(ISNUMBER(SEARCH("★",'트래블마트 통합'!F9)),"★","-"))) -> ★★★ | F23: TRUE | G23: TRUE | H23: =IF(AND(F23,G23),"완료",IF(G23,"진행 완료",IF(F23,"참가 예정","미정"))) -> 완료 | I23: ='트래블마트 통합'!F9 -> 1차 세일즈 콜 청두, 시안, 중경 COTTM Beijing (보통 4월) [★★★ 최우선] 중국 outbound 전문 B2B
A24: ='트래블마트 통합'!F$2 -> 2026년 4월 | B24: ='트래블마트 통합'!$A15 -> 베트남 | C24: ='트래블마트 통합'!$B15 -> 호치민 하노이 | D24: =IFERROR(LEFT('트래블마트 통합'!F15,FIND(CHAR(10),'트래블마트 통합'!F15)-1),'트래블마트 통합'!F15) -> Vietnam International Travel Mart HANOI | E24: =IF(ISNUMBER(SEARCH("★★★",'트래블마트 통합'!F15)),"★★★",IF(ISNUMBER(SEARCH("★★",'트래블마트 통합'!F15)),"★★",IF(ISNUMBER(SEARCH("★",'트래블마트 통합'!F15)),"★","-"))) -> ★★ | F24: FALSE | G24: FALSE | H24: =IF(AND(F24,G24),"완료",IF(G24,"진행 완료",IF(F24,"참가 예정","미정"))) -> 미정 | I24: ='트래블마트 통합'!F15 -> Vietnam International Travel Mart HANOI [★★ 중간] 북베트남 B2B+B2C
A25: ='트래블마트 통합'!F$2 -> 2026년 4월 | B25: ='트래블마트 통합'!$A24 -> 독일 | C25: ='트래블마트 통합'!$B24 -> 베를린 오버하우젠 | D25: =IFERROR(LEFT('트래블마트 통합'!F24,FIND(CHAR(10),'트래블마트 통합'!F24)-1),'트래블마트 통합'!F24) -> Germany Travel Mart (GTM) 2026 | E25: =IF(ISNUMBER(SEARCH("★★★",'트래블마트 통합'!F24)),"★★★",IF(ISNUMBER(SEARCH("★★",'트래블마트 통합'!F24)),"★★",IF(ISNUMBER(SEARCH("★",'트래블마트 통합'!F24)),"★","-"))) -> ★ | F25: FALSE | G25: FALSE | H25: =IF(AND(F25,G25),"완료",IF(G25,"진행 완료",IF(F25,"참가 예정","미정"))) -> 미정 | I25: ='트래블마트 통합'!F24 -> Germany Travel Mart (GTM) 2026 2026년 4월 19일 ~ 21일 [★ 선택] 독일 관광청 주최, 유럽 인바운드 중심
A26: ='트래블마트 통합'!F$2 -> 2026년 4월 | B26: ='트래블마트 통합'!$A28 -> 미국 | C26: ='트래블마트 통합'!$B28 -> 플로리다주 뉴욕 | D26: =IFERROR(LEFT('트래블마트 통합'!F28,FIND(CHAR(10),'트래블마트 통합'!F28)-1),'트래블마트 통합'!F28) -> NYTTravel Show | E26: =IF(ISNUMBER(SEARCH("★★★",'트래블마트 통합'!F28)),"★★★",IF(ISNUMBER(SEARCH("★★",'트래블마트 통합'!F28)),"★★",IF(ISNUMBER(SEARCH("★",'트래블마트 통합'!F28)),"★","-"))) -> - | F26: FALSE | G26: FALSE | H26: =IF(AND(F26,G26),"완료",IF(G26,"진행 완료",IF(F26,"참가 예정","미정"))) -> 미정 | I26: ='트래블마트 통합'!F28 -> NYTTravel Show
A27: ='트래블마트 통합'!F$2 -> 2026년 4월 | B27: ='트래블마트 통합'!$A30 -> South Africa | C27: ='트래블마트 통합'!$B30 -> Cape Town | D27: =IFERROR(LEFT('트래블마트 통합'!F30,FIND(CHAR(10),'트래블마트 통합'!F30)-1),'트래블마트 통합'!F30) -> WTM Africa 2026 | E27: =IF(ISNUMBER(SEARCH("★★★",'트래블마트 통합'!F30)),"★★★",IF(ISNUMBER(SEARCH("★★",'트래블마트 통합'!F30)),"★★",IF(ISNUMBER(SEARCH("★",'트래블마트 통합'!F30)),"★","-"))) -> ★ | F27: FALSE | G27: FALSE | H27: =IF(AND(F27,G27),"완료",IF(G27,"진행 완료",IF(F27,"참가 예정","미정"))) -> 미정 | I27: ='트래블마트 통합'!F30 -> WTM Africa 2026 [★ 선택] 아프리카 시장 접근
A28: ='트래블마트 통합'!F$2 -> 2026년 4월 | B28: ='트래블마트 통합'!$A31 -> 브라질 | C28: ='트래블마트 통합'!$B31 -> 상파울루 | D28: =IFERROR(LEFT('트래블마트 통합'!F31,FIND(CHAR(10),'트래블마트 통합'!F31)-1),'트래블마트 통합'!F31) -> WTM Latin America 2026 | E28: =IF(ISNUMBER(SEARCH("★★★",'트래블마트 통합'!F31)),"★★★",IF(ISNUMBER(SEARCH("★★",'트래블마트 통합'!F31)),"★★",IF(ISNUMBER(SEARCH("★",'트래블마트 통합'!F31)),"★","-"))) -> ★ | F28: FALSE | G28: FALSE | H28: =IF(AND(F28,G28),"완료",IF(G28,"진행 완료",IF(F28,"참가 예정","미정"))) -> 미정 | I28: ='트래블마트 통합'!F31 -> WTM Latin America 2026 2026년 4월 14-16일 [★ 선택] 남미 최대 B2B, 라틴 바이어 네트워크
A29: ='트래블마트 통합'!G$2 -> 2026년 5월 | B29: ='트래블마트 통합'!$A9 -> 중국 | C29: ='트래블마트 통합'!$B9 -> 광동,화동,화북,내륙 | D29: =IFERROR(LEFT('트래블마트 통합'!G9,FIND(CHAR(10),'트래블마트 통합'!G9)-1),'트래블마트 통합'!G9) -> 5/26–5/28 – ITB China | E29: =IF(ISNUMBER(SEARCH("★★★",'트래블마트 통합'!G9)),"★★★",IF(ISNUMBER(SEARCH("★★",'트래블마트 통합'!G9)),"★★",IF(ISNUMBER(SEARCH("★",'트래블마트 통합'!G9)),"★","-"))) -> ★★★ | F29: TRUE | G29: TRUE | H29: =IF(AND(F29,G29),"완료",IF(G29,"진행 완료",IF(F29,"참가 예정","미정"))) -> 완료 | I29: ='트래블마트 통합'!G9 -> 5/26–5/28 – ITB China 1차 Shanghai GITF (Guangzhou International Travel Fair) 5/21–23 [★★★ 최우선] 중국 outbound 최상위 B2B
A30: ='트래블마트 통합'!G$2 -> 2026년 5월 | B30: ='트래블마트 통합'!$A10 -> 한국 | C30: ='트래블마트 통합'!$B10 -> 서울 | D30: =IFERROR(LEFT('트래블마트 통합'!G10,FIND(CHAR(10),'트래블마트 통합'!G10)-1),'트래블마트 통합'!G10) -> 일산 트래블마트 | E30: =IF(ISNUMBER(SEARCH("★★★",'트래블마트 통합'!G10)),"★★★",IF(ISNUMBER(SEARCH("★★",'트래블마트 통합'!G10)),"★★",IF(ISNUMBER(SEARCH("★",'트래블마트 통합'!G10)),"★","-"))) -> - | F30: TRUE | G30: TRUE | H30: =IF(AND(F30,G30),"완료",IF(G30,"진행 완료",IF(F30,"참가 예정","미정"))) -> 완료 | I30: ='트래블마트 통합'!G10 -> 일산 트래블마트 5월 14~17일
A31: ='트래블마트 통합'!G$2 -> 2026년 5월 | B31: ='트래블마트 통합'!$A12 -> 대만 | C31: ='트래블마트 통합'!$B12 -> 타이베이 | D31: =IFERROR(LEFT('트래블마트 통합'!G12,FIND(CHAR(10),'트래블마트 통합'!G12)-1),'트래블마트 통합'!G12) -> 5/22–5/25 – Taipei Tourism Expo (TTE) | E31: =IF(ISNUMBER(SEARCH("★★★",'트래블마트 통합'!G12)),"★★★",IF(ISNUMBER(SEARCH("★★",'트래블마트 통합'!G12)),"★★",IF(ISNUMBER(SEARCH("★",'트래블마트 통합'!G12)),"★","-"))) -> ★ | F31: FALSE | G31: FALSE | H31: =IF(AND(F31,G31),"완료",IF(G31,"진행 완료",IF(F31,"참가 예정","미정"))) -> 미정 | I31: ='트래블마트 통합'!G12 -> 5/22–5/25 – Taipei Tourism Expo (TTE) [★ 선택] 대만 최대 B2C, FIT 시장 강함
A32: ='트래블마트 통합'!G$2 -> 2026년 5월 | B32: ='트래블마트 통합'!$A19 -> 인도네시아 | C32: ='트래블마트 통합'!$B19 -> 자카르타 | D32: =IFERROR(LEFT('트래블마트 통합'!G19,FIND(CHAR(10),'트래블마트 통합'!G19)-1),'트래블마트 통합'!G19) -> BBTF (Bali & Beyond Travel Fair) 2026 | E32: =IF(ISNUMBER(SEARCH("★★★",'트래블마트 통합'!G19)),"★★★",IF(ISNUMBER(SEARCH("★★",'트래블마트 통합'!G19)),"★★",IF(ISNUMBER(SEARCH("★",'트래블마트 통합'!G19)),"★","-"))) -> - | F32: FALSE | G32: FALSE | H32: =IF(AND(F32,G32),"완료",IF(G32,"진행 완료",IF(F32,"참가 예정","미정"))) -> 미정 | I32: ='트래블마트 통합'!G19 -> BBTF (Bali & Beyond Travel Fair) 2026 날짜: 2026년 5월 28일(목) ~ 5월 30일(토) 특징: 상반기 동남아시아 일정 중 호텔 소싱에 가장 중요한 행사
A33: ='트래블마트 통합'!G$2 -> 2026년 5월 | B33: ='트래블마트 통합'!$A22 -> UAE | C33: ='트래블마트 통합'!$B22 -> Dubai | D33: =IFERROR(LEFT('트래블마트 통합'!G22,FIND(CHAR(10),'트래블마트 통합'!G22)-1),'트래블마트 통합'!G22) -> Arabian Travel Market (ATM) 2026 | E33: =IF(ISNUMBER(SEARCH("★★★",'트래블마트 통합'!G22)),"★★★",IF(ISNUMBER(SEARCH("★★",'트래블마트 통합'!G22)),"★★",IF(ISNUMBER(SEARCH("★",'트래블마트 통합'!G22)),"★","-"))) -> ★★★ | F33: TRUE | G33: FALSE | H33: =IF(AND(F33,G33),"완료",IF(G33,"진행 완료",IF(F33,"참가 예정","미정"))) -> 참가 예정 | I33: ='트래블마트 통합'!G22 -> Arabian Travel Market (ATM) 2026 2026년 5월 4일 ~ 5월 7일 [★★★ 최우선] 중동 최대 여행 B2B, GCC 바이어 중심
A34: ='트래블마트 통합'!G$2 -> 2026년 5월 | B34: ='트래블마트 통합'!$A25 -> 호주 | C34: ='트래블마트 통합'!$B25 -> 시드니, 애들레이드 | D34: =IFERROR(LEFT('트래블마트 통합'!G25,FIND(CHAR(10),'트래블마트 통합'!G25)-1),'트래블마트 통합'!G25) -> 5/10–5/14 – Australian Tourism Exchange (ATE) | E34: =IF(ISNUMBER(SEARCH("★★★",'트래블마트 통합'!G25)),"★★★",IF(ISNUMBER(SEARCH("★★",'트래블마트 통합'!G25)),"★★",IF(ISNUMBER(SEARCH("★",'트래블마트 통합'!G25)),"★","-"))) -> ★ | F34: FALSE | G34: FALSE | H34: =IF(AND(F34,G34),"완료",IF(G34,"진행 완료",IF(F34,"참가 예정","미정"))) -> 미정 | I34: ='트래블마트 통합'!G25 -> 5/10–5/14 – Australian Tourism Exchange (ATE) [★ 선택] 오세아니아 최대 B2B
A35: ='트래블마트 통합'!G$2 -> 2026년 5월 | B35: ='트래블마트 통합'!$A28 -> 미국 | C35: ='트래블마트 통합'!$B28 -> 플로리다주 뉴욕 | D35: =IFERROR(LEFT('트래블마트 통합'!G28,FIND(CHAR(10),'트래블마트 통합'!G28)-1),'트래블마트 통합'!G28) -> IPW 2026 | E35: =IF(ISNUMBER(SEARCH("★★★",'트래블마트 통합'!G28)),"★★★",IF(ISNUMBER(SEARCH("★★",'트래블마트 통합'!G28)),"★★",IF(ISNUMBER(SEARCH("★",'트래블마트 통합'!G28)),"★","-"))) -> ★ | F35: FALSE | G35: FALSE | H35: =IF(AND(F35,G35),"완료",IF(G35,"진행 완료",IF(F35,"참가 예정","미정"))) -> 미정 | I35: ='트래블마트 통합'!G28 -> IPW 2026 2026년 5월 17-21일 [★ 선택] 미국 인바운드 최대 B2B 행사
A36: ='트래블마트 통합'!H$2 -> 2026년 6월 | B36: ='트래블마트 통합'!$A10 -> 한국 | C36: ='트래블마트 통합'!$B10 -> 서울 | D36: =IFERROR(LEFT('트래블마트 통합'!H10,FIND(CHAR(10),'트래블마트 통합'!H10)-1),'트래블마트 통합'!H10) -> 6/4–6/7 – Seoul International Travel Fair (SITF) | E36: =IF(ISNUMBER(SEARCH("★★★",'트래블마트 통합'!H10)),"★★★",IF(ISNUMBER(SEARCH("★★",'트래블마트 통합'!H10)),"★★",IF(ISNUMBER(SEARCH("★",'트래블마트 통합'!H10)),"★","-"))) -> ★ | F36: FALSE | G36: FALSE | H36: =IF(AND(F36,G36),"완료",IF(G36,"진행 완료",IF(F36,"참가 예정","미정"))) -> 미정 | I36: ='트래블마트 통합'!H10 -> 6/4–6/7 – Seoul International Travel Fair (SITF) [★ 선택] 한국 최대 여행박람회
A37: ='트래블마트 통합'!H$2 -> 2026년 6월 | B37: ='트래블마트 통합'!$A13 -> 홍콩 | C37: ='트래블마트 통합'!$B13 -> 홍콩 | D37: =IFERROR(LEFT('트래블마트 통합'!H13,FIND(CHAR(10),'트래블마트 통합'!H13)-1),'트래블마트 통합'!H13) -> ITE Hong Kong | E37: =IF(ISNUMBER(SEARCH("★★★",'트래블마트 통합'!H13)),"★★★",IF(ISNUMBER(SEARCH("★★",'트래블마트 통합'!H13)),"★★",IF(ISNUMBER(SEARCH("★",'트래블마트 통합'!H13)),"★","-"))) -> ★★ | F37: FALSE | G37: FALSE | H37: =IF(AND(F37,G37),"완료",IF(G37,"진행 완료",IF(F37,"참가 예정","미정"))) -> 미정 | I37: ='트래블마트 통합'!H13 -> ITE Hong Kong 6월 11~14일 전후 [★★ 중간] 홍콩–광둥 outbound 중심
A38: ='트래블마트 통합'!H$2 -> 2026년 6월 | B38: ='트래블마트 통합'!$A16 -> 태국 | C38: ='트래블마트 통합'!$B16 -> 방콕 | D38: =IFERROR(LEFT('트래블마트 통합'!H16,FIND(CHAR(10),'트래블마트 통합'!H16)-1),'트래블마트 통합'!H16) -> TTM+ (Thailand Travel Mart Plus) 2026 | E38: =IF(ISNUMBER(SEARCH("★★★",'트래블마트 통합'!H16)),"★★★",IF(ISNUMBER(SEARCH("★★",'트래블마트 통합'!H16)),"★★",IF(ISNUMBER(SEARCH("★",'트래블마트 통합'!H16)),"★","-"))) -> - | F38: FALSE | G38: FALSE | H38: =IF(AND(F38,G38),"완료",IF(G38,"진행 완료",IF(F38,"참가 예정","미정"))) -> 미정 | I38: ='트래블마트 통합'!H16 -> TTM+ (Thailand Travel Mart Plus) 2026 예상 날짜: 2026년 6월 중 (보통 6월 둘째 주) 장소: 미정 특징: 태국 관광청(TAT) 주관 행사
A39: ='트래블마트 통합'!H$2 -> 2026년 6월 | B39: ='트래블마트 통합'!$A18 -> 싱가포르 | C39: ='트래블마트 통합'!$B18 -> 마리나베이 | D39: =IFERROR(LEFT('트래블마트 통합'!H18,FIND(CHAR(10),'트래블마트 통합'!H18)-1),'트래블마트 통합'!H18) -> ILTM Asia Pacific 2026 | E39: =IF(ISNUMBER(SEARCH("★★★",'트래블마트 통합'!H18)),"★★★",IF(ISNUMBER(SEARCH("★★",'트래블마트 통합'!H18)),"★★",IF(ISNUMBER(SEARCH("★",'트래블마트 통합'!H18)),"★","-"))) -> ★ | F39: FALSE | G39: FALSE | H39: =IF(AND(F39,G39),"완료",IF(G39,"진행 완료",IF(F39,"참가 예정","미정"))) -> 미정 | I39: ='트래블마트 통합'!H18 -> ILTM Asia Pacific 2026 2026년 6월 29일 ~ 7월 2일 [★ 선택] 아시아 럭셔리 여행 최상위 행사
A40: ='트래블마트 통합'!H$2 -> 2026년 6월 | B40: ='트래블마트 통합'!$A19 -> 인도네시아 | C40: ='트래블마트 통합'!$B19 -> 자카르타 | D40: =IFERROR(LEFT('트래블마트 통합'!H19,FIND(CHAR(10),'트래블마트 통합'!H19)-1),'트래블마트 통합'!H19) -> Travel Meet Asia 2026 | E40: =IF(ISNUMBER(SEARCH("★★★",'트래블마트 통합'!H19)),"★★★",IF(ISNUMBER(SEARCH("★★",'트래블마트 통합'!H19)),"★★",IF(ISNUMBER(SEARCH("★",'트래블마트 통합'!H19)),"★","-"))) -> ★ | F40: TRUE | G40: TRUE | H40: =IF(AND(F40,G40),"완료",IF(G40,"진행 완료",IF(F40,"참가 예정","미정"))) -> 완료 | I40: ='트래블마트 통합'!H19 -> Travel Meet Asia 2026 2026년 6월 23-24일 [★ 선택] 아세안 B2B 네트워크 허브
A41: ='트래블마트 통합'!I$2 -> 2026년 7월 | B41: ='트래블마트 통합'!$A9 -> 중국 | C41: ='트래블마트 통합'!$B9 -> 광동,화동,화북,내륙 | D41: =IFERROR(LEFT('트래블마트 통합'!I9,FIND(CHAR(10),'트래블마트 통합'!I9)-1),'트래블마트 통합'!I9) -> 2차 세일즈 콜 | E41: =IF(ISNUMBER(SEARCH("★★★",'트래블마트 통합'!I9)),"★★★",IF(ISNUMBER(SEARCH("★★",'트래블마트 통합'!I9)),"★★",IF(ISNUMBER(SEARCH("★",'트래블마트 통합'!I9)),"★","-"))) -> - | F41: TRUE | G41: TRUE | H41: =IF(AND(F41,G41),"완료",IF(G41,"진행 완료",IF(F41,"참가 예정","미정"))) -> 완료 | I41: ='트래블마트 통합'!I9 -> 2차 세일즈 콜 심천+대만+홍콩
A42: ='트래블마트 통합'!I$2 -> 2026년 7월 | B42: ='트래블마트 통합'!$A10 -> 한국 | C42: ='트래블마트 통합'!$B10 -> 서울 | D42: =IFERROR(LEFT('트래블마트 통합'!I10,FIND(CHAR(10),'트래블마트 통합'!I10)-1),'트래블마트 통합'!I10) -> 6/30~7/1 | E42: =IF(ISNUMBER(SEARCH("★★★",'트래블마트 통합'!I10)),"★★★",IF(ISNUMBER(SEARCH("★★",'트래블마트 통합'!I10)),"★★",IF(ISNUMBER(SEARCH("★",'트래블마트 통합'!I10)),"★","-"))) -> - | F42: FALSE | G42: FALSE | H42: =IF(AND(F42,G42),"완료",IF(G42,"진행 완료",IF(F42,"참가 예정","미정"))) -> 미정 | I42: ='트래블마트 통합'!I10 -> 6/30~7/1 SITM
A43: ='트래블마트 통합'!I$2 -> 2026년 7월 | B43: ='트래블마트 통합'!$A12 -> 대만 | C43: ='트래블마트 통합'!$B12 -> 타이베이 | D43: =IFERROR(LEFT('트래블마트 통합'!I12,FIND(CHAR(10),'트래블마트 통합'!I12)-1),'트래블마트 통합'!I12) -> 2차 세일즈 콜 | E43: =IF(ISNUMBER(SEARCH("★★★",'트래블마트 통합'!I12)),"★★★",IF(ISNUMBER(SEARCH("★★",'트래블마트 통합'!I12)),"★★",IF(ISNUMBER(SEARCH("★",'트래블마트 통합'!I12)),"★","-"))) -> - | F43: TRUE | G43: TRUE | H43: =IF(AND(F43,G43),"완료",IF(G43,"진행 완료",IF(F43,"참가 예정","미정"))) -> 완료 | I43: ='트래블마트 통합'!I12 -> 2차 세일즈 콜 심천+대만+홍콩
A44: ='트래블마트 통합'!I$2 -> 2026년 7월 | B44: ='트래블마트 통합'!$A13 -> 홍콩 | C44: ='트래블마트 통합'!$B13 -> 홍콩 | D44: =IFERROR(LEFT('트래블마트 통합'!I13,FIND(CHAR(10),'트래블마트 통합'!I13)-1),'트래블마트 통합'!I13) -> 2차 세일즈 콜 | E44: =IF(ISNUMBER(SEARCH("★★★",'트래블마트 통합'!I13)),"★★★",IF(ISNUMBER(SEARCH("★★",'트래블마트 통합'!I13)),"★★",IF(ISNUMBER(SEARCH("★",'트래블마트 통합'!I13)),"★","-"))) -> - | F44: TRUE | G44: TRUE | H44: =IF(AND(F44,G44),"완료",IF(G44,"진행 완료",IF(F44,"참가 예정","미정"))) -> 완료 | I44: ='트래블마트 통합'!I13 -> 2차 세일즈 콜 심천+대만+홍콩
A45: ='트래블마트 통합'!I$2 -> 2026년 7월 | B45: ='트래블마트 통합'!$A14 -> 필리핀 | C45: ='트래블마트 통합'!$B14 -> 세부, 마닐라 | D45: =IFERROR(LEFT('트래블마트 통합'!I14,FIND(CHAR(10),'트래블마트 통합'!I14)-1),'트래블마트 통합'!I14) -> Travel Madness Expo 2026 | E45: =IF(ISNUMBER(SEARCH("★★★",'트래블마트 통합'!I14)),"★★★",IF(ISNUMBER(SEARCH("★★",'트래블마트 통합'!I14)),"★★",IF(ISNUMBER(SEARCH("★",'트래블마트 통합'!I14)),"★","-"))) -> - | F45: TRUE | G45: TRUE | H45: =IF(AND(F45,G45),"완료",IF(G45,"진행 완료",IF(F45,"참가 예정","미정"))) -> 완료 | I45: ='트래블마트 통합'!I14 -> Travel Madness Expo 2026 July 10 to 12, 2026
A46: ='트래블마트 통합'!J$2 -> 2026년 8월 | B46: ='트래블마트 통합'!$A10 -> 한국 | C46: ='트래블마트 통합'!$B10 -> 서울 | D46: =IFERROR(LEFT('트래블마트 통합'!J10,FIND(CHAR(10),'트래블마트 통합'!J10)-1),'트래블마트 통합'!J10) -> 한국 세일즈콜 | E46: =IF(ISNUMBER(SEARCH("★★★",'트래블마트 통합'!J10)),"★★★",IF(ISNUMBER(SEARCH("★★",'트래블마트 통합'!J10)),"★★",IF(ISNUMBER(SEARCH("★",'트래블마트 통합'!J10)),"★","-"))) -> - | F46: TRUE | G46: TRUE | H46: =IF(AND(F46,G46),"완료",IF(G46,"진행 완료",IF(F46,"참가 예정","미정"))) -> 완료 | I46: ='트래블마트 통합'!J10 -> 한국 세일즈콜 8월3~7일
A47: ='트래블마트 통합'!J$2 -> 2026년 8월 | B47: ='트래블마트 통합'!$A17 -> 말레이시아 | C47: ='트래블마트 통합'!$B17 -> 쿠알라룸프르, 쿠칭 | D47: =IFERROR(LEFT('트래블마트 통합'!J17,FIND(CHAR(10),'트래블마트 통합'!J17)-1),'트래블마트 통합'!J17) -> 8/18–8/20 – PATA Travel Mart | E47: =IF(ISNUMBER(SEARCH("★★★",'트래블마트 통합'!J17)),"★★★",IF(ISNUMBER(SEARCH("★★",'트래블마트 통합'!J17)),"★★",IF(ISNUMBER(SEARCH("★",'트래블마트 통합'!J17)),"★","-"))) -> ★★ | F47: FALSE | G47: FALSE | H47: =IF(AND(F47,G47),"완료",IF(G47,"진행 완료",IF(F47,"참가 예정","미정"))) -> 미정 | I47: ='트래블마트 통합'!J17 -> 8/18–8/20 – PATA Travel Mart [★★ 중간] 아시아·태평양 대표 B2B
A48: ='트래블마트 통합'!J$2 -> 2026년 8월 | B48: ='트래블마트 통합'!$A18 -> 싱가포르 | C48: 싱가포르 | D48: =IFERROR(LEFT('트래블마트 통합'!J18,FIND(CHAR(10),'트래블마트 통합'!J18)-1),'트래블마트 통합'!J18) -> NATAS (2026년 8월 21~23일) | E48: =IF(ISNUMBER(SEARCH("★★★",'트래블마트 통합'!J18)),"★★★",IF(ISNUMBER(SEARCH("★★",'트래블마트 통합'!J18)),"★★",IF(ISNUMBER(SEARCH("★",'트래블마트 통합'!J18)),"★","-"))) -> - | F48: TRUE | G48: FALSE | H48: =IF(AND(F48,G48),"완료",IF(G48,"진행 완료",IF(F48,"참가 예정","미정"))) -> 참가 예정 | I48: ='트래블마트 통합'!J18 -> NATAS (2026년 8월 21~23일)
A49: ='트래블마트 통합'!K$2 -> 2026년 9월 | B49: ='트래블마트 통합'!$A9 -> 중국 | C49: ='트래블마트 통합'!$B9 -> 광동,화동,화북,내륙 | D49: =IFERROR(LEFT('트래블마트 통합'!K9,FIND(CHAR(10),'트래블마트 통합'!K9)-1),'트래블마트 통합'!K9) -> 2차 광저우, 심천 | E49: =IF(ISNUMBER(SEARCH("★★★",'트래블마트 통합'!K9)),"★★★",IF(ISNUMBER(SEARCH("★★",'트래블마트 통합'!K9)),"★★",IF(ISNUMBER(SEARCH("★",'트래블마트 통합'!K9)),"★","-"))) -> - | F49: FALSE | G49: FALSE | H49: =IF(AND(F49,G49),"완료",IF(G49,"진행 완료",IF(F49,"참가 예정","미정"))) -> 미정 | I49: ='트래블마트 통합'!K9 -> 2차 광저우, 심천
A50: ='트래블마트 통합'!K$2 -> 2026년 9월 | B50: ='트래블마트 통합'!$A11 -> 일본 | C50: ='트래블마트 통합'!$B11 -> (순환개최) | D50: =IFERROR(LEFT('트래블마트 통합'!K11,FIND(CHAR(10),'트래블마트 통합'!K11)-1),'트래블마트 통합'!K11) -> 9/24–9/27 – Tourism EXPO Japan (TEJ) | E50: =IF(ISNUMBER(SEARCH("★★★",'트래블마트 통합'!K11)),"★★★",IF(ISNUMBER(SEARCH("★★",'트래블마트 통합'!K11)),"★★",IF(ISNUMBER(SEARCH("★",'트래블마트 통합'!K11)),"★","-"))) -> ★★ | F50: FALSE | G50: FALSE | H50: =IF(AND(F50,G50),"완료",IF(G50,"진행 완료",IF(F50,"참가 예정","미정"))) -> 미정 | I50: ='트래블마트 통합'!K11 -> 9/24–9/27 – Tourism EXPO Japan (TEJ) [★★ 중간] 일본 최대 종합 트래블쇼
A51: ='트래블마트 통합'!K$2 -> 2026년 9월 | B51: ='트래블마트 통합'!$A13 -> 홍콩 | C51: ='트래블마트 통합'!$B13 -> 홍콩 | D51: =IFERROR(LEFT('트래블마트 통합'!K13,FIND(CHAR(10),'트래블마트 통합'!K13)-1),'트래블마트 통합'!K13) -> 2차 세일즈 콜 | E51: =IF(ISNUMBER(SEARCH("★★★",'트래블마트 통합'!K13)),"★★★",IF(ISNUMBER(SEARCH("★★",'트래블마트 통합'!K13)),"★★",IF(ISNUMBER(SEARCH("★",'트래블마트 통합'!K13)),"★","-"))) -> - | F51: FALSE | G51: FALSE | H51: =IF(AND(F51,G51),"완료",IF(G51,"진행 완료",IF(F51,"참가 예정","미정"))) -> 미정 | I51: ='트래블마트 통합'!K13 -> 2차 세일즈 콜 대만+홍콩
A52: ='트래블마트 통합'!K$2 -> 2026년 9월 | B52: ='트래블마트 통합'!$A17 -> 말레이시아 | C52: ='트래블마트 통합'!$B17 -> 쿠알라룸프르, 쿠칭 | D52: =IFERROR(LEFT('트래블마트 통합'!K17,FIND(CHAR(10),'트래블마트 통합'!K17)-1),'트래블마트 통합'!K17) -> MATTA Fair | E52: =IF(ISNUMBER(SEARCH("★★★",'트래블마트 통합'!K17)),"★★★",IF(ISNUMBER(SEARCH("★★",'트래블마트 통합'!K17)),"★★",IF(ISNUMBER(SEARCH("★",'트래블마트 통합'!K17)),"★","-"))) -> ★ | F52: FALSE | G52: FALSE | H52: =IF(AND(F52,G52),"완료",IF(G52,"진행 완료",IF(F52,"참가 예정","미정"))) -> 미정 | I52: ='트래블마트 통합'!K17 -> MATTA Fair [★ 선택] 말레이시아 최대 B2C
A53: ='트래블마트 통합'!K$2 -> 2026년 9월 | B53: ='트래블마트 통합'!$A20 -> 인도 | C53: ='트래블마트 통합'!$B20 -> 뭄바이 뉴델리 | D53: =IFERROR(LEFT('트래블마트 통합'!K20,FIND(CHAR(10),'트래블마트 통합'!K20)-1),'트래블마트 통합'!K20) -> 9/2–9/4 – ITB India | E53: =IF(ISNUMBER(SEARCH("★★★",'트래블마트 통합'!K20)),"★★★",IF(ISNUMBER(SEARCH("★★",'트래블마트 통합'!K20)),"★★",IF(ISNUMBER(SEARCH("★",'트래블마트 통합'!K20)),"★","-"))) -> ★★★ | F53: TRUE | G53: TRUE | H53: =IF(AND(F53,G53),"완료",IF(G53,"진행 완료",IF(F53,"참가 예정","미정"))) -> 완료 | I53: ='트래블마트 통합'!K20 -> 9/2–9/4 – ITB India [★★★ 최우선] 인도 outbound 핵심
A54: ='트래블마트 통합'!K$2 -> 2026년 9월 | B54: ='트래블마트 통합'!$A21 -> 러시아 | C54: ='트래블마트 통합'!$B21 -> 모스크바 | D54: =IFERROR(LEFT('트래블마트 통합'!K21,FIND(CHAR(10),'트래블마트 통합'!K21)-1),'트래블마트 통합'!K21) -> OTDYKH Leisure Travel Market 2026 | E54: =IF(ISNUMBER(SEARCH("★★★",'트래블마트 통합'!K21)),"★★★",IF(ISNUMBER(SEARCH("★★",'트래블마트 통합'!K21)),"★★",IF(ISNUMBER(SEARCH("★",'트래블마트 통합'!K21)),"★","-"))) -> ★ | F54: FALSE | G54: FALSE | H54: =IF(AND(F54,G54),"완료",IF(G54,"진행 완료",IF(F54,"참가 예정","미정"))) -> 미정 | I54: ='트래블마트 통합'!K21 -> OTDYKH Leisure Travel Market 2026 2026년 9월 10일 ~ 9월 12일 [★ 선택] 러시아 인바운드·아웃바운드 모두 강함
A55: ='트래블마트 통합'!L$2 -> 2026년 10월 | B55: ='트래블마트 통합'!$A9 -> 중국 | C55: ='트래블마트 통합'!$B9 -> 광동,화동,화북,내륙 | D55: =IFERROR(LEFT('트래블마트 통합'!L9,FIND(CHAR(10),'트래블마트 통합'!L9)-1),'트래블마트 통합'!L9) -> 1차 세일즈 콜 | E55: =IF(ISNUMBER(SEARCH("★★★",'트래블마트 통합'!L9)),"★★★",IF(ISNUMBER(SEARCH("★★",'트래블마트 통합'!L9)),"★★",IF(ISNUMBER(SEARCH("★",'트래블마트 통합'!L9)),"★","-"))) -> - | F55: FALSE | G55: FALSE | H55: =IF(AND(F55,G55),"완료",IF(G55,"진행 완료",IF(F55,"참가 예정","미정"))) -> 미정 | I55: ='트래블마트 통합'!L9 -> 1차 세일즈 콜 청두, 시안, 무한 CITIE Tourism Expo 2026 Guangzhou China (September 11-13) 2026 CHINA OUTBOUND & INBOUND TRAVEL MARKET 10/14–16 (베이징)
A56: ='트래블마트 통합'!L$2 -> 2026년 10월 | B56: ='트래블마트 통합'!$A15 -> 베트남 | C56: ='트래블마트 통합'!$B15 -> 호치민 하노이 | D56: =IFERROR(LEFT('트래블마트 통합'!L15,FIND(CHAR(10),'트래블마트 통합'!L15)-1),'트래블마트 통합'!L15) -> ITE HCMC | E56: =IF(ISNUMBER(SEARCH("★★★",'트래블마트 통합'!L15)),"★★★",IF(ISNUMBER(SEARCH("★★",'트래블마트 통합'!L15)),"★★",IF(ISNUMBER(SEARCH("★",'트래블마트 통합'!L15)),"★","-"))) -> ★★ | F56: TRUE | G56: FALSE | H56: =IF(AND(F56,G56),"완료",IF(G56,"진행 완료",IF(F56,"참가 예정","미정"))) -> 참가 예정 | I56: ='트래블마트 통합'!L15 -> ITE HCMC 16~18 Oct [★★ 중간] 메콩 최대 B2B+B2C (Calendar 기준 9/3–9/5)
A57: ='트래블마트 통합'!L$2 -> 2026년 10월 | B57: ='트래블마트 통합'!$A16 -> 태국 | C57: ='트래블마트 통합'!$B16 -> 방콕 | D57: =IFERROR(LEFT('트래블마트 통합'!L16,FIND(CHAR(10),'트래블마트 통합'!L16)-1),'트래블마트 통합'!L16) -> Visit Japan FIT Fair #17 | E57: =IF(ISNUMBER(SEARCH("★★★",'트래블마트 통합'!L17)),"★★★",IF(ISNUMBER(SEARCH("★★",'트래블마트 통합'!L17)),"★★",IF(ISNUMBER(SEARCH("★",'트래블마트 통합'!L17)),"★","-"))) -> - | F57: TRUE | G57: FALSE | H57: =IF(AND(F57,G57),"완료",IF(G57,"진행 완료",IF(F57,"참가 예정","미정"))) -> 참가 예정 | I57: ='트래블마트 통합'!L16 -> Visit Japan FIT Fair #17 올해 10월16~18일 개최
A58: ='트래블마트 통합'!L$2 -> 2026년 10월 | B58: ='트래블마트 통합'!$A18 -> 싱가포르 | C58: ='트래블마트 통합'!$B18 -> 마리나베이 | D58: =IFERROR(LEFT('트래블마트 통합'!L18,FIND(CHAR(10),'트래블마트 통합'!L18)-1),'트래블마트 통합'!L18) -> 10/21–10/23 – ITB Asia | E58: =IF(ISNUMBER(SEARCH("★★★",'트래블마트 통합'!L18)),"★★★",IF(ISNUMBER(SEARCH("★★",'트래블마트 통합'!L18)),"★★",IF(ISNUMBER(SEARCH("★",'트래블마트 통합'!L18)),"★","-"))) -> ★★★ | F58: TRUE | G58: FALSE | H58: =IF(AND(F58,G58),"완료",IF(G58,"진행 완료",IF(F58,"참가 예정","미정"))) -> 참가 예정 | I58: ='트래블마트 통합'!L18 -> 10/21–10/23 – ITB Asia [★★★ 최우선] 아시아 No.1 B2B 허브
A59: ='트래블마트 통합'!L$2 -> 2026년 10월 | B59: ='트래블마트 통합'!$A20 -> 인도 | C59: ='트래블마트 통합'!$B20 -> 뭄바이 뉴델리 | D59: =IFERROR(LEFT('트래블마트 통합'!L20,FIND(CHAR(10),'트래블마트 통합'!L20)-1),'트래블마트 통합'!L20) -> South Asia Travel & Tourism Exchange | E59: =IF(ISNUMBER(SEARCH("★★★",'트래블마트 통합'!L20)),"★★★",IF(ISNUMBER(SEARCH("★★",'트래블마트 통합'!L20)),"★★",IF(ISNUMBER(SEARCH("★",'트래블마트 통합'!L20)),"★","-"))) -> - | F59: FALSE | G59: FALSE | H59: =IF(AND(F59,G59),"완료",IF(G59,"진행 완료",IF(F59,"참가 예정","미정"))) -> 미정 | I59: ='트래블마트 통합'!L20 -> South Asia Travel & Tourism Exchange
A60: ='트래블마트 통합'!L$2 -> 2026년 10월 | B60: ='트래블마트 통합'!$A25 -> 호주 | C60: ='트래블마트 통합'!$B25 -> 시드니, 애들레이드 | D60: =IFERROR(LEFT('트래블마트 통합'!L25,FIND(CHAR(10),'트래블마트 통합'!L25)-1),'트래블마트 통합'!L25) -> Luxperience | E60: =IF(ISNUMBER(SEARCH("★★★",'트래블마트 통합'!L25)),"★★★",IF(ISNUMBER(SEARCH("★★",'트래블마트 통합'!L25)),"★★",IF(ISNUMBER(SEARCH("★",'트래블마트 통합'!L25)),"★","-"))) -> - | F60: FALSE | G60: FALSE | H60: =IF(AND(F60,G60),"완료",IF(G60,"진행 완료",IF(F60,"참가 예정","미정"))) -> 미정 | I60: ='트래블마트 통합'!L25 -> Luxperience
A61: ='트래블마트 통합'!L$2 -> 2026년 10월 | B61: ='트래블마트 통합'!$A28 -> 미국 | C61: ='트래블마트 통합'!$B28 -> 플로리다주 뉴욕 | D61: =IFERROR(LEFT('트래블마트 통합'!L28,FIND(CHAR(10),'트래블마트 통합'!L28)-1),'트래블마트 통합'!L28) -> Business Travel Show America 2026 | E61: =IF(ISNUMBER(SEARCH("★★★",'트래블마트 통합'!L28)),"★★★",IF(ISNUMBER(SEARCH("★★",'트래블마트 통합'!L28)),"★★",IF(ISNUMBER(SEARCH("★",'트래블마트 통합'!L28)),"★","-"))) -> ★ | F61: FALSE | G61: FALSE | H61: =IF(AND(F61,G61),"완료",IF(G61,"진행 완료",IF(F61,"참가 예정","미정"))) -> 미정 | I61: ='트래블마트 통합'!L28 -> Business Travel Show America 2026 2026년 10월 14-15일 [★ 선택] 북미 코퍼레이트 트래블 대표 행사
A62: ='트래블마트 통합'!M$2 -> 2026년 11월 | B62: ='트래블마트 통합'!$A9 -> 중국 | C62: ='트래블마트 통합'!$B9 -> 광동,화동,화북,내륙 | D62: =IFERROR(LEFT('트래블마트 통합'!M9,FIND(CHAR(10),'트래블마트 통합'!M9)-1),'트래블마트 통합'!M9) -> 2차 베이징 | E62: =IF(ISNUMBER(SEARCH("★★★",'트래블마트 통합'!M9)),"★★★",IF(ISNUMBER(SEARCH("★★",'트래블마트 통합'!M9)),"★★",IF(ISNUMBER(SEARCH("★",'트래블마트 통합'!M9)),"★","-"))) -> - | F62: FALSE | G62: FALSE | H62: =IF(AND(F62,G62),"완료",IF(G62,"진행 완료",IF(F62,"참가 예정","미정"))) -> 미정 | I62: ='트래블마트 통합'!M9 -> 2차 베이징 국경절 1~7일 COITM from 14-16 October in Beijing
A63: ='트래블마트 통합'!M$2 -> 2026년 11월 | B63: ='트래블마트 통합'!$A10 -> 한국 | C63: ='트래블마트 통합'!$B10 -> 서울 | D63: =IFERROR(LEFT('트래블마트 통합'!M10,FIND(CHAR(10),'트래블마트 통합'!M10)-1),'트래블마트 통합'!M10) -> Travel Show | E63: =IF(ISNUMBER(SEARCH("★★★",'트래블마트 통합'!M10)),"★★★",IF(ISNUMBER(SEARCH("★★",'트래블마트 통합'!M10)),"★★",IF(ISNUMBER(SEARCH("★",'트래블마트 통합'!M10)),"★","-"))) -> ★ | F63: TRUE | G63: FALSE | H63: =IF(AND(F63,G63),"완료",IF(G63,"진행 완료",IF(F63,"참가 예정","미정"))) -> 참가 예정 | I63: ='트래블마트 통합'!M10 -> Travel Show 11월 12~15일 Korea MICE Expo (KME) 11/18–11/20 [★ 선택] 한국 MICE 대표 행사
A64: ='트래블마트 통합'!M$2 -> 2026년 11월 | B64: ='트래블마트 통합'!$A12 -> 대만 | C64: ='트래블마트 통합'!$B12 -> 타이베이 | D64: =IFERROR(LEFT('트래블마트 통합'!M12,FIND(CHAR(10),'트래블마트 통합'!M12)-1),'트래블마트 통합'!M12) -> ITF Taiwan International Travel Fair (ITF) 11월 6일 (금) ~ 11월 9일(월) | E64: =IF(ISNUMBER(SEARCH("★★★",'트래블마트 통합'!M12)),"★★★",IF(ISNUMBER(SEARCH("★★",'트래블마트 통합'!M12)),"★★",IF(ISNUMBER(SEARCH("★",'트래블마트 통합'!M12)),"★","-"))) -> - | F64: FALSE | G64: FALSE | H64: =IF(AND(F64,G64),"완료",IF(G64,"진행 완료",IF(F64,"참가 예정","미정"))) -> 미정 | I64: ='트래블마트 통합'!M12 -> ITF Taiwan International Travel Fair (ITF) 11월 6일 (금) ~ 11월 9일(월)
A65: ='트래블마트 통합'!M$2 -> 2026년 11월 | B65: ='트래블마트 통합'!$A26 -> 영국 | C65: ='트래블마트 통합'!$B26 -> 런던 | D65: =IFERROR(LEFT('트래블마트 통합'!M26,FIND(CHAR(10),'트래블마트 통합'!M26)-1),'트래블마트 통합'!M26) -> WTM London 2026 | E65: =IF(ISNUMBER(SEARCH("★★★",'트래블마트 통합'!M26)),"★★★",IF(ISNUMBER(SEARCH("★★",'트래블마트 통합'!M26)),"★★",IF(ISNUMBER(SEARCH("★",'트래블마트 통합'!M26)),"★","-"))) -> ★★★ | F65: FALSE | G65: FALSE | H65: =IF(AND(F65,G65),"완료",IF(G65,"진행 완료",IF(F65,"참가 예정","미정"))) -> 미정 | I65: ='트래블마트 통합'!M26 -> WTM London 2026 2026.11.04 – 11.06 [★★★ 최우선] 글로벌 레저, 기술, 지속가능성
A66: ='트래블마트 통합'!M$2 -> 2026년 11월 | B66: ='트래블마트 통합'!$A29 -> 멕시코 | C66: ='트래블마트 통합'!$B29 -> 과달라하라 | D66: =IFERROR(LEFT('트래블마트 통합'!M29,FIND(CHAR(10),'트래블마트 통합'!M29)-1),'트래블마트 통합'!M29) -> ITB Americas 2026 | E66: =IF(ISNUMBER(SEARCH("★★★",'트래블마트 통합'!M29)),"★★★",IF(ISNUMBER(SEARCH("★★",'트래블마트 통합'!M29)),"★★",IF(ISNUMBER(SEARCH("★",'트래블마트 통합'!M29)),"★","-"))) -> ★ | F66: FALSE | G66: FALSE | H66: =IF(AND(F66,G66),"완료",IF(G66,"진행 완료",IF(F66,"참가 예정","미정"))) -> 미정 | I66: ='트래블마트 통합'!M29 -> ITB Americas 2026 2026년 11월 10-12일 [★ 선택] 미주 전역 바이어 연결 허브
A67: ='트래블마트 통합'!N$2 -> 2026년 12월 | B67: ='트래블마트 통합'!$A9 -> 중국 | C67: ='트래블마트 통합'!$B9 -> 광동,화동,화북,내륙 | D67: =IFERROR(LEFT('트래블마트 통합'!N9,FIND(CHAR(10),'트래블마트 통합'!N9)-1),'트래블마트 통합'!N9) -> 2차 상하이 | E67: =IF(ISNUMBER(SEARCH("★★★",'트래블마트 통합'!N9)),"★★★",IF(ISNUMBER(SEARCH("★★",'트래블마트 통합'!N9)),"★★",IF(ISNUMBER(SEARCH("★",'트래블마트 통합'!N9)),"★","-"))) -> - | F67: FALSE | G67: FALSE | H67: =IF(AND(F67,G67),"완료",IF(G67,"진행 완료",IF(F67,"참가 예정","미정"))) -> 미정 | I67: ='트래블마트 통합'!N9 -> 2차 상하이
A68: ='트래블마트 통합'!O$2 -> 2027년 1월 | B68: ='트래블마트 통합'!$A14 -> 필리핀 | C68: ='트래블마트 통합'!$B14 -> 세부, 마닐라 | D68: =IFERROR(LEFT('트래블마트 통합'!O14,FIND(CHAR(10),'트래블마트 통합'!O14)-1),'트래블마트 통합'!O14) -> ASEAN Tourism Forum + TRAVEX 2027 | E68: =IF(ISNUMBER(SEARCH("★★★",'트래블마트 통합'!O14)),"★★★",IF(ISNUMBER(SEARCH("★★",'트래블마트 통합'!O14)),"★★",IF(ISNUMBER(SEARCH("★",'트래블마트 통합'!O14)),"★","-"))) -> ★★ | F68: FALSE | G68: FALSE | H68: =IF(AND(F68,G68),"완료",IF(G68,"진행 완료",IF(F68,"참가 예정","미정"))) -> 미정 | I68: ='트래블마트 통합'!O14 -> ASEAN Tourism Forum + TRAVEX 2027 1월 하순 (예상, 개최국 순회) [★★ 중간] ASEAN 10개국 공식 B2B, 관광청 네트워킹
A69: ='트래블마트 통합'!O$2 -> 2027년 1월 | B69: ='트래블마트 통합'!$A16 -> 태국 | C69: ='트래블마트 통합'!$B16 -> 방콕 | D69: =IFERROR(LEFT('트래블마트 통합'!O16,FIND(CHAR(10),'트래블마트 통합'!O16)-1),'트래블마트 통합'!O16) -> Thai International Travel Fair 2027 | E69: =IF(ISNUMBER(SEARCH("★★★",'트래블마트 통합'!O16)),"★★★",IF(ISNUMBER(SEARCH("★★",'트래블마트 통합'!O16)),"★★",IF(ISNUMBER(SEARCH("★",'트래블마트 통합'!O16)),"★","-"))) -> ★★★ | F69: FALSE | G69: FALSE | H69: =IF(AND(F69,G69),"완료",IF(G69,"진행 완료",IF(F69,"참가 예정","미정"))) -> 미정 | I69: ='트래블마트 통합'!O16 -> Thai International Travel Fair 2027 1월 하순 (예상) [★★★ 최우선] 태국 최대 B2B+B2C
A70: ='트래블마트 통합'!O$2 -> 2027년 1월 | B70: ='트래블마트 통합'!$A27 -> 스페인 | C70: ='트래블마트 통합'!$B27 -> 마드리드 | D70: =IFERROR(LEFT('트래블마트 통합'!O27,FIND(CHAR(10),'트래블마트 통합'!O27)-1),'트래블마트 통합'!O27) -> FITUR Madrid 2027 | E70: =IF(ISNUMBER(SEARCH("★★★",'트래블마트 통합'!O27)),"★★★",IF(ISNUMBER(SEARCH("★★",'트래블마트 통합'!O27)),"★★",IF(ISNUMBER(SEARCH("★",'트래블마트 통합'!O27)),"★","-"))) -> ★★ | F70: TRUE | G70: FALSE | H70: =IF(AND(F70,G70),"완료",IF(G70,"진행 완료",IF(F70,"참가 예정","미정"))) -> 참가 예정 | I70: ='트래블마트 통합'!O27 -> FITUR Madrid 2027 1월 하순 (예상, 통상 1/20~1/24) [★★ 중간] 세계 3대 관광박람회, 유럽·라틴 핵심
A71: ='트래블마트 통합'!O$2 -> 2027년 1월 | B71: ='트래블마트 통합'!$A28 -> 미국 | C71: ='트래블마트 통합'!$B28 -> 플로리다주 뉴욕 | D71: =IFERROR(LEFT('트래블마트 통합'!O28,FIND(CHAR(10),'트래블마트 통합'!O28)-1),'트래블마트 통합'!O28) -> New York Times Travel Show 2027 | E71: =IF(ISNUMBER(SEARCH("★★★",'트래블마트 통합'!O28)),"★★★",IF(ISNUMBER(SEARCH("★★",'트래블마트 통합'!O28)),"★★",IF(ISNUMBER(SEARCH("★",'트래블마트 통합'!O28)),"★","-"))) -> - | F71: FALSE | G71: FALSE | H71: =IF(AND(F71,G71),"완료",IF(G71,"진행 완료",IF(F71,"참가 예정","미정"))) -> 미정 | I71: ='트래블마트 통합'!O28 -> New York Times Travel Show 2027 1월 하순 (예상)
A72: ='트래블마트 통합'!P$2 -> 2027년 2월 | B72: ='트래블마트 통합'!$A9 -> 중국 | C72: ='트래블마트 통합'!$B9 -> 광동,화동,화북,내륙 | D72: =IFERROR(LEFT('트래블마트 통합'!P9,FIND(CHAR(10),'트래블마트 통합'!P9)-1),'트래블마트 통합'!P9) -> Chinese New Year (2/6) | E72: =IF(ISNUMBER(SEARCH("★★★",'트래블마트 통합'!P9)),"★★★",IF(ISNUMBER(SEARCH("★★",'트래블마트 통합'!P9)),"★★",IF(ISNUMBER(SEARCH("★",'트래블마트 통합'!P9)),"★","-"))) -> - | F72: FALSE | G72: FALSE | H72: =IF(AND(F72,G72),"완료",IF(G72,"진행 완료",IF(F72,"참가 예정","미정"))) -> 미정 | I72: ='트래블마트 통합'!P9 -> Chinese New Year (2/6)
A73: ='트래블마트 통합'!P$2 -> 2027년 2월 | B73: ='트래블마트 통합'!$A14 -> 필리핀 | C73: ='트래블마트 통합'!$B14 -> 세부, 마닐라 | D73: =IFERROR(LEFT('트래블마트 통합'!P14,FIND(CHAR(10),'트래블마트 통합'!P14)-1),'트래블마트 통합'!P14) -> PTAA TravelTour Expo 2027 | E73: =IF(ISNUMBER(SEARCH("★★★",'트래블마트 통합'!P14)),"★★★",IF(ISNUMBER(SEARCH("★★",'트래블마트 통합'!P14)),"★★",IF(ISNUMBER(SEARCH("★",'트래블마트 통합'!P14)),"★","-"))) -> ★★★ | F73: FALSE | G73: FALSE | H73: =IF(AND(F73,G73),"완료",IF(G73,"진행 완료",IF(F73,"참가 예정","미정"))) -> 미정 | I73: ='트래블마트 통합'!P14 -> PTAA TravelTour Expo 2027 2월 중 (예상) [★★★ 최우선] 필리핀 최대 소비자+B2B, 패키지 판매에 최적
A74: ='트래블마트 통합'!P$2 -> 2027년 2월 | B74: ='트래블마트 통합'!$A20 -> 인도 | C74: ='트래블마트 통합'!$B20 -> 뭄바이 뉴델리 | D74: =IFERROR(LEFT('트래블마트 통합'!P20,FIND(CHAR(10),'트래블마트 통합'!P20)-1),'트래블마트 통합'!P20) -> OTM Mumbai 2027 (Outbound Travel Mart) | E74: =IF(ISNUMBER(SEARCH("★★★",'트래블마트 통합'!P20)),"★★★",IF(ISNUMBER(SEARCH("★★",'트래블마트 통합'!P20)),"★★",IF(ISNUMBER(SEARCH("★",'트래블마트 통합'!P20)),"★","-"))) -> ★★ | F74: FALSE | G74: FALSE | H74: =IF(AND(F74,G74),"완료",IF(G74,"진행 완료",IF(F74,"참가 예정","미정"))) -> 미정 | I74: ='트래블마트 통합'!P20 -> OTM Mumbai 2027 (Outbound Travel Mart) 2월 상순 (예상) SATTE 2027 (뉴델리) 2월 하순 (예상) [★★ 중간] 인도 아웃바운드 핵심
A75: ='트래블마트 통합'!Q$2 -> 2027년 3월 | B75: ='트래블마트 통합'!$A16 -> 태국 | C75: ='트래블마트 통합'!$B16 -> 방콕 | D75: =IFERROR(LEFT('트래블마트 통합'!Q16,FIND(CHAR(10),'트래블마트 통합'!Q16)-1),'트래블마트 통합'!Q16) -> Thai Teaw Thai (B2C) | E75: =IF(ISNUMBER(SEARCH("★★★",'트래블마트 통합'!Q16)),"★★★",IF(ISNUMBER(SEARCH("★★",'트래블마트 통합'!Q16)),"★★",IF(ISNUMBER(SEARCH("★",'트래블마트 통합'!Q16)),"★","-"))) -> - | F75: FALSE | G75: FALSE | H75: =IF(AND(F75,G75),"완료",IF(G75,"진행 완료",IF(F75,"참가 예정","미정"))) -> 미정 | I75: ='트래블마트 통합'!Q16 -> Thai Teaw Thai (B2C) 3월 상순 (예상)
A76: ='트래블마트 통합'!Q$2 -> 2027년 3월 | B76: ='트래블마트 통합'!$A17 -> 말레이시아 | C76: ='트래블마트 통합'!$B17 -> 쿠알라룸프르, 쿠칭 | D76: =IFERROR(LEFT('트래블마트 통합'!Q17,FIND(CHAR(10),'트래블마트 통합'!Q17)-1),'트래블마트 통합'!Q17) -> MATTA Fair 2027 (상반기) | E76: =IF(ISNUMBER(SEARCH("★★★",'트래블마트 통합'!Q17)),"★★★",IF(ISNUMBER(SEARCH("★★",'트래블마트 통합'!Q17)),"★★",IF(ISNUMBER(SEARCH("★",'트래블마트 통합'!Q17)),"★","-"))) -> ★ | F76: FALSE | G76: FALSE | H76: =IF(AND(F76,G76),"완료",IF(G76,"진행 완료",IF(F76,"참가 예정","미정"))) -> 미정 | I76: ='트래블마트 통합'!Q17 -> MATTA Fair 2027 (상반기) 3월 말~4월 초 (예상) [★ 선택] 말레이시아 최대 B2C
A77: ='트래블마트 통합'!Q$2 -> 2027년 3월 | B77: ='트래블마트 통합'!$A21 -> 러시아 | C77: ='트래블마트 통합'!$B21 -> 모스크바 | D77: =IFERROR(LEFT('트래블마트 통합'!Q21,FIND(CHAR(10),'트래블마트 통합'!Q21)-1),'트래블마트 통합'!Q21) -> MITT Moscow 2027 | E77: =IF(ISNUMBER(SEARCH("★★★",'트래블마트 통합'!Q21)),"★★★",IF(ISNUMBER(SEARCH("★★",'트래블마트 통합'!Q21)),"★★",IF(ISNUMBER(SEARCH("★",'트래블마트 통합'!Q21)),"★","-"))) -> ★★ | F77: FALSE | G77: FALSE | H77: =IF(AND(F77,G77),"완료",IF(G77,"진행 완료",IF(F77,"참가 예정","미정"))) -> 미정 | I77: ='트래블마트 통합'!Q21 -> MITT Moscow 2027 3월 중 (예상) [★★ 중간] 러시아·CIS 최대, 러시아 outbound 핵심
A78: ='트래블마트 통합'!Q$2 -> 2027년 3월 | B78: ='트래블마트 통합'!$A23 -> Qatar | C78: ='트래블마트 통합'!$B23 -> Doha | D78: =IFERROR(LEFT('트래블마트 통합'!Q23,FIND(CHAR(10),'트래블마트 통합'!Q23)-1),'트래블마트 통합'!Q23) -> Connections Luxury Middle East 2027 | E78: =IF(ISNUMBER(SEARCH("★★★",'트래블마트 통합'!Q23)),"★★★",IF(ISNUMBER(SEARCH("★★",'트래블마트 통합'!Q23)),"★★",IF(ISNUMBER(SEARCH("★",'트래블마트 통합'!Q23)),"★","-"))) -> ★ | F78: FALSE | G78: FALSE | H78: =IF(AND(F78,G78),"완료",IF(G78,"진행 완료",IF(F78,"참가 예정","미정"))) -> 미정 | I78: ='트래블마트 통합'!Q23 -> Connections Luxury Middle East 2027 3월 말~4월 초 (예상) [★ 선택] 초럭셔리 바이어 행사
A79: ='트래블마트 통합'!Q$2 -> 2027년 3월 | B79: ='트래블마트 통합'!$A24 -> 독일 | C79: ='트래블마트 통합'!$B24 -> 베를린 오버하우젠 | D79: =IFERROR(LEFT('트래블마트 통합'!Q24,FIND(CHAR(10),'트래블마트 통합'!Q24)-1),'트래블마트 통합'!Q24) -> ITB Berlin 2027 | E79: =IF(ISNUMBER(SEARCH("★★★",'트래블마트 통합'!Q24)),"★★★",IF(ISNUMBER(SEARCH("★★",'트래블마트 통합'!Q24)),"★★",IF(ISNUMBER(SEARCH("★",'트래블마트 통합'!Q24)),"★","-"))) -> ★★★ | F79: TRUE | G79: FALSE | H79: =IF(AND(F79,G79),"완료",IF(G79,"진행 완료",IF(F79,"참가 예정","미정"))) -> 참가 예정 | I79: ='트래블마트 통합'!Q24 -> ITB Berlin 2027 3월 상순 (예상, 통상 첫째 주 화~목) [★★★ 최우선] 세계 1위 여행 B2B, 글로벌 파트너 확장 필수
A80: ='트래블마트 통합'!R$2 -> 2027년 4월 | B80: ='트래블마트 통합'!$A9 -> 중국 | C80: ='트래블마트 통합'!$B9 -> 광동,화동,화북,내륙 | D80: =IFERROR(LEFT('트래블마트 통합'!R9,FIND(CHAR(10),'트래블마트 통합'!R9)-1),'트래블마트 통합'!R9) -> COTTM Beijing 2027 | E80: =IF(ISNUMBER(SEARCH("★★★",'트래블마트 통합'!R9)),"★★★",IF(ISNUMBER(SEARCH("★★",'트래블마트 통합'!R9)),"★★",IF(ISNUMBER(SEARCH("★",'트래블마트 통합'!R9)),"★","-"))) -> ★★★ | F80: FALSE | G80: FALSE | H80: =IF(AND(F80,G80),"완료",IF(G80,"진행 완료",IF(F80,"참가 예정","미정"))) -> 미정 | I80: ='트래블마트 통합'!R9 -> COTTM Beijing 2027 4월 중 (예상) [★★★ 최우선] 중국 outbound 전문 B2B
A81: ='트래블마트 통합'!R$2 -> 2027년 4월 | B81: ='트래블마트 통합'!$A15 -> 베트남 | C81: ='트래블마트 통합'!$B15 -> 호치민 하노이 | D81: =IFERROR(LEFT('트래블마트 통합'!R15,FIND(CHAR(10),'트래블마트 통합'!R15)-1),'트래블마트 통합'!R15) -> VITM Hanoi 2027 (Vietnam Int'l Travel Mart) | E81: =IF(ISNUMBER(SEARCH("★★★",'트래블마트 통합'!R15)),"★★★",IF(ISNUMBER(SEARCH("★★",'트래블마트 통합'!R15)),"★★",IF(ISNUMBER(SEARCH("★",'트래블마트 통합'!R15)),"★","-"))) -> ★★ | F81: FALSE | G81: FALSE | H81: =IF(AND(F81,G81),"완료",IF(G81,"진행 완료",IF(F81,"참가 예정","미정"))) -> 미정 | I81: ='트래블마트 통합'!R15 -> VITM Hanoi 2027 (Vietnam Int'l Travel Mart) 4월 상순 (예상) [★★ 중간] 북베트남 B2B+B2C
A82: ='트래블마트 통합'!R$2 -> 2027년 4월 | B82: ='트래블마트 통합'!$A24 -> 독일 | C82: ='트래블마트 통합'!$B24 -> 베를린 오버하우젠 | D82: =IFERROR(LEFT('트래블마트 통합'!R24,FIND(CHAR(10),'트래블마트 통합'!R24)-1),'트래블마트 통합'!R24) -> Germany Travel Mart (GTM) 2027 | E82: =IF(ISNUMBER(SEARCH("★★★",'트래블마트 통합'!R24)),"★★★",IF(ISNUMBER(SEARCH("★★",'트래블마트 통합'!R24)),"★★",IF(ISNUMBER(SEARCH("★",'트래블마트 통합'!R24)),"★","-"))) -> ★ | F82: FALSE | G82: FALSE | H82: =IF(AND(F82,G82),"완료",IF(G82,"진행 완료",IF(F82,"참가 예정","미정"))) -> 미정 | I82: ='트래블마트 통합'!R24 -> Germany Travel Mart (GTM) 2027 4월 중 (예상) [★ 선택] 독일 관광청 주최, 유럽 인바운드 중심
A83: ='트래블마트 통합'!R$2 -> 2027년 4월 | B83: ='트래블마트 통합'!$A30 -> South Africa | C83: ='트래블마트 통합'!$B30 -> Cape Town | D83: =IFERROR(LEFT('트래블마트 통합'!R30,FIND(CHAR(10),'트래블마트 통합'!R30)-1),'트래블마트 통합'!R30) -> WTM Africa 2027 (Cape Town) | E83: =IF(ISNUMBER(SEARCH("★★★",'트래블마트 통합'!R30)),"★★★",IF(ISNUMBER(SEARCH("★★",'트래블마트 통합'!R30)),"★★",IF(ISNUMBER(SEARCH("★",'트래블마트 통합'!R30)),"★","-"))) -> ★ | F83: FALSE | G83: FALSE | H83: =IF(AND(F83,G83),"완료",IF(G83,"진행 완료",IF(F83,"참가 예정","미정"))) -> 미정 | I83: ='트래블마트 통합'!R30 -> WTM Africa 2027 (Cape Town) 4월 중 (예상) [★ 선택] 아프리카 시장 접근
A84: ='트래블마트 통합'!R$2 -> 2027년 4월 | B84: ='트래블마트 통합'!$A31 -> 브라질 | C84: ='트래블마트 통합'!$B31 -> 상파울루 | D84: =IFERROR(LEFT('트래블마트 통합'!R31,FIND(CHAR(10),'트래블마트 통합'!R31)-1),'트래블마트 통합'!R31) -> WTM Latin America 2027 (상파울루) | E84: =IF(ISNUMBER(SEARCH("★★★",'트래블마트 통합'!R31)),"★★★",IF(ISNUMBER(SEARCH("★★",'트래블마트 통합'!R31)),"★★",IF(ISNUMBER(SEARCH("★",'트래블마트 통합'!R31)),"★","-"))) -> ★ | F84: FALSE | G84: FALSE | H84: =IF(AND(F84,G84),"완료",IF(G84,"진행 완료",IF(F84,"참가 예정","미정"))) -> 미정 | I84: ='트래블마트 통합'!R31 -> WTM Latin America 2027 (상파울루) 4월 중 (예상) [★ 선택] 남미 최대 B2B, 라틴 바이어 네트워크
A85: ='트래블마트 통합'!S$2 -> 2027년 5월 | B85: ='트래블마트 통합'!$A9 -> 중국 | C85: ='트래블마트 통합'!$B9 -> 광동,화동,화북,내륙 | D85: =IFERROR(LEFT('트래블마트 통합'!S9,FIND(CHAR(10),'트래블마트 통합'!S9)-1),'트래블마트 통합'!S9) -> ITB China 2027 (상하이) 5월 중 (예상) | E85: =IF(ISNUMBER(SEARCH("★★★",'트래블마트 통합'!S9)),"★★★",IF(ISNUMBER(SEARCH("★★",'트래블마트 통합'!S9)),"★★",IF(ISNUMBER(SEARCH("★",'트래블마트 통합'!S9)),"★","-"))) -> ★★★ | F85: FALSE | G85: FALSE | H85: =IF(AND(F85,G85),"완료",IF(G85,"진행 완료",IF(F85,"참가 예정","미정"))) -> 미정 | I85: ='트래블마트 통합'!S9 -> ITB China 2027 (상하이) 5월 중 (예상) GITF Guangzhou 5월 하순 (예상) [★★★ 최우선] 중국 outbound 최상위 B2B
A86: ='트래블마트 통합'!S$2 -> 2027년 5월 | B86: ='트래블마트 통합'!$A10 -> 한국 | C86: ='트래블마트 통합'!$B10 -> 서울 | D86: =IFERROR(LEFT('트래블마트 통합'!S10,FIND(CHAR(10),'트래블마트 통합'!S10)-1),'트래블마트 통합'!S10) -> 일산 트래블마트 2027 | E86: =IF(ISNUMBER(SEARCH("★★★",'트래블마트 통합'!S10)),"★★★",IF(ISNUMBER(SEARCH("★★",'트래블마트 통합'!S10)),"★★",IF(ISNUMBER(SEARCH("★",'트래블마트 통합'!S10)),"★","-"))) -> - | F86: TRUE | G86: FALSE | H86: =IF(AND(F86,G86),"완료",IF(G86,"진행 완료",IF(F86,"참가 예정","미정"))) -> 참가 예정 | I86: ='트래블마트 통합'!S10 -> 일산 트래블마트 2027 5월 중 (예상)
A87: ='트래블마트 통합'!S$2 -> 2027년 5월 | B87: ='트래블마트 통합'!$A12 -> 대만 | C87: ='트래블마트 통합'!$B12 -> 타이베이 | D87: =IFERROR(LEFT('트래블마트 통합'!S12,FIND(CHAR(10),'트래블마트 통합'!S12)-1),'트래블마트 통합'!S12) -> Taipei Tourism Expo (TTE) 2027 | E87: =IF(ISNUMBER(SEARCH("★★★",'트래블마트 통합'!S12)),"★★★",IF(ISNUMBER(SEARCH("★★",'트래블마트 통합'!S12)),"★★",IF(ISNUMBER(SEARCH("★",'트래블마트 통합'!S12)),"★","-"))) -> ★ | F87: FALSE | G87: FALSE | H87: =IF(AND(F87,G87),"완료",IF(G87,"진행 완료",IF(F87,"참가 예정","미정"))) -> 미정 | I87: ='트래블마트 통합'!S12 -> Taipei Tourism Expo (TTE) 2027 5월 하순 (예상) [★ 선택] 대만 최대 B2C, FIT 시장 강함
A88: ='트래블마트 통합'!S$2 -> 2027년 5월 | B88: ='트래블마트 통합'!$A22 -> UAE | C88: ='트래블마트 통합'!$B22 -> Dubai | D88: =IFERROR(LEFT('트래블마트 통합'!S22,FIND(CHAR(10),'트래블마트 통합'!S22)-1),'트래블마트 통합'!S22) -> Arabian Travel Market (ATM) 2027 (Dubai) | E88: =IF(ISNUMBER(SEARCH("★★★",'트래블마트 통합'!S22)),"★★★",IF(ISNUMBER(SEARCH("★★",'트래블마트 통합'!S22)),"★★",IF(ISNUMBER(SEARCH("★",'트래블마트 통합'!S22)),"★","-"))) -> ★★★ | F88: TRUE | G88: FALSE | H88: =IF(AND(F88,G88),"완료",IF(G88,"진행 완료",IF(F88,"참가 예정","미정"))) -> 참가 예정 | I88: ='트래블마트 통합'!S22 -> Arabian Travel Market (ATM) 2027 (Dubai) 5월 상순 (예상) [★★★ 최우선] 중동 최대 여행 B2B, GCC 바이어 중심
A89: ='트래블마트 통합'!S$2 -> 2027년 5월 | B89: ='트래블마트 통합'!$A25 -> 호주 | C89: ='트래블마트 통합'!$B25 -> 시드니, 애들레이드 | D89: =IFERROR(LEFT('트래블마트 통합'!S25,FIND(CHAR(10),'트래블마트 통합'!S25)-1),'트래블마트 통합'!S25) -> Australian Tourism Exchange (ATE) 2027 | E89: =IF(ISNUMBER(SEARCH("★★★",'트래블마트 통합'!S25)),"★★★",IF(ISNUMBER(SEARCH("★★",'트래블마트 통합'!S25)),"★★",IF(ISNUMBER(SEARCH("★",'트래블마트 통합'!S25)),"★","-"))) -> ★ | F89: FALSE | G89: FALSE | H89: =IF(AND(F89,G89),"완료",IF(G89,"진행 완료",IF(F89,"참가 예정","미정"))) -> 미정 | I89: ='트래블마트 통합'!S25 -> Australian Tourism Exchange (ATE) 2027 5월 중 (예상) [★ 선택] 오세아니아 최대 B2B
A90: ='트래블마트 통합'!S$2 -> 2027년 5월 | B90: ='트래블마트 통합'!$A28 -> 미국 | C90: ='트래블마트 통합'!$B28 -> 플로리다주 뉴욕 | D90: =IFERROR(LEFT('트래블마트 통합'!S28,FIND(CHAR(10),'트래블마트 통합'!S28)-1),'트래블마트 통합'!S28) -> IPW 2027 (U.S. Travel Association) | E90: =IF(ISNUMBER(SEARCH("★★★",'트래블마트 통합'!S28)),"★★★",IF(ISNUMBER(SEARCH("★★",'트래블마트 통합'!S28)),"★★",IF(ISNUMBER(SEARCH("★",'트래블마트 통합'!S28)),"★","-"))) -> ★ | F90: FALSE | G90: FALSE | H90: =IF(AND(F90,G90),"완료",IF(G90,"진행 완료",IF(F90,"참가 예정","미정"))) -> 미정 | I90: ='트래블마트 통합'!S28 -> IPW 2027 (U.S. Travel Association) 5월 하순 (예상) [★ 선택] 미국 인바운드 최대 B2B
A91: ='트래블마트 통합'!T$2 -> 2027년 6월 | B91: ='트래블마트 통합'!$A10 -> 한국 | C91: ='트래블마트 통합'!$B10 -> 서울 | D91: =IFERROR(LEFT('트래블마트 통합'!T10,FIND(CHAR(10),'트래블마트 통합'!T10)-1),'트래블마트 통합'!T10) -> Seoul International Travel Fair (SITF) 2027 | E91: =IF(ISNUMBER(SEARCH("★★★",'트래블마트 통합'!T10)),"★★★",IF(ISNUMBER(SEARCH("★★",'트래블마트 통합'!T10)),"★★",IF(ISNUMBER(SEARCH("★",'트래블마트 통합'!T10)),"★","-"))) -> ★ | F91: FALSE | G91: FALSE | H91: =IF(AND(F91,G91),"완료",IF(G91,"진행 완료",IF(F91,"참가 예정","미정"))) -> 미정 | I91: ='트래블마트 통합'!T10 -> Seoul International Travel Fair (SITF) 2027 6월 상순 (예상) SITM 6월 말~7월 초 (예상) [★ 선택] 한국 최대 여행박람회
A92: ='트래블마트 통합'!T$2 -> 2027년 6월 | B92: ='트래블마트 통합'!$A13 -> 홍콩 | C92: ='트래블마트 통합'!$B13 -> 홍콩 | D92: =IFERROR(LEFT('트래블마트 통합'!T13,FIND(CHAR(10),'트래블마트 통합'!T13)-1),'트래블마트 통합'!T13) -> ITE Hong Kong 2027 | E92: =IF(ISNUMBER(SEARCH("★★★",'트래블마트 통합'!T13)),"★★★",IF(ISNUMBER(SEARCH("★★",'트래블마트 통합'!T13)),"★★",IF(ISNUMBER(SEARCH("★",'트래블마트 통합'!T13)),"★","-"))) -> ★★ | F92: FALSE | G92: FALSE | H92: =IF(AND(F92,G92),"완료",IF(G92,"진행 완료",IF(F92,"참가 예정","미정"))) -> 미정 | I92: ='트래블마트 통합'!T13 -> ITE Hong Kong 2027 6월 중순 (예상) [★★ 중간] 홍콩–광둥 outbound 중심
A93: ='트래블마트 통합'!T$2 -> 2027년 6월 | B93: ='트래블마트 통합'!$A16 -> 태국 | C93: ='트래블마트 통합'!$B16 -> 방콕 | D93: =IFERROR(LEFT('트래블마트 통합'!T16,FIND(CHAR(10),'트래블마트 통합'!T16)-1),'트래블마트 통합'!T16) -> TTM+ (Thailand Travel Mart Plus) 2027 | E93: =IF(ISNUMBER(SEARCH("★★★",'트래블마트 통합'!T16)),"★★★",IF(ISNUMBER(SEARCH("★★",'트래블마트 통합'!T16)),"★★",IF(ISNUMBER(SEARCH("★",'트래블마트 통합'!T16)),"★","-"))) -> - | F93: FALSE | G93: FALSE | H93: =IF(AND(F93,G93),"완료",IF(G93,"진행 완료",IF(F93,"참가 예정","미정"))) -> 미정 | I93: ='트래블마트 통합'!T16 -> TTM+ (Thailand Travel Mart Plus) 2027 6월 둘째 주 (예상) 태국 관광청(TAT) 주관
A94: ='트래블마트 통합'!T$2 -> 2027년 6월 | B94: ='트래블마트 통합'!$A18 -> 싱가포르 | C94: ='트래블마트 통합'!$B18 -> 마리나베이 | D94: =IFERROR(LEFT('트래블마트 통합'!T18,FIND(CHAR(10),'트래블마트 통합'!T18)-1),'트래블마트 통합'!T18) -> ILTM Asia Pacific 2027 (싱가포르) | E94: =IF(ISNUMBER(SEARCH("★★★",'트래블마트 통합'!T18)),"★★★",IF(ISNUMBER(SEARCH("★★",'트래블마트 통합'!T18)),"★★",IF(ISNUMBER(SEARCH("★",'트래블마트 통합'!T18)),"★","-"))) -> ★ | F94: FALSE | G94: FALSE | H94: =IF(AND(F94,G94),"완료",IF(G94,"진행 완료",IF(F94,"참가 예정","미정"))) -> 미정 | I94: ='트래블마트 통합'!T18 -> ILTM Asia Pacific 2027 (싱가포르) 6월 말 (예상) [★ 선택] 아시아 럭셔리 여행 최상위 행사
A95: ='트래블마트 통합'!T$2 -> 2027년 6월 | B95: ='트래블마트 통합'!$A19 -> 인도네시아 | C95: ='트래블마트 통합'!$B19 -> 자카르타 | D95: =IFERROR(LEFT('트래블마트 통합'!T19,FIND(CHAR(10),'트래블마트 통합'!T19)-1),'트래블마트 통합'!T19) -> BBTF (Bali & Beyond Travel Fair) 2027 | E95: =IF(ISNUMBER(SEARCH("★★★",'트래블마트 통합'!T19)),"★★★",IF(ISNUMBER(SEARCH("★★",'트래블마트 통합'!T19)),"★★",IF(ISNUMBER(SEARCH("★",'트래블마트 통합'!T19)),"★","-"))) -> - | F95: FALSE | G95: FALSE | H95: =IF(AND(F95,G95),"완료",IF(G95,"진행 완료",IF(F95,"참가 예정","미정"))) -> 미정 | I95: ='트래블마트 통합'!T19 -> BBTF (Bali & Beyond Travel Fair) 2027 6월 중 (예상) Travel Meet Asia 2027 6월 하순 (예상) 호텔 소싱 핵심 행사

Sheet Dev Tracker
A1: API Integration Dev Tracker (IT / Dev Shared) — Actual Progress History by Stage Process | AA1: Stage Weights (progress calc · maps to cols M~W)
A2: Project / Dev Info | K2: Progress Status (Auto-calculated) | AA2: ① | AB2: ② | AC2: ③ | AD2: ④ | AE2: ⑤ | AF2: ⑥ | AG2: ⑦ | AH2: ⑧ | AI2: ⑨ | AJ2: ⑩ | AK2: ⑪
A3: No. | B3: Status | C3: Country | D3: Project | E3: Category | F3: Biz Impact | G3: OHMY Dev Load | H3: Switching | I3: Handling Team | J3: PIC (Sales) | K3: Progress % | L3: Last Activity | M3: Days Elapsed | N3: Delay Check | O3: ① NDA Signed (20%) | P3: ② Contract Signed (30%) | Q3: ③ SLA Finalized (40%) | R3: ④ Dev Kickoff Planned (45%) | S3: ⑤ Dev Kickoff / SPEC·DEV Key (50%) / Credential | T3: ⑥ Certification (60%) | U3: ⑦ Live Test (70%) | V3: ⑧ Dev Completion Planned (75%) | W3: ⑨ Live Key Open (80%) | X3: ⑩ First Booking (90%) | Y3: ⑪ API Live Complete (100%) | Z3: Status (manual backup) | AA3: 0.2 | AB3: 0.3 | AC3: 0.4 | AD3: 0.45 | AE3: 0.5 | AF3: 0.6 | AG3: 0.7 | AH3: 0.75 | AI3: 0.8 | AJ3: 0.9 | AK3: 1 | AL3: Dev Owner | AM3: Target Go-Live | AN3: Blocker | AO3: Note | AP3: Hold/Drop
A4: =IF($D4="","",COUNTA($D$4:$D4)) -> 1 | B4: =IF($D4="","",IF($L4="","Contact",LOOKUP($K4,$AA$5:$AA$8,$AB$5:$AB$8))) -> Contact | C4: Korea | D4: HANHWA Hotel & Resort | E4: CRS | F4: High | G4: 🔴 Full (100%) | I4: SLA | J4: Sophia | K4: {=IF($D4="","",SUMPRODUCT(MAX(($O4:$Y4<>"")*$AA$3:$AK$3)))} -> 0 | L4: =IF(COUNT($O4:$Y4)=0,"",MAX($O4:$Y4)) | M4: =IF($L4="","",TODAY()-$L4) | N4: =IF($L4="","No Record",IF($K4>=1,"Live",IF($M4>=90,"Stalled 90d+",IF($M4>=60,"Stalled 60d+",IF($M4>=30,"Stalled 30d+","In Progress"))))) -> No Record | Z4: Contact
A5: =IF($D5="","",COUNTA($D$4:$D5)) -> 2 | B5: =IF($D5="","",IF($L5="","Contact",LOOKUP($K5,$AA$5:$AA$8,$AB$5:$AB$8))) -> In Development | C5: China | D5: Shiji | E5: Switching System | F5: High | G5: 🟡 Half (50%) | I5: SLA | J5: Sophia | K5: {=IF($D5="","",SUMPRODUCT(MAX(($O5:$Y5<>"")*$AA$3:$AK$3)))} -> 0.45 | L5: =IF(COUNT($O5:$Y5)=0,"",MAX($O5:$Y5)) -> 46237 | M5: =IF($L5="","",TODAY()-$L5) -> 19 | N5: =IF($L5="","No Record",IF($K5>=1,"Live",IF($M5>=90,"Stalled 90d+",IF($M5>=60,"Stalled 60d+",IF($M5>=30,"Stalled 30d+","In Progress"))))) -> In Progress | O5: 45504 | P5: 46199 | R5: 46237 | Z5: In Development | AA5: 0.2 | AB5: NDA/Contract
A6: =IF($D6="","",COUNTA($D$4:$D6)) -> 3 | B6: =IF($D6="","",IF($L6="","Contact",LOOKUP($K6,$AA$5:$AA$8,$AB$5:$AB$8))) -> Contact | C6: Spain | D6: TGX | E6: Switching System | F6: High | G6: 🟡 Half (50%) | I6: SLA | J6: Sophia | K6: {=IF($D6="","",SUMPRODUCT(MAX(($O6:$Y6<>"")*$AA$3:$AK$3)))} -> 0 | L6: =IF(COUNT($O6:$Y6)=0,"",MAX($O6:$Y6)) | M6: =IF($L6="","",TODAY()-$L6) | N6: =IF($L6="","No Record",IF($K6>=1,"Live",IF($M6>=90,"Stalled 90d+",IF($M6>=60,"Stalled 60d+",IF($M6>=30,"Stalled 30d+","In Progress"))))) -> No Record | Z6: NDA/Contract | AA6: 0.45 | AB6: In Development
A7: =IF($D7="","",COUNTA($D$4:$D7)) -> 4 | B7: =IF($D7="","",IF($L7="","Contact",LOOKUP($K7,$AA$5:$AA$8,$AB$5:$AB$8))) -> Contact | C7: Spain | D7: Juniper | E7: Switching System | F7: Mid | G7: 🟢 Minimal (5-10%) | I7: SLA | J7: Sophia | K7: {=IF($D7="","",SUMPRODUCT(MAX(($O7:$Y7<>"")*$AA$3:$AK$3)))} -> 0 | L7: =IF(COUNT($O7:$Y7)=0,"",MAX($O7:$Y7)) | M7: =IF($L7="","",TODAY()-$L7) | N7: =IF($L7="","No Record",IF($K7>=1,"Live",IF($M7>=90,"Stalled 90d+",IF($M7>=60,"Stalled 60d+",IF($M7>=30,"Stalled 30d+","In Progress"))))) -> No Record | Z7: Contact | AA7: 0.7 | AB7: Testing
A8: =IF($D8="","",COUNTA($D$4:$D8)) -> 5 | B8: =IF($D8="","",IF($L8="","Contact",LOOKUP($K8,$AA$5:$AA$8,$AB$5:$AB$8))) -> Contact | C8: Singapore | D8: TAN | E8: Switching System | F8: Low | G8: 🔴 Full (100%) | I8: SLA | J8: Sophia | K8: {=IF($D8="","",SUMPRODUCT(MAX(($O8:$Y8<>"")*$AA$3:$AK$3)))} -> 0 | L8: =IF(COUNT($O8:$Y8)=0,"",MAX($O8:$Y8)) | M8: =IF($L8="","",TODAY()-$L8) | N8: =IF($L8="","No Record",IF($K8>=1,"Live",IF($M8>=90,"Stalled 90d+",IF($M8>=60,"Stalled 60d+",IF($M8>=30,"Stalled 30d+","In Progress"))))) -> No Record | Z8: Contact | AA8: 0.8 | AB8: Live
A9: =IF($D9="","",COUNTA($D$4:$D9)) -> 6 | B9: =IF($D9="","",IF($L9="","Contact",LOOKUP($K9,$AA$5:$AA$8,$AB$5:$AB$8))) -> Contact | D9: IOL | E9: Switching System | F9: Low | I9: SLA | J9: Sophia | K9: {=IF($D9="","",SUMPRODUCT(MAX(($O9:$Y9<>"")*$AA$3:$AK$3)))} -> 0 | N9: =IF($L9="","No Record",IF($K9>=1,"Live",IF($M9>=90,"Stalled 90d+",IF($M9>=60,"Stalled 60d+",IF($M9>=30,"Stalled 30d+","In Progress"))))) -> No Record
A10: =IF($D10="","",COUNTA($D$4:$D10)) -> 7 | B10: =IF($D10="","",IF($L10="","Contact",LOOKUP($K10,$AA$5:$AA$8,$AB$5:$AB$8))) -> Contact | C10: China | D10: Derbysoft | E10: Switching System | F10: Low | G10: 🔴 Full (100%) | I10: SLA | J10: Sophia | K10: {=IF($D10="","",SUMPRODUCT(MAX(($O10:$Y10<>"")*$AA$3:$AK$3)))} -> 0 | L10: =IF(COUNT($O10:$Y10)=0,"",MAX($O10:$Y10)) | M10: =IF($L10="","",TODAY()-$L10) | N10: =IF($L10="","No Record",IF($K10>=1,"Live",IF($M10>=90,"Stalled 90d+",IF($M10>=60,"Stalled 60d+",IF($M10>=30,"Stalled 30d+","In Progress"))))) -> No Record | Z10: Contact
A11: =IF($D11="","",COUNTA($D$4:$D11)) -> 8 | B11: =IF($D11="","",IF($L11="","Contact",LOOKUP($K11,$AA$5:$AA$8,$AB$5:$AB$8))) -> Contact | C11: USA | D11: Synxis | E11: Switching System | F11: Low | G11: 🔴 Full (100%) | I11: SLA | J11: Sophia | K11: {=IF($D11="","",SUMPRODUCT(MAX(($O11:$Y11<>"")*$AA$3:$AK$3)))} -> 0 | L11: =IF(COUNT($O11:$Y11)=0,"",MAX($O11:$Y11)) | M11: =IF($L11="","",TODAY()-$L11) | N11: =IF($L11="","No Record",IF($K11>=1,"Live",IF($M11>=90,"Stalled 90d+",IF($M11>=60,"Stalled 60d+",IF($M11>=30,"Stalled 30d+","In Progress"))))) -> No Record | Z11: Contact
A12: =IF($D12="","",COUNTA($D$4:$D12)) -> 9 | B12: =IF($D12="","",IF($L12="","Contact",LOOKUP($K12,$AA$5:$AA$8,$AB$5:$AB$8))) -> Contact | D12: 11infortec | E12: Switching System | F12: Low | G12: 🔴 Full (100%) | I12: SLA | J12: Sophia | K12: {=IF($D12="","",SUMPRODUCT(MAX(($O12:$Y12<>"")*$AA$3:$AK$3)))} -> 0 | L12: =IF(COUNT($O12:$Y12)=0,"",MAX($O12:$Y12)) | M12: =IF($L12="","",TODAY()-$L12) | N12: =IF($L12="","No Record",IF($K12>=1,"Live",IF($M12>=90,"Stalled 90d+",IF($M12>=60,"Stalled 60d+",IF($M12>=30,"Stalled 30d+","In Progress"))))) -> No Record | Z12: Contact
A13: =IF($D13="","",COUNTA($D$4:$D13)) -> 10 | B13: =IF($D13="","",IF($L13="","Contact",LOOKUP($K13,$AA$5:$AA$8,$AB$5:$AB$8))) -> Testing | C13: Hong Kong | D13: Klook | E13: Channel API | F13: High | G13: 🔴 Full (100%) | I13: GSM | J13: Grace | K13: {=IF($D13="","",SUMPRODUCT(MAX(($O13:$Y13<>"")*$AA$3:$AK$3)))} -> 0.75 | L13: =IF(COUNT($O13:$Y13)=0,"",MAX($O13:$Y13)) -> 45965 | M13: =IF($L13="","",TODAY()-$L13) -> 291 | N13: =IF($L13="","No Record",IF($K13>=1,"Live",IF($M13>=90,"Stalled 90d+",IF($M13>=60,"Stalled 60d+",IF($M13>=30,"Stalled 30d+","In Progress"))))) -> Stalled 90d+ | R13: 45962 | S13: 45962 | T13: 45963 | U13: 45964 | V13: 45965 | Z13: Testing
B14: =IF($D14="","",IF($L14="","Contact",LOOKUP($K14,$AA$5:$AA$8,$AB$5:$AB$8))) -> NDA/Contract | C14: Indonesia | D14: Tiket.com | E14: Channel API | F14: High | G14: 🟡 Half (50%) | I14: GSM | J14: Aiden | K14: {=IF($D14="","",SUMPRODUCT(MAX(($O14:$Y14<>"")*$AA$3:$AK$3)))} -> 0.2 | L14: =IF(COUNT($O14:$Y14)=0,"",MAX($O14:$Y14)) -> 46246 | N14: =IF($L14="","No Record",IF($K14>=1,"Live",IF($M14>=90,"Stalled 90d+",IF($M14>=60,"Stalled 60d+",IF($M14>=30,"Stalled 30d+","In Progress"))))) -> In Progress | O14: 46246
A15: =IF($D15="","",COUNTA($D$4:$D15)) -> 12 | B15: =IF($D15="","",IF($L15="","Contact",LOOKUP($K15,$AA$5:$AA$8,$AB$5:$AB$8))) -> Contact | C15: Israel | D15: GGT (Go Global) | E15: Channel API | F15: High | G15: 🔴 Full (100%) | I15: GSM | J15: Aiden | K15: {=IF($D15="","",SUMPRODUCT(MAX(($O15:$Y15<>"")*$AA$3:$AK$3)))} -> 0 | L15: =IF(COUNT($O15:$Y15)=0,"",MAX($O15:$Y15)) | M15: =IF($L15="","",TODAY()-$L15) | N15: =IF($L15="","No Record",IF($K15>=1,"Live",IF($M15>=90,"Stalled 90d+",IF($M15>=60,"Stalled 60d+",IF($M15>=30,"Stalled 30d+","In Progress"))))) -> No Record | Z15: In Development
A16: =IF($D16="","",COUNTA($D$4:$D16)) -> 13 | B16: =IF($D16="","",IF($L16="","Contact",LOOKUP($K16,$AA$5:$AA$8,$AB$5:$AB$8))) -> Contact | C16: India | D16: TBO | E16: Channel API | F16: High | G16: 🔴 Full (100%) | I16: GSM | J16: Aiden | K16: {=IF($D16="","",SUMPRODUCT(MAX(($O16:$Y16<>"")*$AA$3:$AK$3)))} -> 0 | L16: =IF(COUNT($O16:$Y16)=0,"",MAX($O16:$Y16)) | M16: =IF($L16="","",TODAY()-$L16) | N16: =IF($L16="","No Record",IF($K16>=1,"Live",IF($M16>=90,"Stalled 90d+",IF($M16>=60,"Stalled 60d+",IF($M16>=30,"Stalled 30d+","In Progress"))))) -> No Record | Z16: NDA/Contract
A17: =IF($D17="","",COUNTA($D$4:$D17)) -> 14 | B17: =IF($D17="","",IF($L17="","Contact",LOOKUP($K17,$AA$5:$AA$8,$AB$5:$AB$8))) -> Contact | C17: Russia | D17: RateHawk | E17: Channel API | F17: High | G17: 🔴 Full (100%) | I17: GSM | J17: Aiden | K17: {=IF($D17="","",SUMPRODUCT(MAX(($O17:$Y17<>"")*$AA$3:$AK$3)))} -> 0 | L17: =IF(COUNT($O17:$Y17)=0,"",MAX($O17:$Y17)) | M17: =IF($L17="","",TODAY()-$L17) | N17: =IF($L17="","No Record",IF($K17>=1,"Live",IF($M17>=90,"Stalled 90d+",IF($M17>=60,"Stalled 60d+",IF($M17>=30,"Stalled 30d+","In Progress"))))) -> No Record | Z17: NDA/Contract
A18: =IF($D18="","",COUNTA($D$4:$D18)) -> 15 | B18: =IF($D18="","",IF($L18="","Contact",LOOKUP($K18,$AA$5:$AA$8,$AB$5:$AB$8))) -> Contact | C18: Singapore | D18: Luxury Tours | E18: Channel API | F18: Mid | G18: 🟢 Minimal (5-10%) | H18: TGX | I18: GSM | J18: Aiden | K18: {=IF($D18="","",SUMPRODUCT(MAX(($O18:$Y18<>"")*$AA$3:$AK$3)))} -> 0 | L18: =IF(COUNT($O18:$Y18)=0,"",MAX($O18:$Y18)) | M18: =IF($L18="","",TODAY()-$L18) | N18: =IF($L18="","No Record",IF($K18>=1,"Live",IF($M18>=90,"Stalled 90d+",IF($M18>=60,"Stalled 60d+",IF($M18>=30,"Stalled 30d+","In Progress"))))) -> No Record | Z18: NDA/Contract
A19: =IF($D19="","",COUNTA($D$4:$D19)) -> 16 | B19: =IF($D19="","",IF($L19="","Contact",LOOKUP($K19,$AA$5:$AA$8,$AB$5:$AB$8))) -> In Development | C19: Russia | D19: Travelata(Vivatech) | E19: Channel API | F19: High | G19: 🟢 Minimal (5-11%) | I19: GSM | J19: Aiden | K19: {=IF($D19="","",SUMPRODUCT(MAX(($O19:$Y19<>"")*$AA$3:$AK$3)))} -> 0.5 | L19: =IF(COUNT($O19:$Y19)=0,"",MAX($O19:$Y19)) -> 46253 | M19: =IF($L19="","",TODAY()-$L19) -> 3 | N19: =IF($L19="","No Record",IF($K19>=1,"Live",IF($M19>=90,"Stalled 90d+",IF($M19>=60,"Stalled 60d+",IF($M19>=30,"Stalled 30d+","In Progress"))))) -> In Progress | O19: 46252 | P19: 46253 | R19: 46253 | S19: 46253 | Z19: NDA/Contract
A20: =IF($D20="","",COUNTA($D$4:$D20)) -> 17 | B20: =IF($D20="","",IF($L20="","Contact",LOOKUP($K20,$AA$5:$AA$8,$AB$5:$AB$8))) -> NDA/Contract | C20: Singapore | D20: Within Earth | E20: Channel API | F20: Mid | G20: 🟢 Minimal (5-15%) | I20: GSM | J20: Aiden | K20: {=IF($D20="","",SUMPRODUCT(MAX(($O20:$Y20<>"")*$AA$3:$AK$3)))} -> 0.2 | L20: =IF(COUNT($O20:$Y20)=0,"",MAX($O20:$Y20)) -> 45898 | M20: =IF($L20="","",TODAY()-$L20) -> 358 | N20: =IF($L20="","No Record",IF($K20>=1,"Live",IF($M20>=90,"Stalled 90d+",IF($M20>=60,"Stalled 60d+",IF($M20>=30,"Stalled 30d+","In Progress"))))) -> Stalled 90d+ | O20: 45898 | Z20: NDA/Contract
A21: =IF($D21="","",COUNTA($D$4:$D21)) -> 18 | B21: =IF($D21="","",IF($L21="","Contact",LOOKUP($K21,$AA$5:$AA$8,$AB$5:$AB$8))) -> Contact | C21: Thailand | D21: Pax2night | E21: Channel API | F21: Mid | G21: 🟢 Minimal (5-16%) | H21: TGX | I21: GSM | J21: Aiden | K21: {=IF($D21="","",SUMPRODUCT(MAX(($O21:$Y21<>"")*$AA$3:$AK$3)))} -> 0 | L21: =IF(COUNT($O21:$Y21)=0,"",MAX($O21:$Y21)) | M21: =IF($L21="","",TODAY()-$L21) | N21: =IF($L21="","No Record",IF($K21>=1,"Live",IF($M21>=90,"Stalled 90d+",IF($M21>=60,"Stalled 60d+",IF($M21>=30,"Stalled 30d+","In Progress"))))) -> No Record | Z21: NDA/Contract
A22: =IF($D22="","",COUNTA($D$4:$D22)) -> 19 | B22: =IF($D22="","",IF($L22="","Contact",LOOKUP($K22,$AA$5:$AA$8,$AB$5:$AB$8))) -> Contact | C22: UAE | D22: Happy Travel | E22: Channel API | F22: Mid | G22: 🟢 Minimal (5-17%) | I22: GSM | J22: Aiden | K22: {=IF($D22="","",SUMPRODUCT(MAX(($O22:$Y22<>"")*$AA$3:$AK$3)))} -> 0 | L22: =IF(COUNT($O22:$Y22)=0,"",MAX($O22:$Y22)) | M22: =IF($L22="","",TODAY()-$L22) | N22: =IF($L22="","No Record",IF($K22>=1,"Live",IF($M22>=90,"Stalled 90d+",IF($M22>=60,"Stalled 60d+",IF($M22>=30,"Stalled 30d+","In Progress"))))) -> No Record | Z22: NDA/Contract
A23: =IF($D23="","",COUNTA($D$4:$D23)) -> 20 | B23: =IF($D23="","",IF($L23="","Contact",LOOKUP($K23,$AA$5:$AA$8,$AB$5:$AB$8))) -> Live | C23: Korea | D23: bizplay | E23: Channel API | F23: High | G23: 🟢 Minimal (5-10%) | I23: GSM | J23: Aiden | K23: {=IF($D23="","",SUMPRODUCT(MAX(($O23:$Y23<>"")*$AA$3:$AK$3)))} -> 0.8 | L23: =IF(COUNT($O23:$Y23)=0,"",MAX($O23:$Y23)) -> 46253 | M23: =IF($L23="","",TODAY()-$L23) -> 3 | N23: =IF($L23="","No Record",IF($K23>=1,"Live",IF($M23>=90,"Stalled 90d+",IF($M23>=60,"Stalled 60d+",IF($M23>=30,"Stalled 30d+","In Progress"))))) -> In Progress | V23: 46253 | W23: 46253 | Z23: Contact
A24: =IF($D24="","",COUNTA($D$4:$D24)) -> 21 | B24: =IF($D24="","",IF($L24="","Contact",LOOKUP($K24,$AA$5:$AA$8,$AB$5:$AB$8))) -> Contact | C24: Spain | D24: HBX | E24: Channel API | F24: High | G24: 🔴 Full (100%) | H24: TGX | I24: GSM | J24: Aiden | K24: {=IF($D24="","",SUMPRODUCT(MAX(($O24:$Y24<>"")*$AA$3:$AK$3)))} -> 0 | L24: =IF(COUNT($O24:$Y24)=0,"",MAX($O24:$Y24)) | M24: =IF($L24="","",TODAY()-$L24) | N24: =IF($L24="","No Record",IF($K24>=1,"Live",IF($M24>=90,"Stalled 90d+",IF($M24>=60,"Stalled 60d+",IF($M24>=30,"Stalled 30d+","In Progress"))))) -> No Record | Z24: Contact
A25: =IF($D25="","",COUNTA($D$4:$D25)) -> 22 | B25: =IF($D25="","",IF($L25="","Contact",LOOKUP($K25,$AA$5:$AA$8,$AB$5:$AB$8))) -> Contact | C25: UAE | D25: Webbeds | E25: Channel API | F25: High | G25: 🔴 Full (100%) | I25: GSM | J25: Aiden | K25: {=IF($D25="","",SUMPRODUCT(MAX(($O25:$Y25<>"")*$AA$3:$AK$3)))} -> 0 | L25: =IF(COUNT($O25:$Y25)=0,"",MAX($O25:$Y25)) | M25: =IF($L25="","",TODAY()-$L25) | N25: =IF($L25="","No Record",IF($K25>=1,"Live",IF($M25>=90,"Stalled 90d+",IF($M25>=60,"Stalled 60d+",IF($M25>=30,"Stalled 30d+","In Progress"))))) -> No Record | Z25: Contact
A26: =IF($D26="","",COUNTA($D$4:$D26)) -> 23 | B26: =IF($D26="","",IF($L26="","Contact",LOOKUP($K26,$AA$5:$AA$8,$AB$5:$AB$8))) -> NDA/Contract | C26: Taiwan | D26: Lion Travel | E26: Channel API | F26: High | G26: 🟢 Minimal (5-10%) | H26: SHIJI | I26: GSM | J26: Grace | K26: {=IF($D26="","",SUMPRODUCT(MAX(($O26:$Y26<>"")*$AA$3:$AK$3)))} -> 0.2 | L26: =IF(COUNT($O26:$Y26)=0,"",MAX($O26:$Y26)) -> 45912 | M26: =IF($L26="","",TODAY()-$L26) -> 344 | N26: =IF($L26="","No Record",IF($K26>=1,"Live",IF($M26>=90,"Stalled 90d+",IF($M26>=60,"Stalled 60d+",IF($M26>=30,"Stalled 30d+","In Progress"))))) -> Stalled 90d+ | O26: 45912 | Z26: NDA/Contract
A27: =IF($D27="","",COUNTA($D$4:$D27)) -> 24 | B27: =IF($D27="","",IF($L27="","Contact",LOOKUP($K27,$AA$5:$AA$8,$AB$5:$AB$8))) -> In Development | C27: Taiwan | D27: Star Travel | E27: Channel API | F27: High | G27: 🟢 Minimal (5-10%) | I27: GSM | J27: Grace | K27: {=IF($D27="","",SUMPRODUCT(MAX(($O27:$Y27<>"")*$AA$3:$AK$3)))} -> 0.5 | L27: =IF(COUNT($O27:$Y27)=0,"",MAX($O27:$Y27)) -> 45993 | M27: =IF($L27="","",TODAY()-$L27) -> 263 | N27: =IF($L27="","No Record",IF($K27>=1,"Live",IF($M27>=90,"Stalled 90d+",IF($M27>=60,"Stalled 60d+",IF($M27>=30,"Stalled 30d+","In Progress"))))) -> Stalled 90d+ | P27: 45946 | R27: 45992 | S27: 45993 | Z27: NDA/Contract
A28: =IF($D28="","",COUNTA($D$4:$D28)) -> 25 | B28: =IF($D28="","",IF($L28="","Contact",LOOKUP($K28,$AA$5:$AA$8,$AB$5:$AB$8))) -> In Development | C28: Taiwan | D28: Cola Tour | E28: Channel API | F28: High | G28: 🟢 Minimal (5-10%) | I28: GSM | J28: Grace | K28: {=IF($D28="","",SUMPRODUCT(MAX(($O28:$Y28<>"")*$AA$3:$AK$3)))} -> 0.5 | L28: =IF(COUNT($O28:$Y28)=0,"",MAX($O28:$Y28)) -> 46235 | M28: =IF($L28="","",TODAY()-$L28) -> 21 | N28: =IF($L28="","No Record",IF($K28>=1,"Live",IF($M28>=90,"Stalled 90d+",IF($M28>=60,"Stalled 60d+",IF($M28>=30,"Stalled 30d+","In Progress"))))) -> In Progress | S28: 46235 | Z28: In Development
A29: =IF($D29="","",COUNTA($D$4:$D29)) -> 26 | B29: =IF($D29="","",IF($L29="","Contact",LOOKUP($K29,$AA$5:$AA$8,$AB$5:$AB$8))) -> NDA/Contract | C29: China | D29: Uone | E29: Channel API | G29: 🟢 Minimal (5-10%) | I29: GSM | J29: Grace | K29: {=IF($D29="","",SUMPRODUCT(MAX(($O29:$Y29<>"")*$AA$3:$AK$3)))} -> 0.2 | L29: =IF(COUNT($O29:$Y29)=0,"",MAX($O29:$Y29)) -> 45908 | M29: =IF($L29="","",TODAY()-$L29) -> 348 | N29: =IF($L29="","No Record",IF($K29>=1,"Live",IF($M29>=90,"Stalled 90d+",IF($M29>=60,"Stalled 60d+",IF($M29>=30,"Stalled 30d+","In Progress"))))) -> Stalled 90d+ | O29: 45908 | Z29: Contact
A30: =IF($D30="","",COUNTA($D$4:$D30)) -> 27 | B30: =IF($D30="","",IF($L30="","Contact",LOOKUP($K30,$AA$5:$AA$8,$AB$5:$AB$8))) -> NDA/Contract | C30: China | D30: Amerilink | E30: Channel API | G30: 🟢 Minimal (5-10%) | I30: GSM | J30: Grace | K30: {=IF($D30="","",SUMPRODUCT(MAX(($O30:$Y30<>"")*$AA$3:$AK$3)))} -> 0.2 | L30: =IF(COUNT($O30:$Y30)=0,"",MAX($O30:$Y30)) -> 45957 | M30: =IF($L30="","",TODAY()-$L30) -> 299 | N30: =IF($L30="","No Record",IF($K30>=1,"Live",IF($M30>=90,"Stalled 90d+",IF($M30>=60,"Stalled 60d+",IF($M30>=30,"Stalled 30d+","In Progress"))))) -> Stalled 90d+ | O30: 45957 | Z30: Contact
A31: =IF($D31="","",COUNTA($D$4:$D31)) -> 28 | B31: =IF($D31="","",IF($L31="","Contact",LOOKUP($K31,$AA$5:$AA$8,$AB$5:$AB$8))) -> NDA/Contract | C31: Vietnam | D31: Chudu24 | E31: Channel API | G31: 🟢 Minimal (5-10%) | I31: GSM | J31: Aiden | K31: {=IF($D31="","",SUMPRODUCT(MAX(($O31:$Y31<>"")*$AA$3:$AK$3)))} -> 0.3 | L31: =IF(COUNT($O31:$Y31)=0,"",MAX($O31:$Y31)) -> 46001 | M31: =IF($L31="","",TODAY()-$L31) -> 255 | N31: =IF($L31="","No Record",IF($K31>=1,"Live",IF($M31>=90,"Stalled 90d+",IF($M31>=60,"Stalled 60d+",IF($M31>=30,"Stalled 30d+","In Progress"))))) -> Stalled 90d+ | P31: 46001 | Z31: Contact
A32: =IF($D32="","",COUNTA($D$4:$D32)) -> 29 | B32: =IF($D32="","",IF($L32="","Contact",LOOKUP($K32,$AA$5:$AA$8,$AB$5:$AB$8))) -> Contact | D32: Prime Travel | E32: Channel API | G32: 🟢 Minimal (5-10%) | I32: GSM | J32: Aiden | K32: {=IF($D32="","",SUMPRODUCT(MAX(($O32:$Y32<>"")*$AA$3:$AK$3)))} -> 0 | L32: =IF(COUNT($O32:$Y32)=0,"",MAX($O32:$Y32)) | M32: =IF($L32="","",TODAY()-$L32) | N32: =IF($L32="","No Record",IF($K32>=1,"Live",IF($M32>=90,"Stalled 90d+",IF($M32>=60,"Stalled 60d+",IF($M32>=30,"Stalled 30d+","In Progress"))))) -> No Record | Z32: Contact
A33: =IF($D33="","",COUNTA($D$4:$D33)) -> 30 | B33: =IF($D33="","",IF($L33="","Contact",LOOKUP($K33,$AA$5:$AA$8,$AB$5:$AB$8))) -> In Development | C33: China | D33: Fangcang | E33: Channel API | F33: High | G33: 🟢 Minimal (5-10%) | I33: GSM | J33: Grace | K33: {=IF($D33="","",SUMPRODUCT(MAX(($O33:$Y33<>"")*$AA$3:$AK$3)))} -> 0.5 | L33: =IF(COUNT($O33:$Y33)=0,"",MAX($O33:$Y33)) -> 46246 | M33: =IF($L33="","",TODAY()-$L33) -> 10 | N33: =IF($L33="","No Record",IF($K33>=1,"Live",IF($M33>=90,"Stalled 90d+",IF($M33>=60,"Stalled 60d+",IF($M33>=30,"Stalled 30d+","In Progress"))))) -> In Progress | O33: 46242 | P33: 46243 | Q33: 46244 | R33: 46245 | S33: 46246 | Z33: In Development
A34: =IF($D34="","",COUNTA($D$4:$D34)) -> 31 | B34: =IF($D34="","",IF($L34="","Contact",LOOKUP($K34,$AA$5:$AA$8,$AB$5:$AB$8))) -> Contact | C34: China | D34: Meiya | E34: Channel API | G34: 🟢 Minimal (5-10%) | I34: GSM | J34: IKET | K34: {=IF($D34="","",SUMPRODUCT(MAX(($O34:$Y34<>"")*$AA$3:$AK$3)))} -> 0 | L34: =IF(COUNT($O34:$Y34)=0,"",MAX($O34:$Y34)) | M34: =IF($L34="","",TODAY()-$L34) | N34: =IF($L34="","No Record",IF($K34>=1,"Live",IF($M34>=90,"Stalled 90d+",IF($M34>=60,"Stalled 60d+",IF($M34>=30,"Stalled 30d+","In Progress"))))) -> No Record | Z34: NDA/Contract
A35: =IF($D35="","",COUNTA($D$4:$D35)) -> 32 | B35: =IF($D35="","",IF($L35="","Contact",LOOKUP($K35,$AA$5:$AA$8,$AB$5:$AB$8))) -> In Development | C35: China | D35: JL Tour | E35: Channel API | G35: 🟢 Minimal (5-10%) | I35: GSM | J35: Grace | K35: {=IF($D35="","",SUMPRODUCT(MAX(($O35:$Y35<>"")*$AA$3:$AK$3)))} -> 0.5 | L35: =IF(COUNT($O35:$Y35)=0,"",MAX($O35:$Y35)) -> 45971 | M35: =IF($L35="","",TODAY()-$L35) -> 285 | N35: =IF($L35="","No Record",IF($K35>=1,"Live",IF($M35>=90,"Stalled 90d+",IF($M35>=60,"Stalled 60d+",IF($M35>=30,"Stalled 30d+","In Progress"))))) -> Stalled 90d+ | O35: 45971 | P35: 45971 | Q35: 45971 | R35: 45971 | S35: 45971 | Z35: In Development
A36: =IF($D36="","",COUNTA($D$4:$D36)) -> 33 | B36: =IF($D36="","",IF($L36="","Contact",LOOKUP($K36,$AA$5:$AA$8,$AB$5:$AB$8))) -> Contact | C36: China | D36: Qian Tao | E36: Channel API | G36: 🟢 Minimal (5-10%) | I36: GSM | J36: Grace | K36: {=IF($D36="","",SUMPRODUCT(MAX(($O36:$Y36<>"")*$AA$3:$AK$3)))} -> 0 | L36: =IF(COUNT($O36:$Y36)=0,"",MAX($O36:$Y36)) | M36: =IF($L36="","",TODAY()-$L36) | N36: =IF($L36="","No Record",IF($K36>=1,"Live",IF($M36>=90,"Stalled 90d+",IF($M36>=60,"Stalled 60d+",IF($M36>=30,"Stalled 30d+","In Progress"))))) -> No Record | Z36: NDA/Contract
A37: =IF($D37="","",COUNTA($D$4:$D37)) -> 34 | B37: =IF($D37="","",IF($L37="","Contact",LOOKUP($K37,$AA$5:$AA$8,$AB$5:$AB$8))) -> Contact | C37: India | D37: MakeMyTrip | E37: Channel API | F37: High | G37: 🔴 Full (100%) | I37: GSM | J37: Aiden | K37: {=IF($D37="","",SUMPRODUCT(MAX(($O37:$Y37<>"")*$AA$3:$AK$3)))} -> 0 | L37: =IF(COUNT($O37:$Y37)=0,"",MAX($O37:$Y37)) | M37: =IF($L37="","",TODAY()-$L37) | N37: =IF($L37="","No Record",IF($K37>=1,"Live",IF($M37>=90,"Stalled 90d+",IF($M37>=60,"Stalled 60d+",IF($M37>=30,"Stalled 30d+","In Progress"))))) -> No Record | Z37: NDA/Contract
A38: =IF($D38="","",COUNTA($D$4:$D38)) -> 35 | B38: =IF($D38="","",IF($L38="","Contact",LOOKUP($K38,$AA$5:$AA$8,$AB$5:$AB$8))) -> Contact | C38: Vietnam | D38: Vietravel | E38: Channel API | F38: High | G38: 🟢 Minimal (5-10%) | I38: GSM | J38: Aiden | K38: {=IF($D38="","",SUMPRODUCT(MAX(($O38:$Y38<>"")*$AA$3:$AK$3)))} -> 0 | L38: =IF(COUNT($O38:$Y38)=0,"",MAX($O38:$Y38)) | M38: =IF($L38="","",TODAY()-$L38) | N38: =IF($L38="","No Record",IF($K38>=1,"Live",IF($M38>=90,"Stalled 90d+",IF($M38>=60,"Stalled 60d+",IF($M38>=30,"Stalled 30d+","In Progress"))))) -> No Record | Z38: NDA/Contract
A39: =IF($D39="","",COUNTA($D$4:$D39)) -> 36 | B39: =IF($D39="","",IF($L39="","Contact",LOOKUP($K39,$AA$5:$AA$8,$AB$5:$AB$8))) -> Contact | C39: China | D39: Mafengwo | E39: Channel API | F39: Mid | G39: 🟢 Minimal (5-10%) | I39: GSM | J39: Grace | K39: {=IF($D39="","",SUMPRODUCT(MAX(($O39:$Y39<>"")*$AA$3:$AK$3)))} -> 0 | L39: =IF(COUNT($O39:$Y39)=0,"",MAX($O39:$Y39)) | M39: =IF($L39="","",TODAY()-$L39) | N39: =IF($L39="","No Record",IF($K39>=1,"Live",IF($M39>=90,"Stalled 90d+",IF($M39>=60,"Stalled 60d+",IF($M39>=30,"Stalled 30d+","In Progress"))))) -> No Record | Z39: NDA/Contract
A40: =IF($D40="","",COUNTA($D$4:$D40)) -> 37 | B40: =IF($D40="","",IF($L40="","Contact",LOOKUP($K40,$AA$5:$AA$8,$AB$5:$AB$8))) -> Contact | C40: China | D40: Chai Yi Lc -Yihao | E40: Channel API | F40: High | G40: 🟢 Minimal (5-10%) | I40: GSM | J40: Grace | K40: {=IF($D40="","",SUMPRODUCT(MAX(($O40:$Y40<>"")*$AA$3:$AK$3)))} -> 0 | L40: =IF(COUNT($O40:$Y40)=0,"",MAX($O40:$Y40)) | M40: =IF($L40="","",TODAY()-$L40) | N40: =IF($L40="","No Record",IF($K40>=1,"Live",IF($M40>=90,"Stalled 90d+",IF($M40>=60,"Stalled 60d+",IF($M40>=30,"Stalled 30d+","In Progress"))))) -> No Record | Z40: NDA/Contract
A41: =IF($D41="","",COUNTA($D$4:$D41)) -> 38 | B41: =IF($D41="","",IF($L41="","Contact",LOOKUP($K41,$AA$5:$AA$8,$AB$5:$AB$8))) -> Contact | C41: China | D41: Fenbeitong | E41: Channel API | F41: High | G41: 🟢 Minimal (5-10%) | I41: GSM | J41: Grace | K41: {=IF($D41="","",SUMPRODUCT(MAX(($O41:$Y41<>"")*$AA$3:$AK$3)))} -> 0 | L41: =IF(COUNT($O41:$Y41)=0,"",MAX($O41:$Y41)) | M41: =IF($L41="","",TODAY()-$L41) | N41: =IF($L41="","No Record",IF($K41>=1,"Live",IF($M41>=90,"Stalled 90d+",IF($M41>=60,"Stalled 60d+",IF($M41>=30,"Stalled 30d+","In Progress"))))) -> No Record | Z41: NDA/Contract
A42: =IF($D42="","",COUNTA($D$4:$D42)) -> 39 | B42: =IF($D42="","",IF($L42="","Contact",LOOKUP($K42,$AA$5:$AA$8,$AB$5:$AB$8))) -> NDA/Contract | C42: China | D42: Hibeds | E42: Channel API | F42: High | G42: 🟢 Minimal (5-10%) | I42: GSM | J42: Grace | K42: {=IF($D42="","",SUMPRODUCT(MAX(($O42:$Y42<>"")*$AA$3:$AK$3)))} -> 0.2 | L42: =IF(COUNT($O42:$Y42)=0,"",MAX($O42:$Y42)) -> 46275 | M42: =IF($L42="","",TODAY()-$L42) -> -19 | N42: =IF($L42="","No Record",IF($K42>=1,"Live",IF($M42>=90,"Stalled 90d+",IF($M42>=60,"Stalled 60d+",IF($M42>=30,"Stalled 30d+","In Progress"))))) -> In Progress | O42: 46275 | Z42: NDA/Contract
A43: =IF($D43="","",COUNTA($D$4:$D43)) -> 40 | B43: =IF($D43="","",IF($L43="","Contact",LOOKUP($K43,$AA$5:$AA$8,$AB$5:$AB$8))) -> In Development | C43: Vietnam | D43: Momo | E43: Channel API | F43: High | G43: 🟢 Minimal (5-10%) | I43: GSM | J43: Aiden | K43: {=IF($D43="","",SUMPRODUCT(MAX(($O43:$Y43<>"")*$AA$3:$AK$3)))} -> 0.5 | L43: =IF(COUNT($O43:$Y43)=0,"",MAX($O43:$Y43)) -> 46223 | M43: =IF($L43="","",TODAY()-$L43) -> 33 | N43: =IF($L43="","No Record",IF($K43>=1,"Live",IF($M43>=90,"Stalled 90d+",IF($M43>=60,"Stalled 60d+",IF($M43>=30,"Stalled 30d+","In Progress"))))) -> Stalled 30d+ | O43: 46178 | P43: 46223 | Q43: 46223 | R43: 46223 | S43: 46219 | Z43: NDA/Contract
A44: =IF($D44="","",COUNTA($D$4:$D44)) -> 41 | B44: =IF($D44="","",IF($L44="","Contact",LOOKUP($K44,$AA$5:$AA$8,$AB$5:$AB$8))) -> Contact | C44: China | D44: Wingspulse | E44: Channel API | F44: Mid | G44: 🟢 Minimal (5-10%) | I44: GSM | J44: Grace | K44: {=IF($D44="","",SUMPRODUCT(MAX(($O44:$Y44<>"")*$AA$3:$AK$3)))} -> 0 | L44: =IF(COUNT($O44:$Y44)=0,"",MAX($O44:$Y44)) | M44: =IF($L44="","",TODAY()-$L44) | N44: =IF($L44="","No Record",IF($K44>=1,"Live",IF($M44>=90,"Stalled 90d+",IF($M44>=60,"Stalled 60d+",IF($M44>=30,"Stalled 30d+","In Progress"))))) -> No Record | Z44: NDA/Contract
A45: =IF($D45="","",COUNTA($D$4:$D45)) -> 42 | B45: =IF($D45="","",IF($L45="","Contact",LOOKUP($K45,$AA$5:$AA$8,$AB$5:$AB$8))) -> In Development | C45: China | D45: Huamao | E45: Channel API | F45: Mid | G45: 🟢 Minimal (5-10%) | I45: GSM | J45: Grace | K45: {=IF($D45="","",SUMPRODUCT(MAX(($O45:$Y45<>"")*$AA$3:$AK$3)))} -> 0.5 | L45: =IF(COUNT($O45:$Y45)=0,"",MAX($O45:$Y45)) -> 46248 | M45: =IF($L45="","",TODAY()-$L45) -> 8 | N45: =IF($L45="","No Record",IF($K45>=1,"Live",IF($M45>=90,"Stalled 90d+",IF($M45>=60,"Stalled 60d+",IF($M45>=30,"Stalled 30d+","In Progress"))))) -> In Progress | O45: 46244 | P45: 46245 | Q45: 46246 | R45: 46247 | S45: 46248 | Z45: NDA/Contract
A46: =IF($D46="","",COUNTA($D$4:$D46)) -> 43 | B46: =IF($D46="","",IF($L46="","Contact",LOOKUP($K46,$AA$5:$AA$8,$AB$5:$AB$8))) -> Contact | C46: China | D46: Linkall travel | E46: Channel API | F46: Mid | G46: 🟢 Minimal (5-10%) | I46: GSM | J46: Grace | K46: {=IF($D46="","",SUMPRODUCT(MAX(($O46:$Y46<>"")*$AA$3:$AK$3)))} -> 0 | L46: =IF(COUNT($O46:$Y46)=0,"",MAX($O46:$Y46)) | M46: =IF($L46="","",TODAY()-$L46) | N46: =IF($L46="","No Record",IF($K46>=1,"Live",IF($M46>=90,"Stalled 90d+",IF($M46>=60,"Stalled 60d+",IF($M46>=30,"Stalled 30d+","In Progress"))))) -> No Record | Z46: NDA/Contract
A47: =IF($D47="","",COUNTA($D$4:$D47)) -> 44 | B47: =IF($D47="","",IF($L47="","Contact",LOOKUP($K47,$AA$5:$AA$8,$AB$5:$AB$8))) -> In Development | C47: China | D47: SUZHOU YILV SUNSHINE TRAVEL AGENCY CO.,LTD | E47: Channel API | F47: Mid | G47: 🟢 Minimal (5-10%) | I47: GSM | J47: Grace | K47: {=IF($D47="","",SUMPRODUCT(MAX(($O47:$Y47<>"")*$AA$3:$AK$3)))} -> 0.5 | L47: =IF(COUNT($O47:$Y47)=0,"",MAX($O47:$Y47)) -> 46248 | M47: =IF($L47="","",TODAY()-$L47) -> 8 | N47: =IF($L47="","No Record",IF($K47>=1,"Live",IF($M47>=90,"Stalled 90d+",IF($M47>=60,"Stalled 60d+",IF($M47>=30,"Stalled 30d+","In Progress"))))) -> In Progress | O47: 46244 | P47: 46245 | Q47: 46246 | R47: 46247 | S47: 46248 | Z47: NDA/Contract
A48: =IF($D48="","",COUNTA($D$4:$D48)) -> 45 | B48: =IF($D48="","",IF($L48="","Contact",LOOKUP($K48,$AA$5:$AA$8,$AB$5:$AB$8))) -> In Development | C48: China | D48: Ziru (TMC) | E48: Channel API | F48: Mid | G48: 🟢 Minimal (5-10%) | I48: GSM | J48: Grace | K48: {=IF($D48="","",SUMPRODUCT(MAX(($O48:$Y48<>"")*$AA$3:$AK$3)))} -> 0.5 | L48: =IF(COUNT($O48:$Y48)=0,"",MAX($O48:$Y48)) -> 46248 | M48: =IF($L48="","",TODAY()-$L48) -> 8 | N48: =IF($L48="","No Record",IF($K48>=1,"Live",IF($M48>=90,"Stalled 90d+",IF($M48>=60,"Stalled 60d+",IF($M48>=30,"Stalled 30d+","In Progress"))))) -> In Progress | O48: 46244 | P48: 46245 | Q48: 46246 | R48: 46247 | S48: 46248 | Z48: NDA/Contract
A49: =IF($D49="","",COUNTA($D$4:$D49)) -> 46 | B49: =IF($D49="","",IF($L49="","Contact",LOOKUP($K49,$AA$5:$AA$8,$AB$5:$AB$8))) -> Contact | C49: China | D49: Didi TMC | E49: Channel API | F49: High | G49: 🟢 Minimal (5-10%) | I49: GSM | J49: Grace | K49: {=IF($D49="","",SUMPRODUCT(MAX(($O49:$Y49<>"")*$AA$3:$AK$3)))} -> 0 | L49: =IF(COUNT($O49:$Y49)=0,"",MAX($O49:$Y49)) | M49: =IF($L49="","",TODAY()-$L49) | N49: =IF($L49="","No Record",IF($K49>=1,"Live",IF($M49>=90,"Stalled 90d+",IF($M49>=60,"Stalled 60d+",IF($M49>=30,"Stalled 30d+","In Progress"))))) -> No Record | Z49: NDA/Contract
A50: =IF($D50="","",COUNTA($D$4:$D50)) -> 47 | B50: =IF($D50="","",IF($L50="","Contact",LOOKUP($K50,$AA$5:$AA$8,$AB$5:$AB$8))) -> Contact | C50: China | D50: CN Booking | E50: Channel API | G50: 🟢 Minimal (5-10%) | I50: GSM | J50: Grace | K50: {=IF($D50="","",SUMPRODUCT(MAX(($O50:$Y50<>"")*$AA$3:$AK$3)))} -> 0 | L50: =IF(COUNT($O50:$Y50)=0,"",MAX($O50:$Y50)) | M50: =IF($L50="","",TODAY()-$L50) | N50: =IF($L50="","No Record",IF($K50>=1,"Live",IF($M50>=90,"Stalled 90d+",IF($M50>=60,"Stalled 60d+",IF($M50>=30,"Stalled 30d+","In Progress"))))) -> No Record | Z50: Contact
A51: =IF($D51="","",COUNTA($D$4:$D51)) -> 48 | B51: =IF($D51="","",IF($L51="","Contact",LOOKUP($K51,$AA$5:$AA$8,$AB$5:$AB$8))) -> Contact | C51: Vietnam | D51: Gotadi - HCM Branch | E51: Channel API | G51: 🟢 Minimal (5-10%) | I51: GSM | J51: Aiden | K51: {=IF($D51="","",SUMPRODUCT(MAX(($O51:$Y51<>"")*$AA$3:$AK$3)))} -> 0 | L51: =IF(COUNT($O51:$Y51)=0,"",MAX($O51:$Y51)) | M51: =IF($L51="","",TODAY()-$L51) | N51: =IF($L51="","No Record",IF($K51>=1,"Live",IF($M51>=90,"Stalled 90d+",IF($M51>=60,"Stalled 60d+",IF($M51>=30,"Stalled 30d+","In Progress"))))) -> No Record | Z51: Contact
A52: =IF($D52="","",COUNTA($D$4:$D52)) -> 49 | B52: =IF($D52="","",IF($L52="","Contact",LOOKUP($K52,$AA$5:$AA$8,$AB$5:$AB$8))) -> NDA/Contract | C52: Vietnam | D52: Gotadi - HN Branch | E52: Channel API | G52: 🟢 Minimal (5-10%) | I52: GSM | J52: Aiden | K52: {=IF($D52="","",SUMPRODUCT(MAX(($O52:$Y52<>"")*$AA$3:$AK$3)))} -> 0.4 | L52: =IF(COUNT($O52:$Y52)=0,"",MAX($O52:$Y52)) -> 46212 | M52: =IF($L52="","",TODAY()-$L52) -> 44 | N52: =IF($L52="","No Record",IF($K52>=1,"Live",IF($M52>=90,"Stalled 90d+",IF($M52>=60,"Stalled 60d+",IF($M52>=30,"Stalled 30d+","In Progress"))))) -> Stalled 30d+ | O52: 46212 | P52: 46212 | Q52: 46212 | Z52: NDA/Contract
A53: =IF($D53="","",COUNTA($D$4:$D53)) -> 50 | B53: =IF($D53="","",IF($L53="","Contact",LOOKUP($K53,$AA$5:$AA$8,$AB$5:$AB$8))) -> Contact | C53: China | D53: Joy Travel | E53: Channel API | G53: 🟢 Minimal (5-10%) | I53: GSM | J53: Grace | K53: {=IF($D53="","",SUMPRODUCT(MAX(($O53:$Y53<>"")*$AA$3:$AK$3)))} -> 0 | L53: =IF(COUNT($O53:$Y53)=0,"",MAX($O53:$Y53)) | M53: =IF($L53="","",TODAY()-$L53) | N53: =IF($L53="","No Record",IF($K53>=1,"Live",IF($M53>=90,"Stalled 90d+",IF($M53>=60,"Stalled 60d+",IF($M53>=30,"Stalled 30d+","In Progress"))))) -> No Record | Z53: Contact
A54: =IF($D54="","",COUNTA($D$4:$D54)) -> 51 | B54: =IF($D54="","",IF($L54="","Contact",LOOKUP($K54,$AA$5:$AA$8,$AB$5:$AB$8))) -> Contact | D54: Cheapotel | E54: Channel API | G54: 🟢 Minimal (5-10%) | I54: GSM | J54: Grace | K54: {=IF($D54="","",SUMPRODUCT(MAX(($O54:$Y54<>"")*$AA$3:$AK$3)))} -> 0 | L54: =IF(COUNT($O54:$Y54)=0,"",MAX($O54:$Y54)) | M54: =IF($L54="","",TODAY()-$L54) | N54: =IF($L54="","No Record",IF($K54>=1,"Live",IF($M54>=90,"Stalled 90d+",IF($M54>=60,"Stalled 60d+",IF($M54>=30,"Stalled 30d+","In Progress"))))) -> No Record | Z54: Contact
A55: =IF($D55="","",COUNTA($D$4:$D55)) -> 52 | B55: =IF($D55="","",IF($L55="","Contact",LOOKUP($K55,$AA$5:$AA$8,$AB$5:$AB$8))) -> NDA/Contract | D55: Justgotrip | E55: Channel API | G55: 🟢 Minimal (5-10%) | I55: GSM | J55: Grace | K55: {=IF($D55="","",SUMPRODUCT(MAX(($O55:$Y55<>"")*$AA$3:$AK$3)))} -> 0.2 | L55: =IF(COUNT($O55:$Y55)=0,"",MAX($O55:$Y55)) -> 46027 | M55: =IF($L55="","",TODAY()-$L55) -> 229 | N55: =IF($L55="","No Record",IF($K55>=1,"Live",IF($M55>=90,"Stalled 90d+",IF($M55>=60,"Stalled 60d+",IF($M55>=30,"Stalled 30d+","In Progress"))))) -> Stalled 90d+ | O55: 46027 | Z55: NDA/Contract
A56: =IF($D56="","",COUNTA($D$4:$D56)) -> 53 | B56: =IF($D56="","",IF($L56="","Contact",LOOKUP($K56,$AA$5:$AA$8,$AB$5:$AB$8))) -> Contact | C56: India | D56: TBO | E56: 3rd Party Hotel | F56: High | G56: 🔴 Full (100%) | I56: SLA | J56: Sophia | K56: {=IF($D56="","",SUMPRODUCT(MAX(($O56:$Y56<>"")*$AA$3:$AK$3)))} -> 0 | L56: =IF(COUNT($O56:$Y56)=0,"",MAX($O56:$Y56)) | M56: =IF($L56="","",TODAY()-$L56) | N56: =IF($L56="","No Record",IF($K56>=1,"Live",IF($M56>=90,"Stalled 90d+",IF($M56>=60,"Stalled 60d+",IF($M56>=30,"Stalled 30d+","In Progress"))))) -> No Record | Z56: NDA/Contract
A57: =IF($D57="","",COUNTA($D$4:$D57)) -> 54 | B57: =IF($D57="","",IF($L57="","Contact",LOOKUP($K57,$AA$5:$AA$8,$AB$5:$AB$8))) -> Contact | C57: Russia | D57: Rate Hawk | E57: 3rd Party Hotel | F57: Mid | G57: 🔴 Full (100%) | I57: SLA | J57: Sophia | K57: {=IF($D57="","",SUMPRODUCT(MAX(($O57:$Y57<>"")*$AA$3:$AK$3)))} -> 0 | L57: =IF(COUNT($O57:$Y57)=0,"",MAX($O57:$Y57)) | M57: =IF($L57="","",TODAY()-$L57) | N57: =IF($L57="","No Record",IF($K57>=1,"Live",IF($M57>=90,"Stalled 90d+",IF($M57>=60,"Stalled 60d+",IF($M57>=30,"Stalled 30d+","In Progress"))))) -> No Record | Z57: Contact
A58: =IF($D58="","",COUNTA($D$4:$D58)) -> 55 | B58: =IF($D58="","",IF($L58="","Contact",LOOKUP($K58,$AA$5:$AA$8,$AB$5:$AB$8))) -> Contact | C58: Spain | D58: Restel Hotels | E58: 3rd Party Hotel | F58: High | G58: 🔴 Full (100%) | I58: SLA | J58: Sophia | K58: {=IF($D58="","",SUMPRODUCT(MAX(($O58:$Y58<>"")*$AA$3:$AK$3)))} -> 0 | L58: =IF(COUNT($O58:$Y58)=0,"",MAX($O58:$Y58)) | M58: =IF($L58="","",TODAY()-$L58) | N58: =IF($L58="","No Record",IF($K58>=1,"Live",IF($M58>=90,"Stalled 90d+",IF($M58>=60,"Stalled 60d+",IF($M58>=30,"Stalled 30d+","In Progress"))))) -> No Record | Z58: NDA/Contract
A59: =IF($D59="","",COUNTA($D$4:$D59)) -> 56 | B59: =IF($D59="","",IF($L59="","Contact",LOOKUP($K59,$AA$5:$AA$8,$AB$5:$AB$8))) -> Contact | D59: Prime Travel | E59: 3rd Party Hotel | F59: Mid | G59: 🟢 Minimal (5-10%) | I59: SLA | J59: Sophia | K59: {=IF($D59="","",SUMPRODUCT(MAX(($O59:$Y59<>"")*$AA$3:$AK$3)))} -> 0 | L59: =IF(COUNT($O59:$Y59)=0,"",MAX($O59:$Y59)) | M59: =IF($L59="","",TODAY()-$L59) | N59: =IF($L59="","No Record",IF($K59>=1,"Live",IF($M59>=90,"Stalled 90d+",IF($M59>=60,"Stalled 60d+",IF($M59>=30,"Stalled 30d+","In Progress"))))) -> No Record | Z59: Contact
A60: =IF($D60="","",COUNTA($D$4:$D60)) -> 57 | B60: =IF($D60="","",IF($L60="","Contact",LOOKUP($K60,$AA$5:$AA$8,$AB$5:$AB$8))) -> Contact | C60: Thailand | D60: MG Group | E60: 3rd Party Hotel | F60: Mid | G60: 🟢 Minimal (5-10%) | I60: SLA | J60: Sophia | K60: {=IF($D60="","",SUMPRODUCT(MAX(($O60:$Y60<>"")*$AA$3:$AK$3)))} -> 0 | L60: =IF(COUNT($O60:$Y60)=0,"",MAX($O60:$Y60)) | M60: =IF($L60="","",TODAY()-$L60) | N60: =IF($L60="","No Record",IF($K60>=1,"Live",IF($M60>=90,"Stalled 90d+",IF($M60>=60,"Stalled 60d+",IF($M60>=30,"Stalled 30d+","In Progress"))))) -> No Record | Z60: NDA/Contract
A61: =IF($D61="","",COUNTA($D$4:$D61)) -> 58 | B61: =IF($D61="","",IF($L61="","Contact",LOOKUP($K61,$AA$5:$AA$8,$AB$5:$AB$8))) -> Contact | C61: Spain | D61: Welcomebeds | E61: 3rd Party Hotel | F61: Mid | G61: 🟢 Minimal (5-10%) | I61: SLA | J61: Sophia | K61: {=IF($D61="","",SUMPRODUCT(MAX(($O61:$Y61<>"")*$AA$3:$AK$3)))} -> 0 | L61: =IF(COUNT($O61:$Y61)=0,"",MAX($O61:$Y61)) | M61: =IF($L61="","",TODAY()-$L61) | N61: =IF($L61="","No Record",IF($K61>=1,"Live",IF($M61>=90,"Stalled 90d+",IF($M61>=60,"Stalled 60d+",IF($M61>=30,"Stalled 30d+","In Progress"))))) -> No Record | Z61: Contact
A62: =IF($D62="","",COUNTA($D$4:$D62)) -> 59 | B62: =IF($D62="","",IF($L62="","Contact",LOOKUP($K62,$AA$5:$AA$8,$AB$5:$AB$8))) -> Contact | C62: UK | D62: G2 Travel | E62: 3rd Party Hotel | F62: Mid | G62: 🔴 Full (100%) | I62: SLA | J62: Sophia | K62: {=IF($D62="","",SUMPRODUCT(MAX(($O62:$Y62<>"")*$AA$3:$AK$3)))} -> 0 | L62: =IF(COUNT($O62:$Y62)=0,"",MAX($O62:$Y62)) | M62: =IF($L62="","",TODAY()-$L62) | N62: =IF($L62="","No Record",IF($K62>=1,"Live",IF($M62>=90,"Stalled 90d+",IF($M62>=60,"Stalled 60d+",IF($M62>=30,"Stalled 30d+","In Progress"))))) -> No Record | Z62: NDA/Contract
A63: =IF($D63="","",COUNTA($D$4:$D63)) -> 60 | B63: =IF($D63="","",IF($L63="","Contact",LOOKUP($K63,$AA$5:$AA$8,$AB$5:$AB$8))) -> Contact | C63: Israel | D63: Go Global | E63: 3rd Party Hotel | F63: High | G63: 🔴 Full (100%) | I63: SLA | J63: Sophia | K63: {=IF($D63="","",SUMPRODUCT(MAX(($O63:$Y63<>"")*$AA$3:$AK$3)))} -> 0 | L63: =IF(COUNT($O63:$Y63)=0,"",MAX($O63:$Y63)) | M63: =IF($L63="","",TODAY()-$L63) | N63: =IF($L63="","No Record",IF($K63>=1,"Live",IF($M63>=90,"Stalled 90d+",IF($M63>=60,"Stalled 60d+",IF($M63>=30,"Stalled 30d+","In Progress"))))) -> No Record | Z63: NDA/Contract
A64: =IF($D64="","",COUNTA($D$4:$D64)) -> 61 | B64: =IF($D64="","",IF($L64="","Contact",LOOKUP($K64,$AA$5:$AA$8,$AB$5:$AB$8))) -> Contact | C64: Japan | D64: Miki | E64: 3rd Party Hotel | F64: Mid | G64: 🔴 Full (100%) | I64: SLA | J64: Sophia | K64: {=IF($D64="","",SUMPRODUCT(MAX(($O64:$Y64<>"")*$AA$3:$AK$3)))} -> 0 | L64: =IF(COUNT($O64:$Y64)=0,"",MAX($O64:$Y64)) | M64: =IF($L64="","",TODAY()-$L64) | N64: =IF($L64="","No Record",IF($K64>=1,"Live",IF($M64>=90,"Stalled 90d+",IF($M64>=60,"Stalled 60d+",IF($M64>=30,"Stalled 30d+","In Progress"))))) -> No Record | Z64: Contact
A65: =IF($D65="","",COUNTA($D$4:$D65)) -> 62 | B65: =IF($D65="","",IF($L65="","Contact",LOOKUP($K65,$AA$5:$AA$8,$AB$5:$AB$8))) -> Contact | C65: China | D65: Accomy | E65: 3rd Party Hotel | F65: Mid | G65: 🔴 Full (100%) | I65: SLA | J65: Sophia | K65: {=IF($D65="","",SUMPRODUCT(MAX(($O65:$Y65<>"")*$AA$3:$AK$3)))} -> 0 | L65: =IF(COUNT($O65:$Y65)=0,"",MAX($O65:$Y65)) | M65: =IF($L65="","",TODAY()-$L65) | N65: =IF($L65="","No Record",IF($K65>=1,"Live",IF($M65>=90,"Stalled 90d+",IF($M65>=60,"Stalled 60d+",IF($M65>=30,"Stalled 30d+","In Progress"))))) -> No Record | Z65: Contact
A66: =IF($D66="","",COUNTA($D$4:$D66)) -> 63 | B66: =IF($D66="","",IF($L66="","Contact",LOOKUP($K66,$AA$5:$AA$8,$AB$5:$AB$8))) -> Contact | C66: Taiwan | D66: ABC Travel | E66: 3rd Party Hotel | F66: High | G66: 🔴 Full (100%) | I66: SLA | J66: Sophia | K66: {=IF($D66="","",SUMPRODUCT(MAX(($O66:$Y66<>"")*$AA$3:$AK$3)))} -> 0 | L66: =IF(COUNT($O66:$Y66)=0,"",MAX($O66:$Y66)) | M66: =IF($L66="","",TODAY()-$L66) | N66: =IF($L66="","No Record",IF($K66>=1,"Live",IF($M66>=90,"Stalled 90d+",IF($M66>=60,"Stalled 60d+",IF($M66>=30,"Stalled 30d+","In Progress"))))) -> No Record | Z66: Contact
A67: =IF($D67="","",COUNTA($D$4:$D67)) -> 64 | B67: =IF($D67="","",IF($L67="","Contact",LOOKUP($K67,$AA$5:$AA$8,$AB$5:$AB$8))) -> NDA/Contract | C67: Indonesia | D67: Tiket.com | E67: 3rd Party Hotel | F67: Low | G67: 🔴 Full (100%) | I67: SLA | J67: Sophia | K67: {=IF($D67="","",SUMPRODUCT(MAX(($O67:$Y67<>"")*$AA$3:$AK$3)))} -> 0.2 | L67: =IF(COUNT($O67:$Y67)=0,"",MAX($O67:$Y67)) -> 46246 | M67: =IF($L67="","",TODAY()-$L67) -> 10 | N67: =IF($L67="","No Record",IF($K67>=1,"Live",IF($M67>=90,"Stalled 90d+",IF($M67>=60,"Stalled 60d+",IF($M67>=30,"Stalled 30d+","In Progress"))))) -> In Progress | O67: 46246 | Z67: NDA/Contract
A68: =IF($D68="","",COUNTA($D$4:$D68)) -> 65 | B68: =IF($D68="","",IF($L68="","Contact",LOOKUP($K68,$AA$5:$AA$8,$AB$5:$AB$8))) -> Contact | C68: Japan | D68: JTR | E68: 3rd Party Activity | F68: Low | G68: 🔴 Full (100%) | I68: SLA | J68: Sophia | K68: {=IF($D68="","",SUMPRODUCT(MAX(($O68:$Y68<>"")*$AA$3:$AK$3)))} -> 0 | L68: =IF(COUNT($O68:$Y68)=0,"",MAX($O68:$Y68)) | M68: =IF($L68="","",TODAY()-$L68) | N68: =IF($L68="","No Record",IF($K68>=1,"Live",IF($M68>=90,"Stalled 90d+",IF($M68>=60,"Stalled 60d+",IF($M68>=30,"Stalled 30d+","In Progress"))))) -> No Record | Z68: In Development
A69: =IF($D69="","",COUNTA($D$4:$D69)) -> 66 | B69: =IF($D69="","",IF($L69="","Contact",LOOKUP($K69,$AA$5:$AA$8,$AB$5:$AB$8))) -> Contact | C69: Japan | D69: Linktivity | E69: 3rd Party Activity | F69: Low | G69: 🔴 Full (100%) | I69: SLA | J69: Sophia | K69: {=IF($D69="","",SUMPRODUCT(MAX(($O69:$Y69<>"")*$AA$3:$AK$3)))} -> 0 | L69: =IF(COUNT($O69:$Y69)=0,"",MAX($O69:$Y69)) | M69: =IF($L69="","",TODAY()-$L69) | N69: =IF($L69="","No Record",IF($K69>=1,"Live",IF($M69>=90,"Stalled 90d+",IF($M69>=60,"Stalled 60d+",IF($M69>=30,"Stalled 30d+","In Progress"))))) -> No Record | Z69: Contact
A70: =IF($D70="","",COUNTA($D$4:$D70)) -> 67 | B70: =IF($D70="","",IF($L70="","Contact",LOOKUP($K70,$AA$5:$AA$8,$AB$5:$AB$8))) -> Contact | C70: Japan | D70: Toto booking | E70: 3rd Party Activity | F70: Low | G70: 🔴 Full (100%) | I70: SLA | J70: Sophia | K70: {=IF($D70="","",SUMPRODUCT(MAX(($O70:$Y70<>"")*$AA$3:$AK$3)))} -> 0 | L70: =IF(COUNT($O70:$Y70)=0,"",MAX($O70:$Y70)) | M70: =IF($L70="","",TODAY()-$L70) | N70: =IF($L70="","No Record",IF($K70>=1,"Live",IF($M70>=90,"Stalled 90d+",IF($M70>=60,"Stalled 60d+",IF($M70>=30,"Stalled 30d+","In Progress"))))) -> No Record | Z70: Contact
A71: =IF($D71="","",COUNTA($D$4:$D71)) -> 68 | B71: =IF($D71="","",IF($L71="","Contact",LOOKUP($K71,$AA$5:$AA$8,$AB$5:$AB$8))) -> Live | C71: Singapore | D71: Agoda | E71: Channel API | G71: 🔴 Full (100%) | I71: GSM | J71: Aiden | K71: {=IF($D71="","",SUMPRODUCT(MAX(($O71:$Y71<>"")*$AA$3:$AK$3)))} -> 1 | L71: =IF(COUNT($O71:$Y71)=0,"",MAX($O71:$Y71)) -> 43845 | M71: =IF($L71="","",TODAY()-$L71) -> 2411 | N71: =IF($L71="","No Record",IF($K71>=1,"Live",IF($M71>=90,"Stalled 90d+",IF($M71>=60,"Stalled 60d+",IF($M71>=30,"Stalled 30d+","In Progress"))))) -> Live | Y71: 43845 | Z71: Contact
A72: =IF($D72="","",COUNTA($D$4:$D72)) -> 69 | B72: =IF($D72="","",IF($L72="","Contact",LOOKUP($K72,$AA$5:$AA$8,$AB$5:$AB$8))) -> Live | C72: China | D72: Qunar | E72: Channel API | G72: 🔴 Full (100%) | I72: GSM | J72: Grace | K72: {=IF($D72="","",SUMPRODUCT(MAX(($O72:$Y72<>"")*$AA$3:$AK$3)))} -> 1 | L72: =IF(COUNT($O72:$Y72)=0,"",MAX($O72:$Y72)) -> 45959 | M72: =IF($L72="","",TODAY()-$L72) -> 297 | N72: =IF($L72="","No Record",IF($K72>=1,"Live",IF($M72>=90,"Stalled 90d+",IF($M72>=60,"Stalled 60d+",IF($M72>=30,"Stalled 30d+","In Progress"))))) -> Live | Y72: 45959 | Z72: Contact
A73: =IF($D73="","",COUNTA($D$4:$D73)) -> 70 | B73: =IF($D73="","",IF($L73="","Contact",LOOKUP($K73,$AA$5:$AA$8,$AB$5:$AB$8))) -> Live | C73: China | D73: Alitrip | E73: Channel API | G73: 🔴 Full (100%) | I73: GSM | J73: Grace | K73: {=IF($D73="","",SUMPRODUCT(MAX(($O73:$Y73<>"")*$AA$3:$AK$3)))} -> 1 | L73: =IF(COUNT($O73:$Y73)=0,"",MAX($O73:$Y73)) -> 45959 | M73: =IF($L73="","",TODAY()-$L73) -> 297 | N73: =IF($L73="","No Record",IF($K73>=1,"Live",IF($M73>=90,"Stalled 90d+",IF($M73>=60,"Stalled 60d+",IF($M73>=30,"Stalled 30d+","In Progress"))))) -> Live | P73: 43892 | Y73: 45959 | Z73: Contact
A74: =IF($D74="","",COUNTA($D$4:$D74)) -> 71 | B74: =IF($D74="","",IF($L74="","Contact",LOOKUP($K74,$AA$5:$AA$8,$AB$5:$AB$8))) -> Live | C74: Korea | D74: Myrealtrip API | E74: Channel API | G74: 🟢 Minimal (5-10%) | I74: GSM | J74: Aiden | K74: {=IF($D74="","",SUMPRODUCT(MAX(($O74:$Y74<>"")*$AA$3:$AK$3)))} -> 1 | L74: =IF(COUNT($O74:$Y74)=0,"",MAX($O74:$Y74)) -> 45959 | M74: =IF($L74="","",TODAY()-$L74) -> 297 | N74: =IF($L74="","No Record",IF($K74>=1,"Live",IF($M74>=90,"Stalled 90d+",IF($M74>=60,"Stalled 60d+",IF($M74>=30,"Stalled 30d+","In Progress"))))) -> Live | Y74: 45959 | Z74: Contact
A75: =IF($D75="","",COUNTA($D$4:$D75)) -> 72 | B75: =IF($D75="","",IF($L75="","Contact",LOOKUP($K75,$AA$5:$AA$8,$AB$5:$AB$8))) -> Live | C75: Japan | D75: Hikari Global | E75: Channel API | G75: 🟢 Minimal (5-10%) | I75: GSM | J75: Aiden | K75: {=IF($D75="","",SUMPRODUCT(MAX(($O75:$Y75<>"")*$AA$3:$AK$3)))} -> 1 | L75: =IF(COUNT($O75:$Y75)=0,"",MAX($O75:$Y75)) -> 45959 | M75: =IF($L75="","",TODAY()-$L75) -> 297 | N75: =IF($L75="","No Record",IF($K75>=1,"Live",IF($M75>=90,"Stalled 90d+",IF($M75>=60,"Stalled 60d+",IF($M75>=30,"Stalled 30d+","In Progress"))))) -> Live | Y75: 45959 | Z75: Contact
A76: =IF($D76="","",COUNTA($D$4:$D76)) -> 73 | B76: =IF($D76="","",IF($L76="","Contact",LOOKUP($K76,$AA$5:$AA$8,$AB$5:$AB$8))) -> Live | C76: Korea | D76: Tripbtoz | E76: Channel API | G76: 🟢 Minimal (5-10%) | I76: GSM | J76: Aiden | K76: {=IF($D76="","",SUMPRODUCT(MAX(($O76:$Y76<>"")*$AA$3:$AK$3)))} -> 1 | L76: =IF(COUNT($O76:$Y76)=0,"",MAX($O76:$Y76)) -> 45959 | M76: =IF($L76="","",TODAY()-$L76) -> 297 | N76: =IF($L76="","No Record",IF($K76>=1,"Live",IF($M76>=90,"Stalled 90d+",IF($M76>=60,"Stalled 60d+",IF($M76>=30,"Stalled 30d+","In Progress"))))) -> Live | Y76: 45959 | Z76: Contact
A77: =IF($D77="","",COUNTA($D$4:$D77)) -> 74 | B77: =IF($D77="","",IF($L77="","Contact",LOOKUP($K77,$AA$5:$AA$8,$AB$5:$AB$8))) -> Live | C77: Korea | D77: Hotelpass | E77: Channel API | G77: 🟢 Minimal (5-10%) | I77: GSM | J77: Aiden | K77: {=IF($D77="","",SUMPRODUCT(MAX(($O77:$Y77<>"")*$AA$3:$AK$3)))} -> 1 | L77: =IF(COUNT($O77:$Y77)=0,"",MAX($O77:$Y77)) -> 45959 | M77: =IF($L77="","",TODAY()-$L77) -> 297 | N77: =IF($L77="","No Record",IF($K77>=1,"Live",IF($M77>=90,"Stalled 90d+",IF($M77>=60,"Stalled 60d+",IF($M77>=30,"Stalled 30d+","In Progress"))))) -> Live | Y77: 45959 | Z77: Contact
A78: =IF($D78="","",COUNTA($D$4:$D78)) -> 75 | B78: =IF($D78="","",IF($L78="","Contact",LOOKUP($K78,$AA$5:$AA$8,$AB$5:$AB$8))) -> Live | C78: China | D78: Toptown API (시트립 Vacation 자회사) | E78: Channel API | G78: 🟢 Minimal (5-10%) | I78: GSM | J78: Grace | K78: {=IF($D78="","",SUMPRODUCT(MAX(($O78:$Y78<>"")*$AA$3:$AK$3)))} -> 1 | L78: =IF(COUNT($O78:$Y78)=0,"",MAX($O78:$Y78)) -> 45959 | M78: =IF($L78="","",TODAY()-$L78) -> 297 | N78: =IF($L78="","No Record",IF($K78>=1,"Live",IF($M78>=90,"Stalled 90d+",IF($M78>=60,"Stalled 60d+",IF($M78>=30,"Stalled 30d+","In Progress"))))) -> Live | O78: 45195 | P78: 45217 | Q78: 45217 | Y78: 45959 | Z78: NDA/Contract
A79: =IF($D79="","",COUNTA($D$4:$D79)) -> 76 | B79: =IF($D79="","",IF($L79="","Contact",LOOKUP($K79,$AA$5:$AA$8,$AB$5:$AB$8))) -> Live | C79: Indonesia | D79: Traveloka | E79: Channel API | G79: 🔴 Full (100%) | I79: GSM | J79: Aiden | K79: {=IF($D79="","",SUMPRODUCT(MAX(($O79:$Y79<>"")*$AA$3:$AK$3)))} -> 1 | L79: =IF(COUNT($O79:$Y79)=0,"",MAX($O79:$Y79)) -> 45959 | M79: =IF($L79="","",TODAY()-$L79) -> 297 | N79: =IF($L79="","No Record",IF($K79>=1,"Live",IF($M79>=90,"Stalled 90d+",IF($M79>=60,"Stalled 60d+",IF($M79>=30,"Stalled 30d+","In Progress"))))) -> Live | Y79: 45959 | Z79: Contact
A80: =IF($D80="","",COUNTA($D$4:$D80)) -> 77 | B80: =IF($D80="","",IF($L80="","Contact",LOOKUP($K80,$AA$5:$AA$8,$AB$5:$AB$8))) -> Live | C80: Thailand | D80: MG Group (Room Deal) | E80: Channel API | G80: 🟢 Minimal (5-10%) | I80: GSM | J80: Aiden | K80: {=IF($D80="","",SUMPRODUCT(MAX(($O80:$Y80<>"")*$AA$3:$AK$3)))} -> 1 | L80: =IF(COUNT($O80:$Y80)=0,"",MAX($O80:$Y80)) -> 46029 | M80: =IF($L80="","",TODAY()-$L80) -> 227 | N80: =IF($L80="","No Record",IF($K80>=1,"Live",IF($M80>=90,"Stalled 90d+",IF($M80>=60,"Stalled 60d+",IF($M80>=30,"Stalled 30d+","In Progress"))))) -> Live | Y80: 46029 | Z80: Live
A81: =IF($D81="","",COUNTA($D$4:$D81)) -> 78 | B81: =IF($D81="","",IF($L81="","Contact",LOOKUP($K81,$AA$5:$AA$8,$AB$5:$AB$8))) -> Live | C81: Japan | D81: RTX (Rakuten) | E81: Channel API | G81: 🟢 Minimal (5-10%) | I81: GSM | J81: Aiden | K81: {=IF($D81="","",SUMPRODUCT(MAX(($O81:$Y81<>"")*$AA$3:$AK$3)))} -> 1 | L81: =IF(COUNT($O81:$Y81)=0,"",MAX($O81:$Y81)) -> 46029 | M81: =IF($L81="","",TODAY()-$L81) -> 227 | N81: =IF($L81="","No Record",IF($K81>=1,"Live",IF($M81>=90,"Stalled 90d+",IF($M81>=60,"Stalled 60d+",IF($M81>=30,"Stalled 30d+","In Progress"))))) -> Live | Y81: 46029 | Z81: Live
A82: =IF($D82="","",COUNTA($D$4:$D82)) -> 79 | B82: =IF($D82="","",IF($L82="","Contact",LOOKUP($K82,$AA$5:$AA$8,$AB$5:$AB$8))) -> Live | C82: China | D82: SS Booking | E82: Channel API | G82: 🟢 Minimal (5-10%) | I82: GSM | J82: Grace | K82: {=IF($D82="","",SUMPRODUCT(MAX(($O82:$Y82<>"")*$AA$3:$AK$3)))} -> 1 | L82: =IF(COUNT($O82:$Y82)=0,"",MAX($O82:$Y82)) -> 46029 | M82: =IF($L82="","",TODAY()-$L82) -> 227 | N82: =IF($L82="","No Record",IF($K82>=1,"Live",IF($M82>=90,"Stalled 90d+",IF($M82>=60,"Stalled 60d+",IF($M82>=30,"Stalled 30d+","In Progress"))))) -> Live | O82: 45940 | S82: 45974 | T82: 45985 | Y82: 46029 | Z82: Live
A83: =IF($D83="","",COUNTA($D$4:$D83)) -> 80 | B83: =IF($D83="","",IF($L83="","Contact",LOOKUP($K83,$AA$5:$AA$8,$AB$5:$AB$8))) -> Live | C83: Korea | D83: Linkstay | E83: Channel API | G83: 🟢 Minimal (5-10%) | I83: GSM | J83: Grace | K83: {=IF($D83="","",SUMPRODUCT(MAX(($O83:$Y83<>"")*$AA$3:$AK$3)))} -> 1 | L83: =IF(COUNT($O83:$Y83)=0,"",MAX($O83:$Y83)) -> 46149 | M83: =IF($L83="","",TODAY()-$L83) -> 107 | N83: =IF($L83="","No Record",IF($K83>=1,"Live",IF($M83>=90,"Stalled 90d+",IF($M83>=60,"Stalled 60d+",IF($M83>=30,"Stalled 30d+","In Progress"))))) -> Live | O83: 45926 | P83: 46031 | Q83: 46031 | T83: 46141 | U83: 46149 | Y83: 46029 | Z83: Live
A84: =IF($D84="","",COUNTA($D$4:$D84)) -> 81 | B84: =IF($D84="","",IF($L84="","Contact",LOOKUP($K84,$AA$5:$AA$8,$AB$5:$AB$8))) -> Live | C84: Korea | D84: Hotelbank | E84: Channel API | G84: 🟢 Minimal (5-10%) | I84: GSM | J84: Grace | K84: {=IF($D84="","",SUMPRODUCT(MAX(($O84:$Y84<>"")*$AA$3:$AK$3)))} -> 1 | L84: =IF(COUNT($O84:$Y84)=0,"",MAX($O84:$Y84)) -> 46029 | M84: =IF($L84="","",TODAY()-$L84) -> 227 | N84: =IF($L84="","No Record",IF($K84>=1,"Live",IF($M84>=90,"Stalled 90d+",IF($M84>=60,"Stalled 60d+",IF($M84>=30,"Stalled 30d+","In Progress"))))) -> Live | P84: 45991 | R84: 45992 | S84: 45992 | Y84: 46029 | Z84: Live
A85: =IF($D85="","",COUNTA($D$4:$D85)) -> 82 | B85: =IF($D85="","",IF($L85="","Contact",LOOKUP($K85,$AA$5:$AA$8,$AB$5:$AB$8))) -> Live | C85: China | D85: Huamin | E85: Channel API | G85: 🟢 Minimal (5-10%) | I85: GSM | J85: Grace | K85: {=IF($D85="","",SUMPRODUCT(MAX(($O85:$Y85<>"")*$AA$3:$AK$3)))} -> 1 | L85: =IF(COUNT($O85:$Y85)=0,"",MAX($O85:$Y85)) -> 46029 | M85: =IF($L85="","",TODAY()-$L85) -> 227 | N85: =IF($L85="","No Record",IF($K85>=1,"Live",IF($M85>=90,"Stalled 90d+",IF($M85>=60,"Stalled 60d+",IF($M85>=30,"Stalled 30d+","In Progress"))))) -> Live | O85: 45922 | R85: 45955 | S85: 46013 | Y85: 46029 | Z85: Live
A86: =IF($D86="","",COUNTA($D$4:$D86)) -> 83 | B86: =IF($D86="","",IF($L86="","Contact",LOOKUP($K86,$AA$5:$AA$8,$AB$5:$AB$8))) -> Live | C86: China | D86: Bingtrip | E86: Channel API | G86: 🟢 Minimal (5-10%) | I86: GSM | J86: Grace | K86: {=IF($D86="","",SUMPRODUCT(MAX(($O86:$Y86<>"")*$AA$3:$AK$3)))} -> 1 | L86: =IF(COUNT($O86:$Y86)=0,"",MAX($O86:$Y86)) -> 46054 | M86: =IF($L86="","",TODAY()-$L86) -> 202 | N86: =IF($L86="","No Record",IF($K86>=1,"Live",IF($M86>=90,"Stalled 90d+",IF($M86>=60,"Stalled 60d+",IF($M86>=30,"Stalled 30d+","In Progress"))))) -> Live | O86: 46006 | R86: 46054 | Y86: 46029 | Z86: Live
A87: =IF($D87="","",COUNTA($D$4:$D87)) -> 84 | B87: =IF($D87="","",IF($L87="","Contact",LOOKUP($K87,$AA$5:$AA$8,$AB$5:$AB$8))) -> Live | C87: Japan | D87: RTX (Rakuten) | E87: 3rd Party Hotel | G87: 🔴 Full (100%) | I87: SLA | J87: Sophia | K87: {=IF($D87="","",SUMPRODUCT(MAX(($O87:$Y87<>"")*$AA$3:$AK$3)))} -> 1 | L87: =IF(COUNT($O87:$Y87)=0,"",MAX($O87:$Y87)) -> 46029 | M87: =IF($L87="","",TODAY()-$L87) -> 227 | N87: =IF($L87="","No Record",IF($K87>=1,"Live",IF($M87>=90,"Stalled 90d+",IF($M87>=60,"Stalled 60d+",IF($M87>=30,"Stalled 30d+","In Progress"))))) -> Live | Y87: 46029 | Z87: Live
A88: =IF($D88="","",COUNTA($D$4:$D88)) -> 85 | B88: =IF($D88="","",IF($L88="","Contact",LOOKUP($K88,$AA$5:$AA$8,$AB$5:$AB$8))) -> Live | C88: China | D88: Ctrip Korea | E88: Channel API | G88: 🔴 Full (100%) | I88: GSM | J88: Grace | K88: {=IF($D88="","",SUMPRODUCT(MAX(($O88:$Y88<>"")*$AA$3:$AK$3)))} -> 1 | L88: =IF(COUNT($O88:$Y88)=0,"",MAX($O88:$Y88)) -> 46016 | M88: =IF($L88="","",TODAY()-$L88) -> 240 | N88: =IF($L88="","No Record",IF($K88>=1,"Live",IF($M88>=90,"Stalled 90d+",IF($M88>=60,"Stalled 60d+",IF($M88>=30,"Stalled 30d+","In Progress"))))) -> Live | O88: 45692 | P88: 45721 | Q88: 45811 | R88: 45925 | S88: 45930 | T88: 45932 | U88: 45955 | V88: 45960 | W88: 45972 | X88: 45973 | Y88: 46016 | Z88: Live
A89: =IF($D89="","",COUNTA($D$4:$D89)) -> 86 | B89: =IF($D89="","",IF($L89="","Contact",LOOKUP($K89,$AA$5:$AA$8,$AB$5:$AB$8))) -> Live | C89: China | D89: Dida | E89: Channel API | G89: 🟢 Minimal (5-10%) | I89: GSM | J89: Grace | K89: {=IF($D89="","",SUMPRODUCT(MAX(($O89:$Y89<>"")*$AA$3:$AK$3)))} -> 1 | L89: =IF(COUNT($O89:$Y89)=0,"",MAX($O89:$Y89)) -> 45959 | M89: =IF($L89="","",TODAY()-$L89) -> 297 | N89: =IF($L89="","No Record",IF($K89>=1,"Live",IF($M89>=90,"Stalled 90d+",IF($M89>=60,"Stalled 60d+",IF($M89>=30,"Stalled 30d+","In Progress"))))) -> Live | P89: 44822 | W89: 44876 | Y89: 45959 | Z89: Live
A90: =IF($D90="","",COUNTA($D$4:$D90)) -> 87 | B90: =IF($D90="","",IF($L90="","Contact",LOOKUP($K90,$AA$5:$AA$8,$AB$5:$AB$8))) -> Live | C90: China | D90: KAKE | E90: Channel API | G90: 🟢 Minimal (5-10%) | I90: GSM | J90: Grace | K90: {=IF($D90="","",SUMPRODUCT(MAX(($O90:$Y90<>"")*$AA$3:$AK$3)))} -> 1 | L90: =IF(COUNT($O90:$Y90)=0,"",MAX($O90:$Y90)) -> 45990 | M90: =IF($L90="","",TODAY()-$L90) -> 266 | N90: =IF($L90="","No Record",IF($K90>=1,"Live",IF($M90>=90,"Stalled 90d+",IF($M90>=60,"Stalled 60d+",IF($M90>=30,"Stalled 30d+","In Progress"))))) -> Live | O90: 45869 | P90: 45875 | Q90: 45874 | R90: 45931 | S90: 45908 | T90: 45930 | U90: 45952 | W90: 45960 | X90: 45961 | Y90: 45990 | Z90: Live
A91: =IF($D91="","",COUNTA($D$4:$D91)) -> 88 | B91: =IF($D91="","",IF($L91="","Contact",LOOKUP($K91,$AA$5:$AA$8,$AB$5:$AB$8))) -> Live | C91: China | D91: Hey Trip | E91: Channel API | G91: 🟢 Minimal (5-10%) | I91: GSM | J91: Grace | K91: {=IF($D91="","",SUMPRODUCT(MAX(($O91:$Y91<>"")*$AA$3:$AK$3)))} -> 1 | L91: =IF(COUNT($O91:$Y91)=0,"",MAX($O91:$Y91)) -> 45965 | M91: =IF($L91="","",TODAY()-$L91) -> 291 | N91: =IF($L91="","No Record",IF($K91>=1,"Live",IF($M91>=90,"Stalled 90d+",IF($M91>=60,"Stalled 60d+",IF($M91>=30,"Stalled 30d+","In Progress"))))) -> Live | O91: 45877 | P91: 45926 | R91: 45960 | S91: 45915 | T91: 45943 | U91: 45947 | W91: 45951 | X91: 45951 | Y91: 45965 | Z91: Live
A92: =IF($D92="","",COUNTA($D$4:$D92)) -> 89 | B92: =IF($D92="","",IF($L92="","Contact",LOOKUP($K92,$AA$5:$AA$8,$AB$5:$AB$8))) -> Live | C92: Taiwan | D92: Coolprice | E92: Channel API | G92: 🟢 Minimal (5-10%) | I92: GSM | J92: Grace | K92: {=IF($D92="","",SUMPRODUCT(MAX(($O92:$Y92<>"")*$AA$3:$AK$3)))} -> 1 | L92: =IF(COUNT($O92:$Y92)=0,"",MAX($O92:$Y92)) -> 45990 | M92: =IF($L92="","",TODAY()-$L92) -> 266 | N92: =IF($L92="","No Record",IF($K92>=1,"Live",IF($M92>=90,"Stalled 90d+",IF($M92>=60,"Stalled 60d+",IF($M92>=30,"Stalled 30d+","In Progress"))))) -> Live | O92: 45918 | T92: 45915 | W92: 45968 | Y92: 45990 | Z92: Live
A93: =IF($D93="","",COUNTA($D$4:$D93)) -> 90 | B93: =IF($D93="","",IF($L93="","Contact",LOOKUP($K93,$AA$5:$AA$8,$AB$5:$AB$8))) -> Live | C93: China | D93: Tourmind | E93: Channel API | G93: 🟢 Minimal (5-10%) | I93: GSM | J93: Grace | K93: {=IF($D93="","",SUMPRODUCT(MAX(($O93:$Y93<>"")*$AA$3:$AK$3)))} -> 1 | L93: =IF(COUNT($O93:$Y93)=0,"",MAX($O93:$Y93)) -> 45965 | M93: =IF($L93="","",TODAY()-$L93) -> 291 | N93: =IF($L93="","No Record",IF($K93>=1,"Live",IF($M93>=90,"Stalled 90d+",IF($M93>=60,"Stalled 60d+",IF($M93>=30,"Stalled 30d+","In Progress"))))) -> Live | P93: 45904 | Q93: 45905 | U93: 45916 | W93: 45940 | X93: 45940 | Y93: 45965 | Z93: Live
A94: =IF($D94="","",COUNTA($D$4:$D94)) -> 91 | B94: =IF($D94="","",IF($L94="","Contact",LOOKUP($K94,$AA$5:$AA$8,$AB$5:$AB$8))) -> Live | C94: China | D94: Meituan | E94: Channel API | G94: 🔴 Full (100%) | I94: GSM | J94: Grace | K94: {=IF($D94="","",SUMPRODUCT(MAX(($O94:$Y94<>"")*$AA$3:$AK$3)))} -> 1 | L94: =IF(COUNT($O94:$Y94)=0,"",MAX($O94:$Y94)) -> 45959 | M94: =IF($L94="","",TODAY()-$L94) -> 297 | N94: =IF($L94="","No Record",IF($K94>=1,"Live",IF($M94>=90,"Stalled 90d+",IF($M94>=60,"Stalled 60d+",IF($M94>=30,"Stalled 30d+","In Progress"))))) -> Live | O94: 43888 | Y94: 45959 | Z94: Live
A95: =IF($D95="","",COUNTA($D$4:$D95)) -> 92 | B95: =IF($D95="","",IF($L95="","Contact",LOOKUP($K95,$AA$5:$AA$8,$AB$5:$AB$8))) -> Live | C95: China | D95: Elong | E95: Channel API | G95: 🔴 Full (100%) | I95: GSM | J95: Grace | K95: {=IF($D95="","",SUMPRODUCT(MAX(($O95:$Y95<>"")*$AA$3:$AK$3)))} -> 1 | L95: =IF(COUNT($O95:$Y95)=0,"",MAX($O95:$Y95)) -> 45959 | M95: =IF($L95="","",TODAY()-$L95) -> 297 | N95: =IF($L95="","No Record",IF($K95>=1,"Live",IF($M95>=90,"Stalled 90d+",IF($M95>=60,"Stalled 60d+",IF($M95>=30,"Stalled 30d+","In Progress"))))) -> Live | P95: 43960 | Y95: 45959 | Z95: Live
A96: =IF($D96="","",COUNTA($D$4:$D96)) -> 93 | B96: =IF($D96="","",IF($L96="","Contact",LOOKUP($K96,$AA$5:$AA$8,$AB$5:$AB$8))) -> Live | C96: China | D96: PKFARE API | E96: Channel API | G96: 🟢 Minimal (5-10%) | I96: GSM | J96: Grace | K96: {=IF($D96="","",SUMPRODUCT(MAX(($O96:$Y96<>"")*$AA$3:$AK$3)))} -> 1 | L96: =IF(COUNT($O96:$Y96)=0,"",MAX($O96:$Y96)) -> 45959 | M96: =IF($L96="","",TODAY()-$L96) -> 297 | N96: =IF($L96="","No Record",IF($K96>=1,"Live",IF($M96>=90,"Stalled 90d+",IF($M96>=60,"Stalled 60d+",IF($M96>=30,"Stalled 30d+","In Progress"))))) -> Live | O96: 45228 | P96: 45251 | Q96: 45236 | Y96: 45959 | Z96: Live
A97: =IF($D97="","",COUNTA($D$4:$D97)) -> 94 | B97: =IF($D97="","",IF($L97="","Contact",LOOKUP($K97,$AA$5:$AA$8,$AB$5:$AB$8))) -> Live | C97: Vietnam | D97: Ctrip Vietnam | E97: Channel API | G97: 🔴 Full (100%) | I97: GSM | J97: Aiden | K97: {=IF($D97="","",SUMPRODUCT(MAX(($O97:$Y97<>"")*$AA$3:$AK$3)))} -> 1 | L97: =IF(COUNT($O97:$Y97)=0,"",MAX($O97:$Y97)) -> 45959 | M97: =IF($L97="","",TODAY()-$L97) -> 297 | N97: =IF($L97="","No Record",IF($K97>=1,"Live",IF($M97>=90,"Stalled 90d+",IF($M97>=60,"Stalled 60d+",IF($M97>=30,"Stalled 30d+","In Progress"))))) -> Live | Y97: 45959 | Z97: Live
A98: =IF($D98="","",COUNTA($D$4:$D98)) -> 95 | B98: =IF($D98="","",IF($L98="","Contact",LOOKUP($K98,$AA$5:$AA$8,$AB$5:$AB$8))) -> Live | C98: China | D98: Convergent API (Huizhi) | E98: Channel API | G98: 🟢 Minimal (5-10%) | I98: GSM | J98: Grace | K98: {=IF($D98="","",SUMPRODUCT(MAX(($O98:$Y98<>"")*$AA$3:$AK$3)))} -> 1 | L98: =IF(COUNT($O98:$Y98)=0,"",MAX($O98:$Y98)) -> 45959 | M98: =IF($L98="","",TODAY()-$L98) -> 297 | N98: =IF($L98="","No Record",IF($K98>=1,"Live",IF($M98>=90,"Stalled 90d+",IF($M98>=60,"Stalled 60d+",IF($M98>=30,"Stalled 30d+","In Progress"))))) -> Live | P98: 45253 | Q98: 45244 | Y98: 45959 | Z98: Live
A99: =IF($D99="","",COUNTA($D$4:$D99)) -> 96 | B99: =IF($D99="","",IF($L99="","Contact",LOOKUP($K99,$AA$5:$AA$8,$AB$5:$AB$8))) -> Live | C99: Korea | D99: triptopaz | E99: Channel API | G99: 🟢 Minimal (5-10%) | I99: GSM | J99: Aiden | K99: {=IF($D99="","",SUMPRODUCT(MAX(($O99:$Y99<>"")*$AA$3:$AK$3)))} -> 1 | L99: =IF(COUNT($O99:$Y99)=0,"",MAX($O99:$Y99)) -> 45959 | M99: =IF($L99="","",TODAY()-$L99) -> 297 | N99: =IF($L99="","No Record",IF($K99>=1,"Live",IF($M99>=90,"Stalled 90d+",IF($M99>=60,"Stalled 60d+",IF($M99>=30,"Stalled 30d+","In Progress"))))) -> Live | Y99: 45959 | Z99: Live
A100: =IF($D100="","",COUNTA($D$4:$D100)) -> 97 | B100: =IF($D100="","",IF($L100="","Contact",LOOKUP($K100,$AA$5:$AA$8,$AB$5:$AB$8))) -> Live | C100: China | D100: Qiyouji | E100: Channel API | G100: 🟢 Minimal (5-10%) | I100: GSM | J100: Grace | K100: {=IF($D100="","",SUMPRODUCT(MAX(($O100:$Y100<>"")*$AA$3:$AK$3)))} -> 1 | L100: =IF(COUNT($O100:$Y100)=0,"",MAX($O100:$Y100)) -> 45959 | M100: =IF($L100="","",TODAY()-$L100) -> 297 | N100: =IF($L100="","No Record",IF($K100>=1,"Live",IF($M100>=90,"Stalled 90d+",IF($M100>=60,"Stalled 60d+",IF($M100>=30,"Stalled 30d+","In Progress"))))) -> Live | P100: 45327 | Q100: 45327 | Y100: 45959 | Z100: Live
...

Sheet 마진변동 트래킹
A1: 📋 마진 변동 기안서 생성 프롬프트 (Margin Adjustment Proposal Prompt)
A2: 아래 프롬프트를 복사하여 Claude에 붙여넣으면 기안서가 텍스트로 생성됩니다. (Copy the prompt below and paste it into Claude to generate a proposal in text format.)
A3: ▼ 프롬프트 (아래 전체를 복사하세요) / Prompt (Copy everything below)
A4: 아래 정보를 바탕으로 고객사 마진 변동 기안서를 텍스트로 작성해줘. 표 형식 없이, 읽기 쉬운 문서 형태로 출력해줘. (Based on the information below, write a client margin adjustment proposal in text format. Output in a readable document format without tables.) --- [기본 정보 (Basic Info)] - 기안 제목(Title): {제목 입력} - 고객사명(Client): {고객사명 입력} - 담당자(PIC): {담당자명 입력} - 기안일자(Date): {YYYY-MM-DD} - 프로모션명(Promotion): {프로모션명 입력} [마진 변동 내용 (Margin Change Details)] - 기존 마진(Before Markup): {예: 25%} - 변경 마진(After Markup): {예: 22%} - 변동폭(Change): {예: -3%p} - 변동 사유(Reason): {사유 입력} [적용 일정 (Schedule)] - 적용 시작일(Start Date): {YYYY-MM-DD} - 적용 종료일(End Date): {YYYY-MM-DD} - 시작 시간(Start Time): {예: 오전 9시} - 시간대(Timezone): {예: KST / CST} [기대 효과 (Expected Effects)] 1. {기대효과 1} 2. {기대효과 2} 3. {기대효과 3} [결재 (Approval)] - 기안자(Drafter): {성명} - 1차 결재자(1st Approver): {성명} - 최종 결재자(Final Approver): {성명} --- 위 내용으로 "고객사 마진 변동 및 프로모션 진행 건 (Client Margin Adjustment & Promotion)" 형태의 공식 기안서를 작성해줘. 각 섹션에 번호를 매기고, 목적/마진변동내용/적용일정/기대효과/결재란을 포함해줘. 출력은 순수 텍스트(글)로만 해줘.
A5: 📊 마진 변동 트래킹 로그 (Margin Change Tracking Log)
A6: 번호(No.) | B6: 고객사명(Client) | C6: 담당자(PIC) | D6: 프로모션명(Promotion) | E6: 기존 마진(Before) | F6: 변경 마진(After) | G6: 변동폭(Change) | H6: 적용 시작일(Start) | I6: 적용 종료일(End) | J6: 적용 기간(Duration) | K6: 상태(Status) | L6: 결과(Result) | M6: 비고(Note) | N6: Report CEO
A7: 1 | B7: Qiyouji | C7: Grace | D7: OMH PROMOTION | E7: 0.25 | F7: 0.22 | G7: =F7-E7 -> -0.03 | H7: =DATE(2026,3,20) -> 46101 | I7: =DATE(2026,4,3) -> 46115 | J7: =IF(OR(H7="",I7=""),"",I7-H7+1) -> 15 | K7: 진행중(Active) | L7: 소폭 증가 | M7: Aiden Check | N7: ☑
A8: 2 | B8: Dida | C8: Grace | D8: OMH PROMOTION | E8: 0.25 | F8: 0.22 | G8: =F8-E8 -> -0.03 | H8: =DATE(2026,3,27) -> 46108 | I8: 46115 | J8: =IF(OR(H8="",I8=""),"",I8-H8+1) -> 8 | K8: 진행중(Active) | L8: 대폭 증가 | M8: Aiden Check | N8: ☑
A9: 3 | B9: Alitrip | C9: Grace | D9: OMH PROMOTION | E9: 0.25 | F9: 0.22 | G9: -0.03 | H9: =DATE(2026,5,25) -> 46167 | I9: =DATE(2026,6,8) -> 46181 | J9: =IF(OR(H9="",I9=""),"",I9-H9+1) -> 15 | M9: Aiden Check | N9: ☑
A10: 4 | B10: Agoda | C10: Ben | D10: OMH PROMOTION | E10: 0.47 | F10: 0.4 | G10: =IF(OR(E10="",F10=""),"",F10-E10) -> -0.07 | H10: 46175 | I10: 46184 | J10: =IF(OR(H10="",I10=""),"",I10-H10+1) -> 10 | K10: 진행중(Active) | M10: Aiden Check | N10: ☑
G11: =IF(OR(E11="",F11=""),"",F11-E11) | J11: =IF(OR(H11="",I11=""),"",I11-H11+1)
G12: =IF(OR(E12="",F12=""),"",F12-E12) | J12: =IF(OR(H12="",I12=""),"",I12-H12+1)
G13: =IF(OR(E13="",F13=""),"",F13-E13) | J13: =IF(OR(H13="",I13=""),"",I13-H13+1)
G14: =IF(OR(E14="",F14=""),"",F14-E14) | J14: =IF(OR(H14="",I14=""),"",I14-H14+1)
G15: =IF(OR(E15="",F15=""),"",F15-E15) | J15: =IF(OR(H15="",I15=""),"",I15-H15+1)
G16: =IF(OR(E16="",F16=""),"",F16-E16) | J16: =IF(OR(H16="",I16=""),"",I16-H16+1)
G17: =IF(OR(E17="",F17=""),"",F17-E17) | J17: =IF(OR(H17="",I17=""),"",I17-H17+1)
G18: =IF(OR(E18="",F18=""),"",F18-E18) | J18: =IF(OR(H18="",I18=""),"",I18-H18+1)
G19: =IF(OR(E19="",F19=""),"",F19-E19) | J19: =IF(OR(H19="",I19=""),"",I19-H19+1)
G20: =IF(OR(E20="",F20=""),"",F20-E20) | J20: =IF(OR(H20="",I20=""),"",I20-H20+1)
G21: =IF(OR(E21="",F21=""),"",F21-E21) | J21: =IF(OR(H21="",I21=""),"",I21-H21+1)
G22: =IF(OR(E22="",F22=""),"",F22-E22) | J22: =IF(OR(H22="",I22=""),"",I22-H22+1)
... G28: =IF(OR(E28="",F28=""),"",F28-E28) | J28: =IF(OR(H28="",I28=""),"",I28-H28+1)

Sheet 계약변경
A1: No. | B1: Company | C1: Settlement Period | D1: Contract Date | E1: Follow Up | F1: 완료 날짜(예상포함) | G1: Citibank announcement
A2: 1 | B2: MEITUAN | C2: Weekly | D2: 46083 | E2: 3/2 재변경 진행 중 | F2: 46143 | G2: 화폐 모두 변경 완료 | H2: 이전 check out 건 manual 정리 포함
A3: 2 | B3: QUNAR | C3: Weekly | E3: 4/6 변경 진행 중 | F3: 46174 | G3: 6/1 변경 완료 | H3: Qunar 6/3일 내부 변경 예정, 원본 합의서 우편으로 보냄
A4: 3 | B4: CONVERGENT | C4: Weekly | D4: 46083 | E4: 3/2 재변경 완료 | F4: 46125 | G4: 4/13변경 완료
A5: 4 | B5: TONGCHENG | C5: Weekly | D5: 46083 | E5: 3/2 변경 완료 | F5: 46104 | G5: 3/23 변경 완료
A6: 5 | B6: Traveloka | C6: Monthly | E6: 6/4 change completely | F6: 46143 | G6: 6/4 finish
A7: 6 | B7: PKFARE | C7: Bi-Weekly | D7: 46097 | E7: 3/16 변경 완료 - 이건 한국 들어감 | F7: 46113 | G7: 4/1변경 완료
A8: 7 | B8: QIYOUJI | C8: Bi-Weekly | D8: 46097 | E8: 3/16 변경 완료 | F8: 46113 | G8: 4/1변경 완료
A9: 8 | B9: DIDA | C9: Bi-Weekly | D9: 46113 | E9: 4/1 재변경 진행 중 | F9: 46143 | G9: 4/16 변경 완료
A10: 9 | B10: TOURMIND | C10: Bi-Weekly | D10: 46097 | E10: 4/1 재변경 진행 중 | F10: 46113 | G10: 4/1변경 완료
A11: 10 | B11: HEYTRIP | C11: Bi-Weekly | D11: 46143 | E11: 4/1 협의 진행 중, 데포짓 변경처리 필요 | F11: 46143 | G11: 5/1로 변경 완료 | H11: deposit 우리에게 씨티 입금해야되는데, Heytrip 담당 입금정보 시스템에서 업데이트 안되어있어 싱가포르 KEB Hana 엔화 계좌 입금했음
A12: 11 | B12: KAKE | C12: Bi-Weekly | D12: 46113 | E12: 리뷰 회신 대기 중 -3/16계약로 진행 | F12: 46113 | G12: 4/1변경 완료
A13: 12 | B13: ALITRIP | C13: Bi-Weekly | D13: 46082 | E13: 3/1 재변경 완료 | F13: 46113 | G13: 4/1변경 완료
A14: 13 | B14: SS BOOKING | C14: Bi-Weekly | D14: 46097 | E14: 3/16 변경 완료 | F14: 46097 | G14: 3/16 변경 완료
A15: 14 | B15: TOPTOWN | C15: Bi-Weekly | D15: 46082 | E15: 3/1 재변경 완료 | F15: 46113 | G15: 4/1변경 완료
A16: 15 | B16: RTX | C16: Bi-Weekly | D16: 46082 | E16: 4/1 변경 완료 | F16: 46113 | G16: 변경 완료
A17: 16 | B17: Room Deal (MG) | C17: Bi-Weekly | D17: 46097 | E17: 5/1자 변경 진행 중, 크로스셀링으로 진행 | F17: 46188 | G17: MS. Sophia review the MG's feedback - related to Purchasing contract
A18: 17 | B18: Ctrip | C18: Weekly | D18: 46143 | F18: 46143 | G18: 메일 확인 ~ 소피아님 확인 필요
A19: 18 | B19: Agoda
A21: No. | B21: Company | C21: Settlement Period | D21: Contract Date | E21: Follow Up | F21: 완료 날짜(예상포함) | G21: Citibank announcement
A22: 1 | B22: HOTELBANK | C22: Bi-Weekly | D22: 46082 | E22: 3/1 재변경 완료 | F22: 46113 | G22: 4/1변경 완료
A23: 2 | B23: HUAMIN | C23: Bi-Weekly | D23: 46097 | E23: 3/16변경 완료 | F23: 46113 | G23: 4/1변경 완료
A24: 3 | B24: COOLPRICE | C24: Bi-Weekly | D24: 46082 | E24: 3/31 Addendum 보냈음 | F24: 46113 | G24: 4/1변경 완료
A25: 4 | B25: STAR TRAVEL | C25: Bi-Weekly | D25: 46082 | E25: addendum with new bank acc | F25: 46113 | G25: 4/1변경 완료 ( no addendum yet)
A26: 5 | B26: LINKSTAY | C26: Bi-Weekly | D26: 46082 | E26: 3/31 Addendum 보냈음 | F26: 46113 | G26: 4/1변경 완료
A27: 6 | B27: KLOOK | C27: Bi-Weekly | D27: 46082 | E27: New contract | F27: 46113 | G27: 4/1변경 완료
A28: 7 | B28: JL Tour | C28: Bi-Weekly | F28: 46113 | G28: 4/1변경 완료
A29: 8 | B29: Bingtrip | C29: Weekly | F29: 46113 | G29: 4/1변경 완료

Sheet Mapping Schedule
A1: [2026 Mapping Schedule] | J1: Q1 | W1: Q2 | AJ1: Q3 | AW1: Q4
J2: Jan | N2: Feb | R2: Mar | W2: Apr | AA2: May | AE2: Jun | AJ2: Jul | AN2: Aug | AS2: Sep | AW2: Oct | BA2: Nov | BF2: Dec
A3: Category | B3: Project | C3: Handling Team | D3: PIC | E3: Current Step | F3: Status | G3: Start Date | H3: End Date | I3: Notes / Issues | J3: W1 | K3: W2 | L3: W3 | M3: W4 | N3: W1 | O3: W2 | P3: W3 | Q3: W4 | R3: W1 | S3: W2 | T3: W3 | U3: W4 | V3: W5 | W3: W1 | X3: W2 | Y3: W3 | Z3: W4 | AA3: W1 | AB3: W2 | AC3: W3 | AD3: W4 | AE3: W1 | AF3: W2 | AG3: W3 | AH3: W4 | AI3: W5 | AJ3: W1 | AK3: W2 | AL3: W3 | AM3: W4 | AN3: W1 | AO3: W2 | AP3: W3 | AQ3: W4 | AR3: W5 | AS3: W1 | AT3: W2 | AU3: W3 | AV3: W4 | AW3: W1 | AX3: W2 | AY3: W3 | AZ3: W4 | BA3: W1 | BB3: W2 | BC3: W3 | BD3: W4 | BE3: W5 | BF3: W1 | BG3: W2 | BH3: W3 | BI3: W4
A4: Manual Mapping | B4: Ctrip KR Manual Check - Jun 2026 | C4: Content | E4: Receive Room List | F4: Done | G4: 46188 | H4: 46199 | I4: Finish manual mapping | J4: =IF(AND(ISNUMBER($G4),ISNUMBER($H4),J$191+6>=$G4,J$191<=$H4),"●","") | K4: =IF(AND(ISNUMBER($G4),ISNUMBER($H4),K$191+6>=$G4,K$191<=$H4),"●","") | L4: =IF(AND(ISNUMBER($G4),ISNUMBER($H4),L$191+6>=$G4,L$191<=$H4),"●","") | M4: =IF(AND(ISNUMBER($G4),ISNUMBER($H4),M$191+6>=$G4,M$191<=$H4),"●","") | N4: =IF(AND(ISNUMBER($G4),ISNUMBER($H4),N$191+6>=$G4,N$191<=$H4),"●","") | O4: =IF(AND(ISNUMBER($G4),ISNUMBER($H4),O$191+6>=$G4,O$191<=$H4),"●","") | P4: =IF(AND(ISNUMBER($G4),ISNUMBER($H4),P$191+6>=$G4,P$191<=$H4),"●","") | Q4: =IF(AND(ISNUMBER($G4),ISNUMBER($H4),Q$191+6>=$G4,Q$191<=$H4),"●","") | ... BI4: =IF(AND(ISNUMBER($G4),ISNUMBER($H4),BI$191+6>=$G4,BI$191<=$H4),"●","")
B5: Ctrip VN Manual Check | C5: Content | E5: Manual Map after SCM Review | F5: On Hold | G5: 46174 | H5: 46241 | I5: Following up with SCM on some denied create-new-room requests, almost finished | J5: =IF(AND(ISNUMBER($G5),ISNUMBER($H5),J$191+6>=$G5,J$191<=$H5),"●","") | K5: =IF(AND(ISNUMBER($G5),ISNUMBER($H5),K$191+6>=$G5,K$191<=$H5),"●","") | L5: =IF(AND(ISNUMBER($G5),ISNUMBER($H5),L$191+6>=$G5,L$191<=$H5),"●","") | M5: =IF(AND(ISNUMBER($G5),ISNUMBER($H5),M$191+6>=$G5,M$191<=$H5),"●","") | N5: =IF(AND(ISNUMBER($G5),ISNUMBER($H5),N$191+6>=$G5,N$191<=$H5),"●","") | O5: =IF(AND(ISNUMBER($G5),ISNUMBER($H5),O$191+6>=$G5,O$191<=$H5),"●","") | P5: =IF(AND(ISNUMBER($G5),ISNUMBER($H5),P$191+6>=$G5,P$191<=$H5),"●","") | Q5: =IF(AND(ISNUMBER($G5),ISNUMBER($H5),Q$191+6>=$G5,Q$191<=$H5),"●","") | ... BI5: =IF(AND(ISNUMBER($G5),ISNUMBER($H5),BI$191+6>=$G5,BI$191<=$H5),"●","")
B6: Ctrip KR Manual Check - Aug 2026 | C6: Content | E6: Receive Room List | F6: On Hold | G6: 46244 | I6: 896 rooms. Prioritizing Alitrip recheck
B7: Recheck Alitrip's Manual Mapping | C7: Content | F7: In Progress | G7: 46247 | H7: 46261 | I7: ~1100 rooms | J7: =IF(AND(ISNUMBER($G7),ISNUMBER($H7),J$191+6>=$G7,J$191<=$H7),"●","") | K7: =IF(AND(ISNUMBER($G7),ISNUMBER($H7),K$191+6>=$G7,K$191<=$H7),"●","") | L7: =IF(AND(ISNUMBER($G7),ISNUMBER($H7),L$191+6>=$G7,L$191<=$H7),"●","") | M7: =IF(AND(ISNUMBER($G7),ISNUMBER($H7),M$191+6>=$G7,M$191<=$H7),"●","") | N7: =IF(AND(ISNUMBER($G7),ISNUMBER($H7),N$191+6>=$G7,N$191<=$H7),"●","") | O7: =IF(AND(ISNUMBER($G7),ISNUMBER($H7),O$191+6>=$G7,O$191<=$H7),"●","") | P7: =IF(AND(ISNUMBER($G7),ISNUMBER($H7),P$191+6>=$G7,P$191<=$H7),"●","") | Q7: =IF(AND(ISNUMBER($G7),ISNUMBER($H7),Q$191+6>=$G7,Q$191<=$H7),"●","") | ... BI7: =IF(AND(ISNUMBER($G7),ISNUMBER($H7),BI$191+6>=$G7,BI$191<=$H7),"●","")
B8: Dida Manual Check - VN SCM | C8: Content | F8: Not Started | J8: =IF(AND(ISNUMBER($G8),ISNUMBER($H8),J$191+6>=$G8,J$191<=$H8),"●","") | K8: =IF(AND(ISNUMBER($G8),ISNUMBER($H8),K$191+6>=$G8,K$191<=$H8),"●","") | L8: =IF(AND(ISNUMBER($G8),ISNUMBER($H8),L$191+6>=$G8,L$191<=$H8),"●","") | M8: =IF(AND(ISNUMBER($G8),ISNUMBER($H8),M$191+6>=$G8,M$191<=$H8),"●","") | N8: =IF(AND(ISNUMBER($G8),ISNUMBER($H8),N$191+6>=$G8,N$191<=$H8),"●","") | O8: =IF(AND(ISNUMBER($G8),ISNUMBER($H8),O$191+6>=$G8,O$191<=$H8),"●","") | P8: =IF(AND(ISNUMBER($G8),ISNUMBER($H8),P$191+6>=$G8,P$191<=$H8),"●","") | Q8: =IF(AND(ISNUMBER($G8),ISNUMBER($H8),Q$191+6>=$G8,Q$191<=$H8),"●","") | ... BI8: =IF(AND(ISNUMBER($G8),ISNUMBER($H8),BI$191+6>=$G8,BI$191<=$H8),"●","")
P9: Not Started
P10: In Progress
P11: Blocked
P12: On Hold
P13: Done
J191: 46027 | K191: 46034 | L191: 46041 | M191: 46048 | N191: 46055 | O191: 46062 | P191: 46069 | Q191: 46076 | R191: 46083 | S191: 46090 | T191: 46097 | U191: 46104 | V191: 46111 | W191: 46118 | X191: 46125 | Y191: 46132 | Z191: 46139 | AA191: 46146 | AB191: 46153 | AC191: 46160 | AD191: 46167 | AE191: 46174 | AF191: 46181 | AG191: 46188 | AH191: 46195 | AI191: 46202 | AJ191: 46209 | AK191: 46216 | AL191: 46223 | AM191: 46230 | AN191: 46237 | AO191: 46244 | AP191: 46251 | AQ191: 46258 | AR191: 46265 | AS191: 46272 | AT191: 46279 | AU191: 46286 | AV191: 46293 | AW191: 46300 | AX191: 46307 | AY191: 46314 | AZ191: 46321 | BA191: 46328 | BB191: 46335 | BC191: 46342 | BD191: 46349 | BE191: 46356 | BF191: 46363 | BG191: 46370 | BH191: 46377 | BI191: 46384

Sheet Jane
A1: 날짜 (Date) | B1: 작성자 (Reporter) | C1: 채널명 (Channel) | D1: 유형 (Type) | E1: 내용 (Details) | F1: 대응/액션 (Action Plan) | G1: 비고 (Remarks)
A2: 예: 04/07 e.g. MM/DD | B2: 이름 Name | C2: 채널/업체명 Channel/Company Name | D2: ▼ 선택 ▼ Select | E2: 상세 내용 기재 Describe in detail | F2: "무엇을, 언제까지" 명시 Specify "What, by When"
A3: 4/13 ~ 4/17 | B3: Jane | C3: 하나투어 | D3: 요금/물량 이슈 | E3: 13개 호텔에 대한 가격 조정 요청 및 연장 요청 | F3: 진행 중인 프로모션 리체크 하여 최대한 가격 조정 및 연장 가능한 호텔 연장 처리 완료
B4: Jane | C4: 여기어때투어 | D4: 요금/물량 이슈 | E4: JP SCM에서 Oriental Hotel Universal City 한국 마켓에 판매 해달라는 요청 있어 여기어때투어에 특가 요금표 제공하여 판매 부스트하는 방식으로 가능 안내 | F4: 업데이트 된 고정 요금 확인하였으나 메타 최저가 대비 가격이 높아 제안 불가, 호텔과 다시 조정 필요함 안내
A5: 4/20 ~ 4/24 | B5: Jane | C5: 샬레코리아 | D5: 프로모션제안 | E5: SK이노베이션 하드블럭 요청 | F5: 요금 안내 드렸으나 유류할증료 인상 등의 영향으로 해외 시설은 모객이 어려울 것으로 판단 되어 진행 어렵다고 함
A6: 4/27 ~ 4/30 | B6: Jane | C6: 모두투어 | D6: 기타 | E6: API 연동 관련 제안서 발송 및 미팅 | F6: 공급사 추가 계획 아직 없어 미팅 진행 어렵다고 함
C7: 스테이폴리오 | D7: 기타 | E7: API 연동 관련 미팅 | F7: 5월 미팅 예정, 일정 확인 중
C8: 11번가 | D8: 기타 | E8: 업체 파악 | F8: 문의 메일 드렸으나 답변 없음
C9: 11번가 | D9: 매핑/콘텐츠 | E9: 매핑 이슈 | F9: 1) K26020711004H01 기존 매핑 이슈 발생 건, 11번가 오류로 관련 취소 수수료 11번가에서 지불 예정 확인 받았으나 지불 예정 날짜 답변 받지 못해서 체이스 예정 2) 객실명에 해당 단어들이 모두 포함되어 있으면 매칭 되는 11번가 룸매핑 방식에 따라 추후 비슷한 케이스 발생할 가능성 높을 것으로 보임
A10: 5/4 ~ 5/8 | B10: Jane | C10: 점보투어즈 한국지사 | D10: 기타 | E10: 닷비즈 신규 가입, 3rd party 공급 문의 | F10: 소피아님께 전달 드림
B11: Jane | C11: 모두투어 | D11: 기타 | E11: API 연동 관련 미팅 | F11: 5/14 미팅 예정
B12: Jane | C12: 여기어때투어 | D12: 이상 없음(No Issue) | E12: 기존 FIT본부와 별개로 고품격여행팀에서 닷비즈 신규 가입 및 호텔 리스트 요청 | F12: 호텔 리스트 정리 및 요금표 송부, 닷비즈 사용법 안내
A13: 5/18 ~ 5/22 | B13: Jane | C13: 현대여행사 | D13: 이상 없음(No Issue) | E13: 단체 견적 요청 | F13: 3개 호텔 단체 견적서 제출
B14: Jane | C14: 샬레코리아 | D14: 이상 없음(No Issue) | E14: 3분기 요금표 요청 | F14: API 연동 관련 미팅 예정
B15: Jane | C15: KKDAY | D15: 이상 없음(No Issue) | E15: 3분기 요금/재고 업데이트 요청 | F15: 금주까지 예약 추이 보고 제공 금액 결정 예정
B16: Jane | C16: 여기어때투어 | D16: 이상 없음(No Issue) | E16: Hotel Monterey Fukuoka 요금표 요청 | F16: 송부 드림
A17: 5/25~5/29 | B17: Jane | C17: KKDAY | D17: 이상 없음(No Issue) | E17: 3분기 요금표 요청 | F17: 회신 및 연장 처리 확인 완료
B18: Jane | C18: 여기어때투어 | D18: 이상 없음(No Issue) | E18: KOKO HOTEL Nagoya Sakae, Sotetsu Fresa Inn Nihombashi Kayabacho 요금표 요청 | F18: 송부 드림
B19: Jane | C19: AGL | D19: 이상 없음(No Issue) | E19: 미팅 | F19: 미팅 참석, 호텔리스트 송부 예정
B20: Jane | C20: Myrealtrip | D20: 이상 없음(No Issue) | E20: 마이리얼트립 화이트리스트 요청 | F20: JP 취합 완료, VN 회신 대기 중
B21: Jane | C21: Tripbtoz | D21: 이상 없음(No Issue) | E21: Tripbtoz-Hotel Skypark Daejeon 1 매핑 이슈 | F21: 수정 요청 하였으나 처리에 시간 다소 걸릴 것 같아 우선 해당 호텔 블락 처리
B22: Jane | C22: 스테이폴리오 | D22: 이상 없음(No Issue) | E22: 료칸리스트, 테스트 계정 요청 | F22: 전달 완료
A23: 6/1~6/5 | B23: Jane | C23: 여기어때투어 | D23: 이상 없음(No Issue) | E23: API 연동 관련 미팅 | F23: 참석 완료
B24: Jane | C24: Myrealtrip | D24: 이상 없음(No Issue) | E24: 화이트리스트 요청 | F24: JP 전달 완료, 노출 여부 확인 예정 / VN 취합 중
B25: Jane | C25: Triptopaz | D25: 이상 없음(No Issue) | E25: 화이트리스트 요청 | F25: JP, VN 취합 중
B26: Jane | C26: 샬레코리아 | D26: 이상 없음(No Issue) | E26: 미팅 | F26: 1년 요금 제공 가능한 호텔 확인 중
B27: Jane | C27: 부산 대학교 연합 | D27: 이상 없음(No Issue) | E27: 후쿠오카 단체 견적 | F27: JP SCM 확인 중
B28: Jane | C28: STEM | D28: 이상 없음(No Issue) | E28: 후쿠오카 단체 견적 | F28: JP SCM 확인 중
B29: Jane | C29: Hikari | D29: 이상 없음(No Issue) | E29: 미팅 | F29: 어레인지 완료, 매출리포트 작성
B30: Jane | C30: Ctrip | D30: 매핑/콘텐츠 | E30: K26050210011H01 매핑 오류 | F30: Compensation 발생 시 5:5 부담 예정, 우선 VN OP로 핸들링 내용 전달
B31: Jane | C31: Tripbtoz | D31: 매핑/콘텐츠 | E31: K26052911150H01 매핑 오류 | F31: Tripbtoz-sub agent 수정 중이라고 함
B32: Jane | C32: Webbeds | D32: 이상 없음(No Issue) | E32: 연동 관련 F/U | F32: 테스트 계정, 톱리스트 전달
B33: Jane | C33: AGL | D33: 이상 없음(No Issue) | E33: 호텔 리스트 | F33: 고정 요금 제공 가능한 호텔 리스트 전달
A34: 6/8~6/12 | B34: Jane | C34: 샬레코리아 | D34: 이상 없음(No Issue) | E34: 3분기 요금표 | F34: 5개 호텔 전달 완료
B35: Jane | C35: Triptopaz | D35: 매핑/콘텐츠 | E35: 매핑 되어 있으나 요금 안 나오는 호텔 | F35: 예시 호텔 우선 확인 중, 추가 호텔 리스트 요청 예정
B36: Jane | C36: Myrealtrip | D36: 이상 없음(No Issue) | E36: 화이트리스트 요청 | F36: JP 전달 완료, 노출 여부 확인 예정 / VN 취합 중
B37: Jane | C37: Triptopaz | D37: 이상 없음(No Issue) | E37: 화이트리스트 요청 | F37: JP, VN 취합 중
B38: Jane | C38: MKS | D38: 이상 없음(No Issue) | E38: 호텔 가격 확인 요청 | F38: 11개 호텔 객실료 회신 완료
B39: Jane | C39: 부산 대학교 연합 | D39: 이상 없음(No Issue) | E39: 기타큐슈 단체 견적 | F39: JP SCM 확인 중
B40: Jane | C40: Hanatour | D40: 이상 없음(No Issue) | E40: Sotetsu Grand Fresa Osaka - Namba 전용 요금 | F40: JP SCM 확인 중
B41: Jane | C41: STEM | D41: 이상 없음(No Issue) | E41: 후쿠오카 단체 견적 | F41: JP SCM 확인 중
A42: 6/15~6/19 | B42: Jane | C42: 여기어때 | D42: 이상 없음(No Issue) | E42: 요금표 송부 | F42: 3개 호텔 요금표 송부 완료
B43: Jane | C43: All | D43: 이상 없음(No Issue) | E43: Room Type Name 로직 변경 관련 검토 요청 | F43: 각 에이전트로 메일 송부, 회신 대기 중
B44: Jane | C44: Tripbtoz, Triptopaz, Hotelpass | D44: 이상 없음(No Issue) | E44: 여름 프로모션 참여 가능 여부 확인 요청 | F44: 각 에이전트로 메일 송부, 회신 대기 중
B45: Jane | C45: Myrealtrip | D45: 이상 없음(No Issue) | E45: 소테츠 브랜드관 프로모션 | F45: 마리트에서 추가 정보 요청, 회신 예정
B46: Jane | C46: Triptopaz, Myrealtrip | D46: 이상 없음(No Issue) | E46: 후쿠오카시장 트렌드 조사 | F46: 3개 에이전트 메일 송부 드림, 회신 대기 중
B47: Jane | C47: Hikari | D47: 이상 없음(No Issue) | E47: 미팅 | F47: 미팅 참석 및 리캡 완료
B48: Jane | C48: All | D48: 이상 없음(No Issue) | E48: 6월 상반 인보이스 확인 | F48: 확인 및 수동 발송 완료
B49: Jane | C49: Tripbtoz | D49: 이상 없음(No Issue) | E49: 미팅 | F49: 미팅 참석 및 리캡 완료
B50: Jane | C50: Stem | D50: 이상 없음(No Issue) | E50: 후쿠오카 단체 견적 | F50: 예약금 입금 확인, 숙박객 명단 대기 중
A51: 6/22~6/26 | B51: Jane | C51: Hotelpass, Myrealtrip, Triptopaz, Tripbtoz, Hikari | D51: 이상 없음(No Issue) | E51: 6월 트렌드 인사이트 및 설문 | F51: 요청 완료, 회신 대기중
B52: Jane | C52: STEM | D52: 이상 없음(No Issue) | E52: 후쿠오카 단체 견적 | F52: 예약 생성 완료, 8월 잔금 확인 예정
B53: Jane | C53: Hotelpass, Myrealtrip | D53: 이상 없음(No Issue) | E53: 후지타 관광 프로모션 | F53: JP SCM Rate 셋팅 확인 되면 각 에이전트로 전달 예정
B54: Jane | C54: Myrealtrip | D54: 이상 없음(No Issue) | E54: 소테츠 브랜드관 프로모션 | F54: JP SCM에서 금일 중 회신 예정
B55: Jane | C55: Myrealtrip, Triptopaz | D55: 이상 없음(No Issue) | E55: 후쿠오카 시장 트렌드 조사 | F55: Triptopaz 미회신, Myrealtrip 회신 받음
B56: Jane | C56: Webbeds | D56: 이상 없음(No Issue) | E56: 웹베즈 미팅 | F56: DOTW · FITRuums 매출 리포트 작성 완료
A57: 6/29~7/3 | B57: Jane | C57: Hotelpass, Myrealtrip, Triptopaz, Tripbtoz, Hikari | D57: 이상 없음(No Issue) | E57: 6월 트렌드 인사이트 및 설문 | F57: Hotelpass, Hikari 취합 완료
B58: Jane | C58: Hotelpass, Myrealtrip | D58: 이상 없음(No Issue) | E58: 후지타 관광 프로모션 | F58: Hotelpass, Myrealytrip에 전달 완료
B59: Jane | C59: 기타 | D59: 이상 없음(No Issue) | E59: 티켓패스 월 마감 | F59: "판매량 12 / 수탁고 126,518 / 수익 5,839
B60: Jane | C60: 돌하루팡 | D60: 이상 없음(No Issue) | E60: 미팅 어레인지 | F60: 어레인지 완료, 7/3 미팅 예정
B61: Jane | C61: Myrealtrip | D61: 이상 없음(No Issue) | E61: 소테츠 브랜드관 프로모션 | F61: 프로모션 기간 확인, 오픈 시 페이지 공유 예정
B62: Jane | C62: All | D62: 이상 없음(No Issue) | E62: 신규 한국 업체 컨택 | F62: 업체 이메일 발송 중
B63: Jane | C63: Myrealtrip | D63: 이상 없음(No Issue) | E63: 마리특 | F63: VN Hotel list 발송
A64: 7/6~ 7/10 | B64: Jane | C64: 7개 KR Agent | D64: 이상 없음(No Issue) | E64: KR Agent 미팅 어레인지 | F64: 에어텔닷컴, 트립비토즈 완료
B65: Jane | C65: Myrealtrip | D65: 이상 없음(No Issue) | E65: 소테츠 브랜드관 프로모션 | F65: 판매 개시
B66: Jane | C66: Myrealtrip | D66: 이상 없음(No Issue) | E66: 마리특 베트남 프로모션 | F66: 판매 개시
B67: Jane | C67: 돌하루팡 | D67: 이상 없음(No Issue) | E67: NDA 송부 | F67: 리뷰 완료 했다고 함, 날인본 수령 예정
B68: Jane | C68: 스테이폴리오 | D68: 이상 없음(No Issue) | E68: 미팅 후속 F/U | F68: 메일 드렸으나 회신 없음
B69: Jane | C69: Hotelpass, Myrealtrip | D69: 이상 없음(No Issue) | E69: 후지타 관광 프로모션 | F69: Hotelpass 판매 시작, Myrealytrip 판매 예정
B70: Jane | C70: All | D70: 이상 없음(No Issue) | E70: 신규 한국 업체 컨택 | F70: 업체 컨택 중
A71: 7/13~7/16 | B71: Jane | C71: All | D71: 이상 없음(No Issue) | E71: 신규 한국 업체 컨택 | F71: 업체 컨택 중
B72: Jane | C72: 돌하루팡 | D72: 이상 없음(No Issue) | E72: NDA 송부 | F72: NDA 날인본 및 회사 소개서 수령, 계약서 준비중
B73: Jane | C73: 스테이폴리오 | D73: 이상 없음(No Issue) | E73: 미팅 후속 F/U | F73: 추후 진행 필요 시 논의 예정, 케이스 종료
B74: Jane | C74: Kayak | D74: 기타 | E74: API 문서 공유 요청 | F74: 메일 드렸으나 회신 없음
B75: Jane | C75: 이제너두 | D75: 기타 | E75: 제휴 문의 | F75: 온라인 미팅 어레인지 중
A76: 7/20~7/24 | B76: Jane | C76: All | D76: 이상 없음(No Issue) | E76: 한국 업체 미팅 | F76: 어레인지 중
B77: Jane | C77: 돌하루팡 | D77: 신규 계약 | E77: 계약서 발송 필요 | F77: 국문 계약서 준비 중
B78: Jane | C78: 이제너두 | D78: 기타 | E78: 제휴 문의 | F78: 대면 미팅 예정
B79: Jane | C79: 여기어때투어 | D79: 이상 없음(No Issue) | E79: Hotel Monterey Fukuoka 4분기 요금표 요청 | F79: 송부 드림
B80: Jane | C80: All | D80: 이상 없음(No Issue) | E80: 한국 에이전트 태국 탑셀링 요청 | F80: 호텔패스, 마이리얼트립 전달 완료, 트립토파즈 대기 중
B81: Jane | C81: Myrealtrip | D81: 프로모션제안 | E81: 빅체인 호텔을 전용 브랜드관 요청 | F81: JP SCM 확인 중
B82: Jane | C82: asiarooms | D82: 신규 계약 | E82: NDA 수령 | F82: 계약 진행 여부 확인 중
A83: 7/27~7/31 | B83: Jane | C83: All | D83: 이상 없음(No Issue) | E83: 한국 업체 미팅 | F83: 어레인지 완료
B84: Jane | C84: 돌하루팡 | D84: 신규 계약 | E84: 계약서 발송 | F84: 국문 계약서 피드백 받아 수정 중
B85: Jane | C85: All | D85: 이상 없음(No Issue) | E85: 한국 에이전트 태국 탑셀링 요청 | F85: 트립토파즈 전달 완료
B86: Jane | C86: 샬레코리아 | D86: 이상 없음(No Issue) | E86: 신규 복지몰 입점 1년치 요금 요청 | F86: JP SCM 확인 중
B87: Jane | C87: All | D87: 이상 없음(No Issue) | E87: 일본 지진 관련 예약 트렌드 여파 | F87: 보고서 작성하여 JP SCM 전달 완료
A88: 8/3~8/7 | B88: Jane | C88: 이제너두 | D88: 기타 | E88: 제휴 문의 | F88: 미팅 완료, NDA와 다이렉스 호텔 리스트, 탑셀링 리스트 송부
B89: Jane | C89: 돌하루팡 | D89: 신규 계약 | E89: 계약서 발송 | F89: 계약서 날인본 발송 및 API 문서 전달
B90: Jane | C90: 트립토파즈 | D90: 이상 없음(No Issue) | E90: 한국 업체 미팅 | F90: 25&26년 부킹 트렌드 리포트 작성
B91: Jane | C91: 마이리얼트립 | D91: 이상 없음(No Issue) | E91: 한국 업체 미팅 | F91: 소테츠 프로모션 성과 리포트 작성
B92: Jane | C92: 에어텔닷컴 | D92: 이상 없음(No Issue) | E92: 한국 업체 미팅 | F92: 25&26년 예약 실적 리포트
A93: 8/10~8/14 | B93: Jane | C93: 이제너두 | D93: 신규 계약 | E93: 제휴 문의 | F93: 회신 없어 전화 드림, 리뷰에 시간이 걸린다고 함
B94: Jane | C94: 돌하루팡 | D94: 신규 계약 | E94: 개발 착수 | F94: 양사 개발팀 컨택포인트 전달 완료
B95: Jane | C95: 에어텔닷컴 | D95: 이상 없음(No Issue) | E95: 호텔 추천 요청 | F95: 탑셀링 전달, 요금표 송부
B96: Jane | C96: 트립토파즈 | D96: 이상 없음(No Issue) | E96: 네이버 슈퍼위크 프로모션 | F96: 각 SCM에 프로모션 확인 요청
A97: 8/17~8/21 | B97: Jane | C97: Hotelpass | D97: 기타 | E97: 프로모션 연장 문의 | F97: 여름 프로모션 결과값 기반으로 호텔패스와 진행 방향 확인 중
B98: Jane | C98: 3 KR Agent | D98: 기타 | E98: 겨울 시즌 국내 집중 도시 확인 | F98: 2곳 답변 받아 보고 완료
B99: Jane | C99: 샬레코리아 | D99: 기타 | E99: 이화의료원 하드블럭 문의 | F99: JP SCM 확인 중
B100: Jane | C100: 마이리얼트립 | D100: 기타 | E100: 하드블럭 프로모션 제안 | F100: JP SCM 확인 중
...

Sheet Grace
A1: 날짜 (Date) | B1: 작성자 (Reporter) | C1: 채널명 (Channel) | D1: 유형 (Type) | E1: 내용 (Details) | F1: 대응/액션 (Action Plan) | G1: 비고 (Remarks)
A2: 예: 04/07 e.g. MM/DD | B2: 이름 Name | C2: 채널/업체명 Channel/Company Name | D2: ▼ 선택 ▼ Select | E2: 상세 내용 기재 Describe in detail | F2: "무엇을, 언제까지" 명시 Specify "What, by When"
A3: 46115 | B3: Grace | C3: Convergent | D3: 프로모션제안 | E3: 화폐에 대한 추가 논의 중; 4/8 화폐 변경 완료 | F3: 변경 후 모니터링 | G3: 현재 부킹 다시 상승
A4: 46118 | B4: Grace | C4: AMT | D4: API 연동 진행 | E4: API 문서 보내고 계약 진행 현황 확인 중 | F4: 개발 시점 확인 필요
A5: 46119 | B5: Grace | C5: FBT | D5: 테스트/검증 | E5: 현재 테스트 어카운트 및 직계약 리스트 확인 | F5: 계약 진행 및 개발 일정 확인 예정 | G5: 지계약 리스트 정리 중
B6: Grace | C6: Hotelbank | D6: 요금/물량 이슈 | E6: 3/26 이후 부킹 건 없음, 이슈 확인 요청; 4/8 물량 안 나오고 요금 매우 높음 | F6: 공급사 어딘지 알아보기 | G6: JP supplier: Daiei, AHN, JTB, Miki (HIS) INTL: DIDA, EPS, HotelBeds, Rakuten X, Webbeds, TBO, Yanolja GoGlobal.
B7: Grace | C7: Huamin | D7: 라이브 오픈 준비 | E7: CS 정보 요청, 오픈 직전 정보 수집 완료 | F7: 오픈 진행 예정 | G7: 4/21 그 주 오픈 예정
A8: 46120 | B8: Grace | C8: Bingtrip | D8: 인증/테스트 완료 | E8: CS 정보 요청 완료; SLA 다시 사인, 테스트 certificate 끝 | F8: 기술 팀 검증 후 보증금 받기 | G8: 오픈 완료
B9: Grace | C9: Alitrip | D9: 매핑/콘텐츠 | E9: Top list 필요, 매핑 가이드 미팅 요청 | F9: Top list 보냈음, 미팅 진행 | G9: 매핑 우리 측 하기로 함
B10: Grace | C10: JL tour | D10: 계약 갱신 | E10: SLA 다시 사인 필요 | F10: SLA 다시 받기 | G10: 완료
B11: Grace | C11: Qian Tao | D11: 신규 계약 | E11: 계약 진행 중 | F11: 4월 내 마무리 | G11: 개발 일정 확인 중 (4월 말)
B12: Grace | C12: Heytrip | D12: 계약 갱신 | E12: 계약 다시 진행 | F12: 4월 안 마무리 필요
A13: 4월13일~4월17일 | B13: Grace | C13: Hibeds | D13: 신규 계약 | E13: 우리 먼저 공급 계약 진행 | F13: 승인 받을 수 다음 주 바로 처리함
C14: FBT | D14: 요금/물량 이슈 | E14: FBT 담당자와 티나님은 친한 관계가 있어 "현재 자체 보유 물량이 충분하지 않은 상황으로 확인되었습니다." -우리가 공급은 가능하나 진행하는 조건은 No Deposit을 제안한 상태입니다. | F14: 직계약 리스트를 취합하여 정리 중
C15: Justgotrip | D15: 신규 계약 | E15: Allianze Trade는 우리에서 직접 신청 및 컨택이 필요한 업체입니다. 해당 업체에 대한 이해가 선행되어야 하기 때문에, 당사가 직접 커뮤니케이션을 진행하는 것이 적절합니다. 현재 이와 관련하여, JustGoTrip 담당자에게 EXP를 담당하는 Allianze Trade 측 PIC가 있는지 확인 중입니다. | F15: Allianze trade 더 알아보기
C16: QuoteDMC | D16: 이상 없음(No Issue) | E16: 미팅 요청 | F16: meeting arrangement
C17: Huamin | D17: 라이브 오픈 준비 | E17: 4/21 그 주 오픈예정 | F17: F/U with the process
C18: Star Travel | D18: API 연동 진행 | E18: 4월 개발 일정들어간다고 함 | F18: chasing, but according what PIC said, it was in the schedule
C19: Heytrip | D19: 요금/물량 이슈 | E19: 물량 없다 계속 claimed | F19: room mapping % 요청했지만, 못 받을 수 있음
C20: Meituan | D20: 요금/물량 이슈 | E20: IT 측 좀 chase 필요 | F20: 입금 펜딩 이미 한 달 넘어, 빨리 진행 필요
C21: Hotelbank | D21: 요금/물량 이슈 | E21: 요금 재고 다른 공급사 비교했을 때 경쟁력이 없음 | F21: scm 측 다시 feedback 받아야함/ action 필요 | G21: 우리 scm한테 뭐 요청할 때 deadline 추가하면 좋을 것 같음
C22: Tourmind | D22: 정산이슈 | E22: 입금 계속 홀드상태 | F22: Tourmind PIC랑 계속 확인 중
C23: HBXgroup | D23: 기타 | E23: 미팅 요청 | F23: meeting arrangement
C24: Chai yi Lv | D24: 신규 계약 | E24: NDA/ Contract 진행 중 | F24: Bank guarantee 진행할 예정, 다만 Bank guarantee 통과 못 하는 부분 다시 deposit 필요함 | G24: 프로님 요청하는 부분이 있어, 은행에 따라 다를 수 있음
A25: 4월21일~4월30일 | B25: Grace | C25: Kake | D25: 요금/물량 이슈 | E25: 현재 유일한 3rd party 일부 상품 판매하고 있음 -일중 이슈 인해 일본 3rd party 건 많이 판매 못 함, 측 오늘 3rdparty 우선 닫음 | F25: Kake 직계약 다시 pull할 예정이고 5/1 행사 다가오기 때문에 3rd party는 5/5이후 다시 오픈 예정
C26: Tourmind | D26: 정산이슈 | E26: 3/16~3/31 payment 다시 반송되었음 -이유: 중계 은행 없기 때문에 | F26: citi은행 새로운 invoice 다시 발행 - 내주 확인 필요
C27: Staylah | D27: 신규 계약 | E27: 연동하고 싶지만 현재 우리 닷비즈도 고도화하면서 우선 펜딩 | F27: CMS list 요청 및 받기
C28: Huamin | D28: 라이브 오픈 준비 | E28: 원래 내주 오픈 예정. 상대측 시스템 조율 중 오픈 시점 5/10 그 주 예정 | F28: 5/10 다시 확인 필요
C29: Elong | D29: 기타 | E29: Epayment test 필요asap | F29: 지라로 신청했음 -아직 대기 중 , 빨리 진행 필요
C30: Hibeds | D30: API 연동 진행 | E30: Hibeds: 우리랑 연동 먼저, cross 나중에 실행하기로 했음 | F30: key credential 신청, 필요 서류 보낼 예정
C31: PKARE | D31: 정산이슈 | E31: 우리한테 큰 공지가 없지만 은행 계정 바꾸려면 PK도 새로운 account 생성 필요, 그거 때문에 payment 조금 delay | F31: Vicky한테 공지 및 확인
C32: PKARE | D32: 요금/물량 이슈 | E32: (위 내용 동일) 4/22, 오후 2시 부터~ 24시간 이내 caching 시간 필요하기 때문에 이 시간 동안 부킹이 없음 | F32: 부킹 정상 들어오는지 확인/ Third Party Payor Agreement sign 필요
C33: Heytrip | D33: 신규 계약 | E33: 신규 계약 다시 진행 | F33: 요금 환불 및 다시 받기 그리고 termination 계약서 작성 필요
C34: Elong | D34: 기타 | E34: Ebooking 관련 interface 채크 필요 | F34: IT과 확인 (4/28)
C35: Alitrip | D35: 요금/물량 이슈 | E35: 요금/재고 이슈 발생, no rate 경우 체널에게 전달 받지 못함, API 자동 중단됨 | F35: IT과 확인 (4/28) | G35: QPS 문제도 있기도하고 사전 필터링 또는 검증 로직을 적용하는 것은 어렵음
C36: Zhiyi Technology | D36: 신규 계약 | E36: 신규 핸드링 - SLA 문제 확인 중
C37: Coolprice | D37: 기타 | E37: 예약건은 API로 하는게 아님 Dotbiz으로 들어옴 | F37: 우리 고객사기 때문에 usd10 차감해줌
C38: PKARE | D38: 요금/물량 이슈 | E38: QPS 초과 및 caching에 대한 | F38: 아직 모니터링 필요, 정상 때 까지 | G38: Third Party Payor Agreement sign: 은행 정보 업데이트 QPS 불안정적인 (4/25~4/29 오전) 4/29 오후 3시쯤 정상들어옴, 다만 다른 문제 있는지 모니터링 필요
C39: Huamin | D39: 매핑/콘텐츠 | E39: Ctrip 최신 room mapping list 요청 | F39: Karl랑 확인 중이고 , mapping 빨리 진행 필요, or 오픈 지연됨 | G39: Ctrip mapping 리스트 전달했음
C40: Amerilink | D40: 신규 계약 | E40: Bank guarantee/deposit 안됨 allianze trade - 우리는 직접 신청해야함. 결론: credit 요청 : usd 10000로 시작 이유: 물량이 올라갈 수 없는 상황이면 bank guarantee 신청 어렵다고 함 | F40: 이거 홀드? 아님 allianze trade 담당자 섭의 필요?
C41: Linkstay | D41: 신규 계약 | E41: API certification 진행 완 | F41: 보증금 받은 후에 오픈 확인
C42: Fangcang (AMT) | D42: 신규 계약 | E42: 계약 진행 5/5이후 | F42: -
C43: Qunar | D43: 정산이슈 | E43: Entity 바꾸면서 서류 진행 필요 | F43: 늦어도 6월 다 끝나야함
A44: 5월6일~5월8일 | B44: Grace | C44: Linkstay | D44: API 연동 진행 | E44: 오픈 직전 | F44: 보증금 받았음, 5/7라이브 테스트 후 오픈 예정
C45: Huamin | D45: 매핑/콘텐츠 | E45: 매핑 이슈 확인 | F45: Ctrip 건 쓰기 때문에 불 필요 code 발견- 해결 방법, ignore
C46: Qiyouji | D46: 정산이슈 | E46: CS 이슈 | F46: CS 측 답변 끝나지만 우리 측도 개선 필요하다고 생각함 | G46: 문화, CS, 나라도 다르기 때문에 우리 어느 부분 자세하게 필요하는 지 파악 필요 특히, 이미 물량 많이 없는 업체- 오마이의 실수였으면 고객사에게 더 큰 꼬리 잡으면 안된다고 생각함
C47: Klook | D47: API 연동 진행 | E47: 계약서 | F47: CS부분 계속 조율하고 있으며 SLA 도 받을 예정
C48: Cola | D48: 신규 계약 | E48: 개발 및 계약 | F48: 개발 일정 , 5,6월이지만 현재 확인 중
C49: Star Travel | D49: API 연동 진행 | E49: 연동 시간 늘어짐 | F49: 4월 연동 시작해야지만 종종 이슈 때문에 지연됨 | G49: IT 한명만 기 때문에 시간 걸림
C50: Convergent | D50: 이상 없음(No Issue) | E50: 물량 느린거 확인 | F50: 프로모션 진행기 때문에 물량 푹 상승 | G50: 현재 시장도 조사 및 확인
C51: Meituan | D51: 이상 없음(No Issue) | E51: 현재 시장 트렌드 확인 | F51: 무가나 노출 안되는 이슈 있어, 다른 업체 다 수집해서 다음주 바로 scm보냄 | G51: 현재 시장도 조사 및 확인
C52: Dida | D52: 이상 없음(No Issue) | E52: 현재 시장 트렌드 확인 | F52: 무가나 노출 안되는 이슈 있어, 다른 업체 다 수집해서 다음주 바로 scm보냄 | G52: 현재 시장도 조사 및 확인
C53: PKARE | D53: 이상 없음(No Issue) | E53: 현재 시장 트렌드 확인 | F53: 휴가 중이라 답변 다음주 다시 체이스, 그리고 물량 이슈도 확인 필요
C54: Ctrip | D54: 기타 | E54: CTRIP 계정 받기 | F54: 다음주 요아나와 대리통 사용하는 법 알아가기
C55: Chai yi Lv | D55: 신규 계약 | E55: bank guarantee 진행 중 | F55: 아직 확인 중이라, 최대한 우리에게 전달함
C56: Just go trip | D56: 신규 계약 | E56: 보증금 1만 불로 협의 | F56: 현재 협의 중, 가능하는 지 다음주 확인
C57: Heytrip | D57: 계약 갱신 | E57: 환불 진행 필요, 다만 고객사 인보이스 요청 | F57: 인보이스 요청 중임 | G57: 다만 정산 5월 건 부터 싱가포로 바꿈, 정산 시간도 5일 -> 7일로 전환했음
A58: 5월11일~5월15일 | B58: Grace | C58: Linkstay | D58: 신규 계약 | E58: 이번 주 오픈 예정 | F58: 확인해보니 아직 오픈 안되어서 다음주 다시 확인
C59: Tongcheng | D59: 기타 | E59: 일본 담당 롬 탑리스트 요청 | F59: 탑리스트 직계약만 보냈음
C60: Meituan | D60: 정산이슈 | E60: 현재 벤딩 건 다 MT와 비키 확인 중 26일 다 받아야함 | F60: 당음주 벤딩건 무사히 들어오는지 확인 필요
C61: Hibeds | D61: 신규 계약 | E61: NDA 서로 이익 보장 안되어 Hibeds건 NDA 확인 | F61: Hibeds NDA 우리 내부 확인 필요 | G61: 월화 완성 필요, 상상보다 담당자 분이 욺지기 빠른 편
C62: Alitrip | D62: 매핑/콘텐츠 | E62: 우리 기술적인 불안정적이고 내주 3번 offline 됨 | F62: 확인해보니 현재 PIC 한국/일본 Mapping 완료
C63: Alitrip | D63: 기타 | E63: Push data 관련 - Alitrip 최근 마지막 받았던 push data는 작년 임 | F63: 우리는 체널 측에 Push하는 데이터 측시 Push든 꾸준히 Push 등 필요함
C64: Huamin | D64: 기타 | E64: 오픈 준비 | F64: 5/12 오픈 완료 | G64: 부킹 건 하루 5건 ~ 10건 사이 qps 없음 - toptown과 동일 透传模式 사용, 우리 IT monitoring 중
C65: Ctrip | D65: 매핑/콘텐츠 | E65: Mapping 이슈 제일 큼 | F65: 다음주 금요일 Mapping 관련 ctrip에게 교육 받기 with Content
C66: Ctrip | D66: 기타 | E66: It issue | F66: Ctrip Open Platform에서 downstream, failed logs 확인해서 IT 전달, 일반적인 시스템 문제지 더 많은 문제 있을지
C67: Fangcang (AMT) | D67: 신규 계약 | E67: 계약서 피드백을 받았음 | F67: 우리 내부 확인 필요
C68: Klook | D68: 신규 계약 | E68: 계약서 피드백을 받았음 | F68: Klook 내 SLA 까지 우리 다 확인 필요
C69: Tourmind | D69: 정산이슈 | E69: 3.16~3.30 정산 | F69: 5/12 AGT 반환 건 받았어 내주/차주 오마이 입금 가능
C70: Elong | D70: 기타 | E70: Meituan와 2 일본 호텔 받아 -promotion | F70: 이륭이 한국 말고 다른 나라도 된다고 해서 JP Scm 리스트 설치해서 받았는데.. 일본만 안되더라고.. 청치상 문제기 때문에 | G70: 현재 eLONG 태국 WORKSHOP 중이라 답변이 못 받아서 JP SCM 정확성 답변 줄 수 없음
A71: 5월18일~5월22일 | B71: Grace | C71: Pkfare | D71: 기타 | E71: configuration added | F71: Configuration added, 물량 다시 상승
C72: Ctrip | D72: 매핑/콘텐츠 | E72: Mapping 이슈 제일 큼 | F72: 금요일 매핑 관련 다시 확인
C73: Ctrip | D73: 매핑/콘텐츠 | E73: Active/inactive hotel push | F73: old and new history need to check
C74: Alitrip | D74: 기타 | E74: lose hotel 에 대한 관련 | F74: lose 대신 마크업 2주간 진행 | G74: 5/25~6/8 오전 9시
C75: Heytrip | D75: 정산이슈 | E75: Deposit 입금 잘 못 | F75: 엔화로 입금, 엔화로 반납(termination 경우)
C76: Heytrip | D76: 정산이슈 | E76: 5/1~5/15 Settlement 건 | F76: 한국 하나 입금했음 | G76: 프로님과 확인해서 문제 없음
C77: Meituan | D77: 정산이슈 | E77: 정산 마무리 필요 | F77: 펜딩건 5/20 입금 완료
C78: Linkstay | D78: 라이브 오픈 준비 | E78: open 5/18 | F78: 부킹 건 2건 | G78: 아직 물량 없음
C79: Asiayo | D79: 기타 | E79: deposit refund | F79: 소피아님과 확인- 기안 완료 | G79: 소피아님 마무리 필요
C80: Tourmind | D80: 기타 | E80: 물량 확인 | F80: 기술상이 업그래드 됐음 물량 소푹 상승 | G80: 1주더 모니터링 필요
C81: Bingtrip | D81: 기타 | E81: 물량 첫 날 계속 상승 유지 | F81: 5/25 마크업 일 주 진행, 물량 및 경쟁사 확인 | G81: QPS - F/U 6/22~
A82: 5월 25~29일 | B82: Grace | C82: KK Day | D82: 테스트/검증 | E82: 경쟁력 요금 확인 필요 | F82: 테스트 아카운드 진행 | G82: 5/26~6/30
C83: Alitrip | D83: 프로모션제안 | E83: 마크업 서로 맞춤 | F83: 2 주 (5/25~6/8 오전 10시 한국 시간) | G83: Override F/U
C84: Bingtrip | D84: 프로모션제안 | E84: 오마이 마크업 내림 | F84: 1 주 (5/25~6/1 10시 한국 시간)
C85: Klook | D85: 기타 | E85: 계약 빨리 확인 필요 | F85: 계약 아직 진행하면서 SLA 도 우선 요청
C86: Ningbo candoor consulting Co., Ltd. | D86: 신규 계약 | E86: test account | F86: 신규 업체 ,test account 확인 | G86: 6/19 F/U
C87: JL Tour | D87: 신규 계약 | E87: 6월 연동 시작 가능 - chase | F87: 6-7 월 개발 예정 | G87: 6/19 F/U
C88: SN tour | D88: 신규 계약 | E88: test ID | F88: 신규 업체 ,test account 확인 | G88: 6/19 F/U
C89: Mengtu | D89: 신규 계약 | E89: API 가능 | F89: 신규 업체 ,test account 확인 | G89: 6/19 F/U
C90: Wingpulse | D90: 신규 계약 | E90: 바로 연동 가능 | F90: 초안 예정 | G90: 6/19 F/U
C91: Hotelsys.com | D91: 신규 계약 | E91: API 가능 + test ID | F91: 신규 업체 ,test account 확인 | G91: 6/19 F/U
C92: Nice tour | D92: 신규 계약 | E92: Group reservation 가능 정보 전달 | F92: 정보 전달
C93: Haven Trip | D93: 신규 계약 | E93: 협업 방안 찾기 | F93: - | G93: 6/19 F/U
C94: Huamao | D94: 신규 계약 | E94: 진행 예정 | F94: 초안 예정 | G94: 6/19 F/U
C95: Ziru | D95: 신규 계약 | E95: test account | F95: 신규 업체 ,test account 확인 | G95: 6/19 F/U
C96: Yunnan province international travel agency | D96: 신규 계약 | E96: test account | F96: 신규 업체 ,test account 확인 | G96: 6/19 F/U
A97: 6월 1~5일 | B97: Grace | C97: Klook | D97: 신규 계약 | E97: Contract and SLA checking | F97: Is still checking with SLA
C98: Hibeds | D98: 신규 계약 | E98: API documents | F98: Contract done, API lead time checking
C99: Wild China | D99: 신규 계약 | E99: Focus on Luxury hotels | F99: Currently timeline is not suitable to connect
C100: Mintu | D100: 신규 계약 | E100: Deposit issue | F100: Deposit issue/alliance insurance required | G100: 6/19 F/U
...

Sheet Award
A1: Award Name | B1: Year | C1: Awarding Company | D1: Remark
A2: Collaborative Excellent Partner | B2: 2023 | C2: Trip.com
A3: Performance Excellent Partner | B3: 2024
A4: Performance Excellent Partner | B4: 2025 | D4: JP, KR 호텔 파트너
A5: Collaborative Excellent Partner | B5: 2025 | D5: VN 호텔 파트너
A6: Outstanding Progress Partner | B6: 2026 | D6: VN 호텔 파트너
A7: Outstanding Partner Award | B7: 2022 | C7: Meituan
A8: Influential Partner of the Year | B8: 2025
A9: Outstanding Contribution Award | B9: 2025 | C9: Elong
A10: Significant Progress Award | B10: 2025 | C10: Alitrip

Sheet CRM
B1: Channel Information (채널 정보)
A2: # | B2: Status | C2: Tier | D2: KPI Q3 | E2: Type | F2: Channel Name | G2: Company Name | H2: PIC(OMH) | I2: Handover To | J2: Entity | K2: Region | L2: Country | M2: City | N2: BM | O2: PIC(Channel) | P2: Position | Q2: System | R2: Switching | S2: Supply | T2: Hotel Data | U2: Room Data | V2: Contact Number | W2: Chating APPs | X2: E-mail | Y2: E-mail 2 | Z2: Homepage | AA2: Address | AB2: Currency ( for KR hotels) | AC2: Currency ( for JP hotels) | AD2: Currency ( for VN hotels) | AE2: Currency ( for others) | AF2: Payment Type | AG2: Payment period | AH2: Deposit Type | AI2: Deposit | AJ2: Provide DP Rate
B3: Active | C3: Tier 1 | D3: 1500 | E3: API | F3: Ctrip Korea | G3: Trip.com Travel Singapore Pte. Ltd. | H3: Grace | J3: Singapore | K3: East Asia | L3: Global | M3: Korea | N3: B2C | O3: Mr. Nam | P3: 부장 | Z3: https://kr.trip.com | AA3: 7/F D-Tower 17 Jungro 3 Gil Jongrogu, Seoul, Republic of Korea | AF3: weekly | AG3: 5 | AI3: 0
B4: Active | C4: Tier 1 | D4: 1000 | E4: API | F4: Agoda | G4: Agoda Company Pte. Ltd. | H4: Ben | I4: Bryant | J4: Shanghai | K4: Global | L4: Global | M4: Shanghai | N4: B2C | O4: Ms. Marie Mr. Anthony (Thailand) | P4: Manager Director- Travel Distribution | S4: Active | V4: +82 10.4195.2032 66 81 825 6660 | X4: Jihyun.lee@agoda.com udomchai.miksirakul@agoda.com | Z4: www.agoda.com | AA4: 999/9 Rama 1 Road. The Offices at Central World, 27th floor (changing soon in April)
B5: Active | C5: Tier 2 | E5: API | F5: Dida | G5: DidaTravel International Limited | H5: Grace | J5: China | K5: East Asia | L5: China | M5: Shenzhen | N5: B2B | O5: Ms. Seven | P5: Senior Account Manager | S5: Active | V5: +86 13524375996 | X5: seven.sun@dida.com | Z5: Dida | AA5: Room 17C, D, E, Tower B, Global Harbor, No. 1188 Kaixuan North Road, Putuo District, Shanghai. | AB5: USD | AC5: JYP | AD5: USD | AE5: USD | AF5: bi-weekly | AG5: 5 | AJ5: NO
B6: Active | C6: Tier 1 | E6: API | F6: Meituan | G6: Xigua limited | H6: Grace | J6: China | K6: East Asia | L6: China | M6: Shanghai | N6: B2B/B2C | O6: Ms. Zhang | P6: Senior Market Manager | V6: +86 18217620588 | X6: zhangdan58@meituan.com | AA6: 上海市黄兴路221号互联宝地T6栋 Building T6, Hulianbaodi, No.221 Huangxing Road, Shanghai | AB6: USD | AC6: JYP | AD6: USD | AE6: USD | AF6: weekly | AG6: 7 | AJ6: NO
B7: Active | C7: Tier 2 | E7: API | F7: Elong | G7: Tongcheng Travel Holdings Limited eLong International Travel (Hong Kong) Limited | H7: Grace | J7: China | K7: East Asia | L7: China | M7: Korea | N7: B2C | O7: Ms. Iris | P7: International Market Director | V7: +82 1094398482 | X7: iris.nam@ly.com | AA7: 6F, Noon Square, 14, Myeongdong-gil, Jung-gu, Seoul, Korea | AB7: JYP | AC7: JYP | AD7: JYP | AE7: JYP | AF7: weekly | AG7: 7 | AJ7: NO
B8: Active | C8: Tier 2 | E8: API | F8: PKFARE API | G8: 深圳马可孛罗科技有限公司 (Marco Polo Technology Co., Ltd.) | H8: Grace | J8: Hongkong | K8: East Asia | L8: China | M8: Shenzhen | N8: B2B | O8: Ms. Cici | P8: Director | V8: +86 13588300346 | X8: cici.tang@pkfare.com | Z8: www.PKFARE.com | AA8: 深圳市南山区科技中一路198号创益科兴科学园A座23层 | AB8: USD | AC8: USD | AD8: USD | AE8: USD | AF8: bi-weekly | AG8: 7 | AH8: Bank Guarantee | AI8: USD 10,000 (실결제 USD 9,964) | AJ8: NO
B9: Active | C9: Tier 1 | D9: 100 | E9: API | F9: Ctrip Vietnam | G9: Trip.com Travel Singapore Pte. Ltd. | H9: Ben | I9: Aiden | J9: Vietnam | K9: East South Asia | L9: China | M9: Vietnam | N9: B2C | O9: Ms. Lucy | P9: Vietnam Market Manager | V9: +84 935659690 | X9: Lucynguyen@trip.com | Z9: https://vn.trip.com/ | AA9: L12, LIM TOWER 3, 29A Nguyen Dinh Chieu St, Da Kao Ward, Dist 01, HCMC | AB9: VND | AC9: VND | AD9: VND | AE9: VND | AF9: weekly | AG9: 5 | AI9: 0
B10: Active | C10: Tier 2 | E10: API | F10: Convergent API (Huizhi) | G10: Convergent International Travel Development Co., Ltd. | H10: Grace | J10: Shenzhen | K10: East Asia | L10: China | M10: Shenzhen | N10: B2B | O10: Mr. Bruce (sales) Ms. Ying (op) Mr. Benny | P10: Senior BD Manager (API) Head of Third- Party Cooperation | V10: +86-18826240125 86 134 3181 6755 | X10: bruce@huizhi-intl.com ying.liu@huizhi-intl.com | Z10: www.huizhi-intl.com | AA10: 广东省深圳市福田区卓越世纪中心四号楼35A02C | AB10: USD | AC10: USD | AD10: USD | AE10: USD | AF10: bi-weekly | AG10: 15 | AH10: Bank Guarantee | AI10: USD 10,000 | AJ10: NO
B11: Active | C11: Tier 3 | E11: API | F11: triptopaz | G11: Triptopaz | H11: Aiden | J11: Korea | K11: East Asia | L11: Korea | M11: Seoul | N11: B2C | O11: 류 소정 김 종우 | P11: 차장 매니저 | V11: =82-10-8341-2208 -> -10477 | X11: sage@triptopaz.com pauljw@triptopaz.com | AA11: 서울시 송파구 석촌동 183-4 펙베이빌딩 6층 | AB11: KRW | AC11: KRW | AD11: KRW | AE11: KRW | AF11: bi-weekly | AG11: 15 | AI11: 0
B12: Active | C12: Tier 3 | E12: API | F12: Qiyouji | G12: GUANGDONG QIYOUJI INTERNATIONAL TRAVEL SERVICE CO.,LTD | H12: Grace | J12: Guangzhou | K12: East Asia | L12: China | M12: Guangzhou | N12: B2B | O12: Ms. Lillian | P12: Project Manager | V12: =86-20-31526590 -> -31526524 | X12: lillian.lin@qiyoji.com | Z12: http://baofangke.qiyouji.com | AA12: Office 312, Hongxing Building, No. 238, Jinzhong Heng Lu, Baiyun Distric, Guangzhou, CHINA | AB12: JYP | AC12: JPY | AD12: JYP | AE12: JYP | AF12: bi-weekly | AG12: 15 | AH12: Bank Guarantee | AI12: USD 15,000 | AJ12: NO
B13: Active | C13: Tier 3 | E13: API | F13: Qunar | G13: Qunar.com Information Technology Co., Ltd. | H13: Grace | J13: Beijing | K13: East Asia | L13: China | M13: Beijing | N13: B2C | O13: Ms. Wen | P13: Business Development Director-OSC | V13: =86-137-1517-1047 -> -2615 | X13: wencheng.cheng@qunar.com | Z13: www.qunar.com/ | AA13: 深圳市福田区福华三路168号荣超国际商会中心 | AB13: USD | AC13: USD | AD13: USD | AE13: USD | AF13: weekly | AG13: 7 | AJ13: NO
B14: Active | C14: Tier 3 | E14: API | F14: Alitrip | G14: Alibaba Group (Fliggy) | H14: Grace | J14: China | K14: East Asia | L14: China | M14: Japan | N14: B2B/B2C | O14: Mr. Harry | P14: Senior Supplier Manager | V14: + 080 3852-0931 | W14: wechat | X14: hongbo.h@alibaba-inc.com | Z14: https://www.fliggy.com/ | AA14: 浙江省余杭区阿里巴巴西溪园区C区--C区访客中心，阿里巴巴西溪C区(C2门) | AB14: JYP | AC14: JPY | AD14: JYP | AE14: JYP | AF14: bi-weekly | AG14: 15 | AJ14: NO
B15: Active | C15: Tier 3 | D15: 30 | E15: API | F15: Myrealtrip API | G15: Myrealtrip Inc. | H15: Aiden | J15: Korea | K15: East Asia | L15: Korea | M15: Seoul | N15: B2C | O15: 이미소 | P15: 매니저 | Z15: https://www.myrealtrip.com/ | AA15: 서울시 서초구 강남대로 311, 드림플러스 강남 18F | AB15: KRW | AC15: KRW | AD15: KRW | AE15: KRW | AF15: bi-weekly | AG15: 15 | AI15: 0
B16: Active | C16: Tier 3 | E16: API | F16: Hikari Global | G16: Hikari Global Inc. | H16: Aiden | J16: Korea | K16: East Asia | L16: Korea | M16: Seoul | N16: B2B | O16: Ms. Park/Mei | P16: Overseas Manager | V16: +82 01089261624 | X16: wigus0909@hotmail.com | Z16: https://www.hikariglobal.co.kr/ | AA16: 03149 서울특별시 종로구 인사동5길 42, 종로빌딩 11층 | AB16: JYP | AC16: JPY | AD16: JYP | AE16: JYP | AF16: weekly | AG16: 5 | AI16: 0
B17: Active | C17: Tier 3 | D17: 50 | E17: API | F17: Tripbtoz | G17: Tripbtoz Inc. | H17: Aiden | J17: Korea | K17: East Asia | L17: Korea | M17: Seoul | N17: B2B/B2C | O17: 이미정 | P17: 매니저 | V17: +82 10 7328 5450 | X17: mijungl@tripbtoz.com | Z17: https://www.tripbtoz.com/ | AA17: 서울시 강남구 테헤란로 415 L7빌딩 3층 | AB17: KRW | AC17: JPY | AD17: KRW | AE17: KRW | AF17: bi-weekly | AG17: 15 | AH17: Guarantee Insurance | AI17: 30000000
B18: Active | C18: Tier 3 | D18: 20 | E18: API | F18: Hotelpass | G18: Hotelpass Global LTD. | H18: Aiden | J18: Korea | K18: East Asia | L18: Korea | M18: Seoul | N18: B2B/B2C | O18: 박혜수 | P18: 팀장 | V18: +82 2 2262 5114 | X18: naomi@hotelpass.com | AA18: 13F, Gwanghui Bldg., 307 Toegyero, Jung-gu, Seoul, Korea | AB18: KRW | AC18: JPY | AD18: USD | AE18: USD | AF18: Monthly | AG18: 31 | AI18: 0
B19: Active | C19: Tier 3 | F19: Kakao | G19: Kakao Corp. | H19: Aiden | J19: Korea | K19: East Asia | L19: Korea | M19: Gyeonggi | N19: B2C | Z19: https://travel.kakao.com/
B20: Active | C20: Tier 3 | E20: Dotbiz | F20: GC Company (여기어때) | G20: (주)여기어때투어 | H20: Aiden | J20: Korea | K20: East Asia | L20: Korea | M20: Seoul | N20: B2C | O20: 한유진 | P20: 팀장 | X20: ruby@gctour.co.kr | AA20: 서울 종로구 효자로 23 국제항운빌딩 2 | AB20: KRW | AC20: KRW | AD20: KRW | AE20: KRW | AF20: Monthly | AG20: 31
B21: Active | C21: Tier 3 | E21: API | F21: Toptown API (시트립 Vacation 자회사) | G21: Shanghai Toptown International Travel Agency CO.,LTD | H21: Grace | J21: Hongkong | K21: East Asia | L21: China | M21: Shanghai | N21: B2B | O21: Ms. Freya | P21: Vice Director | V21: +86 158 0045 4692 | X21: freya.wang@toptown.cn | AA21: "Room1604, 16F, No. 807 Zhaojiabang Road, Xuhui District, Shanghai 200032, China 上海市徐汇区肇嘉浜路807号（五洲国际大厦）1604室" | AB21: USD | AC21: USD | AD21: USD | AE21: USD | AF21: bi-weekly | AG21: 5 | AJ21: NO
B22: Active | C22: Tier 1 | D22: 100 | E22: API | F22: Traveloka | G22: Traveloka Services Pte. Ltd | H22: Ben | I22: Bryant | J22: Indonesia | K22: East South Asia | L22: Indonesia | M22: Jakarta | N22: B2C | O22: Ida Ayu Agung Dwi Cahyantari | P22: PIC | X22: ida.cahyantari@traveloka.com | Z22: https://www.traveloka.com/en-vn | AA22: Green Office Park 1 BSD City, Jl. BSD Raya Bar., Sampora, Kec. Cisauk, Kabupaten Tangerang, Banten 15345. | AB22: USD | AC22: USD | AD22: USD | AE22: USD | AF22: Monthly | AG22: 31 | AJ22: NO
B23: Active | C23: Tier 3 | E23: Dotbiz | F23: airtel.com(에어텔닷컴) | G23: 에어텔닷컴 | H23: Aiden | J23: Korea | K23: East Asia | L23: Korea | M23: Seoul | N23: B2C | O23: 김성준 | P23: 주임 | X23: sjun0223@airteltour.com | Z23: https://www.airtel.co.kr/ | AB23: KRW | AC23: KRW | AD23: KRW | AE23: KRW
B24: Active | C24: Tier 3 | E24: Dotbiz | F24: Hana Tour_JP Team | G24: (주)하나투어 | H24: Aiden | J24: Korea | K24: East Asia | L24: Korea | M24: Seoul | N24: B2C | O24: 이현지 | P24: 선임 | X24: hyun77@hanatour.com | Z24: https://www.hanatour.com/ | AB24: USD | AC24: JPY | AD24: USD | AE24: USD | AF24: Monthly | AG24: 31 | AI24: 0
B25: Active | C25: Tier 3 | E25: Dotbiz | F25: Onlinetour | G25: (주)온라인투어 | H25: Aiden | J25: Korea | K25: East Asia | L25: Korea | M25: Seoul | N25: B2C | O25: GC Company와 합병 | Z25: https://www.onlinetour.co.kr/ | AB25: KRW | AC25: KRW | AD25: KRW | AE25: KRW | AF25: bi-weekly | AG25: 15
B26: Active | C26: Tier 3 | E26: Dotbiz | F26: Modetour Network | G26: (주)모두투어네트워크 | H26: Aiden | J26: Korea | K26: East Asia | L26: Korea | M26: Seoul | N26: B2C | O26: 정기혜 | P26: 매니저 | X26: jung_kihye@modetour.com | Z26: https://www.modetour.com/
B27: Active | C27: Tier 3 | E27: Dotbiz | F27: KKDAY | G27: KKday Group | H27: Aiden | J27: Taiwan | K27: East Asia | L27: Taiwan | M27: Taipei | N27: B2C | O27: Mr. Wiko | Z27: https://www.kkday.com/
B28: Active | C28: Tier 3 | E28: Dotbiz | F28: The Hyundai Travel | G28: 현대백화점면세점 | H28: Aiden | J28: Korea | K28: East Asia | L28: Korea | M28: Seoul | O28: 현대드림투어 계정 사용
B29: Active | C29: Tier 3 | E29: API (B2C) | F29: bizplay | G29: bizplay Inc. | H29: Aiden | J29: Korea | K29: East Asia | L29: Korea | M29: Seoul | O29: 여명호 | P29: 팀장 | X29: ymh0510@bizplay.co.kr
B30: Active | F30: Hodo Japan | G30: Hodo Japan Inc. | H30: Aiden | K30: East Asia | L30: Japan
B31: Active | C31: Tier 3 | E31: API | F31: Stayzada | G31: Stayzada | H31: Aiden | J31: Korea | K31: East Asia | L31: Korea | M31: Seoul | O31: 최영학 | P31: 이사 | X31: eversnake@naver.com
B32: Active | C32: Tier 3 | E32: Dotbiz | F32: White Windmill Tour | G32: White Windmill Tour | H32: Aiden | J32: Korea | K32: East Asia | L32: Korea | M32: Seoul | O32: 김수혁 | P32: 매니저 | X32: ppaazz4@naver.com
B33: Active | C33: Tier 3 | F33: Webbeds DMC | H33: Aiden | K33: Global | L33: Global
B34: Active | C34: Tier 3 | E34: Dotbiz | F34: goodtimetour | G34: goodtimetour | H34: Aiden | J34: Korea | K34: East Asia | L34: Korea | M34: Seoul | O34: 민병일 | P34: 사장
B35: Active | C35: Tier 3 | E35: Dotbiz | F35: Geumson Tour | G35: 주식회사 금손투어 | H35: Aiden | J35: Korea | K35: East Asia | L35: Korea | M35: Seoul | O35: 이성범 | X35: togeumson@naver.com
B36: New | F36: Go UNI Travel (JPY) | G36: (주)Go UNI Travel | H36: Grace | J36: Taiwan | K36: East Asia | L36: Taiwan | M36: Taipei | N36: B2C
B37: Active | C37: Tier 3 | E37: API | F37: Hana card travel bucket | G37: (주)하나카드 | H37: Aiden | J37: Korea | K37: East Asia | L37: Korea | M37: Seoul
B38: Active | C38: Tier 3 | E38: Dotbiz | F38: Centum Golf Inc. | G38: Centum Golf Inc. | H38: Aiden | J38: Korea | K38: East Asia | L38: Korea | M38: Seoul | O38: 강청구 | P38: 본부장 | X38: joe.kang@centumgolf.com
B39: Active | C39: Tier 3 | E39: Dotbiz | F39: Ilbonman | G39: 주식회사 일본만 | H39: Aiden | J39: Korea | K39: East Asia | L39: Korea | M39: Seoul | O39: 이주영 | P39: 팀장 | X39: gogojd84@ilbonman.com
B40: Active | C40: Tier 3 | E40: Dotbiz | F40: VECTORCOM | H40: Aiden | J40: Korea | K40: East Asia | L40: Korea | M40: Seoul
B41: Active | C41: Tier 3 | E41: Dotbiz | F41: CHALET KOREA | G41: 샬레코리아 | H41: Aiden | J41: Korea | K41: East Asia | L41: Korea | M41: Seoul | O41: 이소영 | P41: 과장 | X41: syyc220@funnbiz.co.kr
B42: Active | C42: Tier 3 | E42: Dotbiz | F42: 여행작가 박은하 | H42: Aiden | J42: Korea | K42: East Asia | L42: Korea | M42: Seoul
B43: Active | C43: Tier 3 | E43: Dotbiz | F43: (주)스트리밍하우스 | G43: (주)스트리밍하우스 | H43: Aiden | J43: Korea | K43: East Asia | L43: Korea | M43: Seoul | O43: 신동훈 | P43: 대표 | X43: cs@hyuil.co.kr
B44: Active | C44: Tier 3 | E44: API | F44: 11st Korea | G44: (주)11번가 | H44: Aiden | J44: Korea | K44: East Asia | L44: Korea | M44: Seoul | O44: 한주연 | P44: 매니저 | X44: joo11@sk.com | Z44: https://www.11st.co.kr/
B45: Active | C45: Tier 3 | E45: Dotbiz | F45: Hyundai Dream Tour | G45: 현대드림투어 | H45: Aiden | J45: Korea | K45: East Asia | L45: Korea | M45: Seoul | O45: 김정민 | P45: 책임 | X45: gem000617@hyundaidreamtour.com
B46: Pipeline | E46: API | F46: EGL Tours | G46: EGL Tours Company Limited | H46: Grace | J46: Hongkong | K46: East Asia | L46: Hong Kong | M46: Kowloon | N46: B2C | O46: Mr. Tai | P46: Assistant Manager | V46: +852 3692 0888 | X46: info@egltours.com | Z46: www.egltours.com | AA46: 九龍觀塘鴻圖道83號東瀛遊廣場15樓
B47: Pipeline | E47: API | F47: Wing On Travel | G47: 香港永安旅游有限公司 | H47: Grace | J47: Hongkong | K47: East Asia | L47: Hong Kong | M47: Kwuntong | N47: B2C | O47: Ms. Fanny Mr. Grabriel | P47: Assitant Product Manager - FIT Travel Operation Executive Innovative Operation | V47: +852 2928 8882 +86 188 8892 1456 | X47: fannylo@wingontravel.com gabrielzheng@wingontravel.com | AA47: 30/F., Paul Y. Centre, 51 Hung To Road, Kwun Tong, Kowloon, Hongkong
B48: New | E48: API | F48: Travel Expert | G48: 專業旅運 | H48: Grace | J48: Hong Kong | K48: East Asia | L48: Hong Kong | M48: Wanchai | N48: B2C | V48: +852 3700 2999 | X48: enquiry@travelexpert.com.hk
B49: Pipeline | C49: Tier 2 | E49: API | F49: Lion Travel | G49: Lion Travel Service | H49: Grace | J49: Taiwan | K49: East Asia | L49: Taiwan | M49: Taipei | N49: B2C | O49: Ms. VivianLin Ms. Hana Lin Mr. Jeff | P49: Manager FIT Senior Specialist FIT Strategies project Supervisor | V49: 866 912 639 965 866 922 023 582 | X49: vivianlin@liontravel.com hanalin@liontravel.com jeffchan@liontravel.com | AA49: 台北市內湖區石潭路151號
B50: Pipeline | C50: Tier 2 | E50: API | F50: Cola Travel | G50: Colatour Travel Service CO., Ltd. | H50: Grace | J50: Taiwan | K50: East Asia | L50: Taiwan | M50: Taipei | N50: B2C | O50: Ms. Feona | P50: 全球訂房部 Manager | V50: 02-2522-1419 | X50: yufen.hsu@colatour.com.tw | AA50: 10457台北市中山區南京東路二段85號13樓
B51: Pipeline | C51: Tier 3 | E51: API | F51: South East Travel Service | G51: 東南旅遊 | H51: Grace | J51: Taiwan | K51: East Asia | L51: Taiwan | M51: Taipei | N51: B2C | O51: Ms. Yumi | P51: FIT director | V51: 02-25110519 #2712 | X51: yumi.lin@settour.com.tw | AA51: 台北市中山北路二段71號6樓
B52: New | F52: Five Blessings Travel (LifeTravel) | G52: 五福旅遊 | H52: Grace | J52: Taiwan | K52: East Asia | L52: Taiwan | M52: Taipei | N52: B2C | O52: 林宜學/Mrs Lin | P52: Manager | X52: roylin0616@lifetour.com.tw
B53: New | F53: Everfun Holiday | G53: Everfun Travel Services Corp. | H53: Grace | J53: Taiwan | K53: East Asia | L53: Taiwan | M53: Taipei | N53: B2C | X53: nancyhsieh@everfuntravel.com
B54: New | F54: Besttour.com. tw | G54: 喜鴻假期 | H54: Grace | J54: Taiwan | K54: East Asia | L54: Taiwan | M54: Taipei | N54: B2C | X54: mkd@besttour.com.tw
B55: New | F55: Best Way Travel | G55: 百威旅行社股份有限公司 | H55: Grace | J55: Taiwan | K55: East Asia | L55: Taiwan | M55: Taipei | N55: B2C
B56: New | F56: EZ TRAVEL | G56: 易飛網旅行社股份有限公司 | H56: Grace | J56: Taiwan | K56: East Asia | L56: Taiwan | M56: Taipei | N56: B2C | O56: Mr. Kaken Chen Ms. Maria Huang | P56: Product Planning Product Manager | X56: kakenchen@eztravel.com.tw mariahuang@eztravel.com.tw | AA56: 4F, No.51, Sec.3, Min-Sheng E. Rd., Taipei, Taiwan 104
B57: Pipeline | E57: API | F57: Star Travel Corp | G57: TSG Star Travel Corp. | H57: Grace | J57: Taiwan | K57: East Asia | L57: Taiwan | M57: Taipei | N57: B2C | O57: 葉維瑄/Ms. Syuan | P57: 專員 Associate | V57: 886--8183-3888 #6905 | X57: syuan4848@startravel.com.tw | AA57: 台北市中山區民生東路二段161號7樓 | AI57: 0
B58: New | F58: Mafengwo | G58: Beijing Mafengwo Network Technology Co., Ltd. | H58: Grace | J58: China | K58: East Asia | L58: China | M58: Beijing/Guizhou | N58: B2C | O58: Mr. Nan | P58: Product Manager | V58: 86 186 2950 8970 | X58: nanlei@mafengwo.com | Z58: https://www.mafengwo.cn/ | AA58: 北京市朝阳区酒仙桥北路9号院恒通国际创新园C9马蜂窝
B59: New | C59: Tier 2 | E59: API | F59: RTX | G59: Rakuten Travel Xchange | H59: Aiden | J59: Singapore | K59: East Asia | L59: Singapore | M59: Singapore | N59: B2B wholesaler / API provider | S59: Dev.
B60: Terminated | F60: AsiaYo | H60: Grace | J60: Taiwan | K60: East Asia | L60: Taiwan | M60: Taipei | N60: API,B2C,B2B | O60: 강호연 | P60: 팀장 | X60: brad.kang@asiayo.com | Z60: www.asiayo.com
B61: Active | C61: Tier 3 | E61: API | F61: KAKE | G61: KAKE Hotels Marketing Co., Limited | H61: Grace | J61: Hongkong | K61: East Asia | L61: China | M61: Shenzhen | N61: B2B | O61: Mr. Wesley | P61: VP of Business Development | V61: 86 15012926802 | X61: wesley.li@mq-trip.com | AA61: 深圳市龙岗区坂田街道象角塘社区源创空间-雪象园A3栋四层-411 | AB61: USD | AC61: USD | AD61: USD | AE61: USD | AF61: Bi-weekly | AI61: USD 30,000 (실결제 USD 29,964) | AJ61: NO
B62: New | E62: API | F62: Profit Travel | G62: Profit Travel Agency Company Limited | H62: Grace | J62: Hongkong | K62: East Asia | L62: Hong Kong | M62: TST East | N62: B2B | O62: Mr. Teddy | P62: Manager | V62: 852 23112282 | X62: sales@profittravel.com.hk | AA62: Suite 401, Tower A, New Mandarin Plaza, 14 Science Museum Rd, TST East, KLN, HK
B63: New | E63: API | F63: Westminster | G63: Westminster Travel Ltd. | H63: Grace | J63: Hongkong | K63: East Asia | L63: Hong Kong | M63: Tsuen Wan | N63: B2C
B64: Active | C64: Tier 3 | E64: API | F64: Hey Trip | G64: Hey Trip Intl Corp. | H64: Grace | J64: Hongkong | K64: East Asia | L64: China | M64: Guanzhou | N64: B2B | O64: Mr. Samuel Mr. Jack | P64: Overseas BD Director Vice President | V64: 86 19527134928 86 135 6006 1046 | X64: samuel@heytripgo.com Jack@heytripgo.com | AA64: 番禺区洛浦街道南桂路3号恒达中心A3栋2楼 (HQ) | AB64: USD | AC64: USD | AD64: USD | AE64: USD | AF64: Bi-weekly | AG64: 15 | AH64: Guarantee deposit | AI64: USD 100,000 | AJ64: NO
B65: New | E65: API | F65: MakeMyTrip | G65: MakeMyTrip | H65: Ben | I65: Bryant | J65: India | K65: Global | L65: India | M65: Gurugram | N65: OTA | O65: Vivek | X65: Vivek.Kumar3@go-mmt.com | Z65: www.makemytrip.com/
B66: New | E66: API | F66: travala.com | G66: travala.com | H66: Ben | I66: Bryant | J66: Singapore | K66: Global | L66: Singapore | M66: Singapore | N66: OTA,B2C | Z66: let
B67: New | E67: API | G67: Mutour Int Development Limited | H67: Grace | J67: China | K67: East Asia | L67: China | M67: Guanzhou | N67: B2B | O67: Ms. Ivy Huang Ms. Sonir | P67: Commercial Director Area Commercial Director | V67: 86 157 6622 6924 86 137 1155 9710 | X67: ivy.huang@mutourint.com sonir.chen@mutourint.com | AA67: 天河区黄埔大道西100号富力盈泰广场B座1106
B68: NDA | F68: AllmyTour | H68: Grace | K68: East Asia
B69: NDA | E69: API | F69: Amerilink | G69: Amerilink International Corp. | H69: Grace | J69: USA | K69: East Asia | L69: China | M69: Beijing | N69: B2B | O69: Ms. Wynnie | P69: Business Development Manager - P6 | V69: 86 193 3719 3422 | X69: wynnie.xiao@aichotels.com | Z69: www.aichotels.com | AA69: Suite707, Tower 1, Bright China Chang An Buiding, No.7 Jian Guo Men Nei Ave, Beijing
B70: New | E70: Switching | F70: Ratehawk | G70: Emerging Travel Group (RateHawk brand) | H70: Grace | J70: UAE | K70: Global | L70: UAE | M70: Lisbon / Singapore (Asia HQ) | N70: B2B,switching
B71: Pipeline | E71: API | F71: QianTao | G71: Qian Tao Technology | H71: Grace | J71: China | K71: East Asia | L71: China | M71: Guanzhou | N71: B2B | O71: Ms. Nico Mr. Bob | P71: Business Manager Deputy General Manager | V71: 86 166 76306605 86 188 2628 5255 | X71: guanyuman@gzyuanao.com.cn fengqianyu@qiantaohotel.com | AA71: 广州市白云区鹤联街229号万力创新园C栋C201
B72: New | F72: TBO | G72: TBO Tek Ltd | H72: Ben | I72: Bryant | J72: India / UAE | K72: Global | L72: India / UAE | M72: Shanghai | O72: Catherone Guo | P72: Associate Director Sales | X72: catherine.guo@tbo.com
B73: Active | E73: API | F73: Coolprice | G73: ITF Traveling LTD | H73: Grace | J73: Taiwan | K73: East Asia | L73: Taiwan | M73: New Taipei City | N73: B2C | O73: Mr. Eric | X73: aaa61209@hotmail.com | AA73: 新北市士城区中华路一段219号29楼 | AB73: USD | AC73: USD | AD73: USD | AE73: USD | AF73: Bi-weekly | AI73: USD 10,000 | AJ73: NO
B74: Active | E74: API | F74: Huamin | G74: Hua Min Tourism Reservation Co., Ltd | H74: Grace | J74: Hongkong | K74: East Asia | L74: China | M74: Shanghai | N74: B2B | O74: Mr. Jojo | P74: Business Development Director | V74: +852 2273 1000/1772 | X74: simon.yu@huamin.com.hk/1736464190@qq.com' | AA74: Room 2201, No. 807, Zhaojiabang Road, Shanghai
B75: Pipeline | E75: API | F75: Connexus Travel | G75: Connexus Travel Limitred | H75: Grace | J75: Hongkong | K75: East Asia | L75: Hong Kong | M75: Kowloon | N75: B2B | O75: Ms. Wendy | P75: Head of Product Management | V75: +852 9452 6622 | Z75: www.connexustravel.com
B76: Pipeline | E76: API | F76: ACCOMY TAIWAN | G76: Accomy Taiwan Co., Ltd | H76: Grace | J76: Taiwan | K76: East Asia | L76: Taiwan | M76: Taipei | N76: B2B | O76: Ms. Ariel | P76: Director of Global Partnerdhip & Resource Operations | V76: 86 916 033 331 | X76: ariel.ho@accomy.com
B77: Contract | C77: Tier 2 | E77: API | F77: Klook | G77: Klook Travel Technology Limited | H77: Grace | J77: Hongkong | K77: East Asia | L77: Hong Kong | M77: Central | N77: B2C | O77: Ms. Holly | P77: Partner Development & Connectivity Manager | V77: 852 95090067 | X77: holly.hou@klook.com | AA77: 22/F Kinwick Centre, 32 Hollywood Road, Central, Hong Kong | AB77: JPY | AC77: JPY | AD77: JPY | AE77: JPY | AF77: Bi-weekly | AI77: USD 30,000
B78: Contract | C78: Tier 3 | E78: API | F78: Hotel Bank | G78: Hotel Bank Travel Company Limited | H78: Grace | J78: Taiwan | K78: East Asia | L78: Taiwan | M78: Gaoshiong | N78: B2B | O78: Mr. Terence | P78: Chairman | V78: 886918255520 | X78: terence@hotelbank.com.tw | AA78: No.25, Baoding St. Sanmin Dist. Kaohsiung City | AI78: USD 10,000
B79: New | F79: at | G79: Hotels Reservation Center INC. | H79: Grace | J79: Taiwan | K79: East Asia | L79: Taiwan | M79: Taipei | N79: B2B | O79: Ms. Eunice | P79: General Manager | V79: 886 2 2740 7988 | X79: hrc@hrclink.com.tw/ eunice@hrclink.com.tw | AA79: 台北市復興北路1號12樓之五
B80: Pipeline | E80: API | F80: CN Booking | G80: 龙腾捷旅 | H80: Grace | J80: China | K80: East Asia | L80: China | M80: Shenzhen | N80: B2B | O80: Ms. Michelle Ms. Anna Lan | P80: Overseas Supplier Contracting Manager COO | V80: 0755-8235164 | X80: globalhotel-9@cnbooking.net sz_lanyan@163.com | Z80: https://cnbooking.net/ | AA80: 25th Floor of Tian An International Building, Luohu District, Shenzhen, P.R.C.
B81: New | F81: Cooltrip | G81: 酷旅 | H81: Grace | K81: China
B82: New | F82: Gan You Tong | G82: 赣游通（江西旅游科技集团有限公司） | H82: Grace | K82: China
B83: New | F83: Henglv | G83: 恒旅 | H83: Grace | K83: China
B84: New | F84: Huayi Travel | G84: 香港华逸旅游 | H84: Grace | K84: China
B85: New | F85: JINGDONG TRAVEL | G85: 京东旅行 | H85: Grace | K85: China
B86: New | F86: JL-Tour | G86: 深圳捷旅 | H86: Grace | J86: Japan | K86: East Asia | L86: Japan
B87: New | F87: Lezhi Travel | G87: 成都乐智出游(高德) | H87: Grace | K87: China
B88: New | F88: Spring | G88: 春秋国旅 | H88: Grace | K88: China
B89: Pipeline | E89: API | F89: mytour | G89: MYTOUR VIET NAM COMPANY LIMITED | H89: Ben | I89: Aiden | J89: Vietnam | K89: South East Asia | L89: Vietnam | M89: Ha Noi | N89: B2B/B2C | O89: Ms Huyền | P89: Head Hotel Business /093 6132091‬- CEO My tour | V89: 773371442 | X89: csmytour@mytour.vn | Z89: mytour.vn | AA89: Tầng 3, Tòa nhà Viwaseen, Số 48, Nguyễn Cảnh Dị, Phường Dịch Vọng, Quận Cầu Giấy, Hà Nội, Việt Nam
B90: New | E90: API | F90: ACE Tours & Travel | G90: ACE& TRAVEL PTE LTD | H90: Ben | I90: Bryant | J90: Singapore | K90: South East Asia | L90: Singapore | M90: Singapore | N90: TA,B2C | Z90: https://www.acetours.sg/
B91: New | E91: API | F91: WTS Travel | G91: WTS Travel & Tours Pte Ltd | H91: Ben | I91: Bryant | J91: Singapore | K91: South East Asia | L91: Singapore | M91: Singapore | N91: TA, B2C,B2B | O91: Henry Ching | P91: HOD Overseas Department | V91: 90053309 | X91: enquiries@wtstravel.com.sg;henryching@wts.com.sg | Z91: https://www.wtstravel.com.sg/ | AA91: 3 Temasek Blvd, #01-484 / 485 / 486, Singapore 038983
B92: New | E92: Switching | F92: Trust You | G92: TrustYou GmbH | H92: Ben | I92: Bryant | J92: Singapore | K92: South East Asia | L92: Singapore | M92: Singapore | N92: B2B | Z92: https://www.trustyou.com/
B93: New | E93: API | F93: RMG Tours | G93: RMG Tours | H93: Ben | I93: Bryant | J93: Singapore | K93: South East Asia | L93: Singapore | M93: Singapore | N93: B2B | Z93: https://rmgtours.com/our-suite-of-services/
B94: New | E94: Switching | F94: Hoteliers.Guru | G94: Hoteliers.Guru | H94: Ben | I94: Bryant | J94: Thailand | K94: South East Asia | L94: Thailand | M94: Phuket | N94: Switching/B2B | Z94: https://www.hoteliers.guru/home
B95: Certificate | C95: Tier 3 | E95: API | F95: SS Booking | G95: HONGKONG SSBOOKING TECHNOLOGY COMPANY LIMITED | H95: Grace | J95: Hongkong | K95: East Asia | L95: China | M95: Guanzhou | N95: B2B | O95: Ms. Olivia Ms. Kathleen | P95: Overseas Hotel Operations Director COO | V95: 6 135 2268 8178 82 133 3759 9338 | X95: zc@ssbooking.com zhanghuan@xiangdo.vip | AA95: Room 4008, FULI TIANYU Center, No.180 Jiangnandadaozhong Avenue,Haizhhu District,Guangzhou,China(HQ) | AB95: JPY | AC95: JPY | AD95: JPY | AE95: JPY | AF95: Bi-weekly | AI95: USD 30,000
B96: New | E96: Dotbiz | F96: Lets sees tour & travels | G96: Let See Tour & Travel Pvt.Ltd | H96: Ben | I96: Bryant | J96: India | K96: Middle East | L96: India | M96: Guwahati | N96: B2B/B2C | O96: Zourez Emad | X96: cso@letsseetourandtravels.com | Z96: https://www.letsseetourandtravels.com/ | AA96: Subham Buildwell, RG Baruah Rd, beside NEEPCO bhawan, Sundarpur, Guwahati, Assam 781005,
B97: Pipeline | E97: API | F97: Vntrip | G97: VNTRIP Technology Co., Ltd., | H97: Ben | I97: Aiden | J97: Vietnam | K97: South East Asia | L97: Vietnam | M97: Ha Noi | N97: B2B/B2C | O97: Ms Giang | P97: Sales team leader | W97: zalo: quyên quyên | X97: giang.th.nguyen@vntrip.vn | Y97: sales@vntrip.vn | Z97: Vntrip.vn | AA97: No. 10/55 Thuy Khue Street, Tay Ho Ward, Hanoi City, Vietnam
B98: Certificate | C98: Tier 3 | E98: Dotbiz | F98: chudu24 | G98: CHU DU TWO FOUR SERVICES JOINT STOCK COMPANY | H98: Ben | I98: Aiden | J98: Vietnam | K98: South East Asia | L98: Vietnam | M98: TP HCM | N98: B2B/B2C | O98: Ms Alex | P98: Manager - International Business Development | V98: +84 39 358 7879 | X98: trang.nguyen.quynh@chudu24.com | Y98: outbound@chudu24.com | Z98: chudu24.com | AA98: 10th Floor, 60 Nguyen Dinh Chieu, Tan Dinh Ward, HCMC | AB98: USD | AC98: USD | AD98: VND | AE98: USD | AF98: Prepay
B99: Certificate | E99: API | F99: Gotadi - HCM Branch | G99: GOTADI TRAVEL TECHNOLOGIES JSC | H99: Ben | I99: Aiden | J99: Vietnam | K99: South East Asia | L99: Vietnam | M99: TP HCM | N99: B2B/B2C | O99: Mr. Huỳnh Thế VĨ | P99: Market Manager | V99: +84 939 213 188 | X99: vi.ht@hgaviation.vn | Y99: c@gotadi.com | Z99: gotadi.com | AA99: Tầng 8, Tòa nhà Vietcombank, Số 5 Công Trường Mê Linh, Quận 1, TP. Hồ Chí Minh, Việt Nam | AB99: USD | AC99: USD | AD99: VND | AE99: USD | AF99: Postpay | AG99: Bi-weekly | AH99: N/A
B100: Certificate | E100: Dotbiz | F100: Gotadi - HN Branch | G100: GOTADI TRAVEL TECHNOLOGIES JSC | H100: Ben | I100: Aiden | J100: Vietnam | K100: South East Asia | L100: Vietnam | M100: Ha Noi | N100: B2B/B2C | O100: LE BAO KHANH (Ms.Khanh) | P100: Senior Sales Manager | V100: 0392 867 117 | W100: Zalo | X100: khanh.lebao@gotadi.com | Z100: gotadi.com | AA100: số 47 Phan Chu Trinh, Cửa Nam, Hà Nội | AB100: VND | AC100: VND | AD100: VND | AE100: VND | AF100: Postpay | AG100: Bi-weekly | AH100: N/A
...

Sheet Jasmine
A1: 날짜 (Date) | B1: 작성자 (Reporter) | C1: 채널명 (Channel) | D1: 유형 (Type) | E1: 내용 (Details) | F1: 대응/액션 (Action Plan) | G1: 비고 (Remarks)
A2: 예: 04/07 e.g. MM/DD | B2: 이름 Name | C2: 채널/업체명 Channel/Company Name | D2: ▼ 선택 ▼ Select | E2: 상세 내용 기재 Describe in detail | F2: "무엇을, 언제까지" 명시 Specify "What, by When"
A3: 4/13~4/17 | B3: Jasmine | C3: 씨트립 | D3: 매핑/콘텐츠 | E3: 객실명이 한글로만 설정되어있어 수정필요건 발생 | F3: 200395 - Ocean to you Resort Sokcho Seorak Beach Hotel and condo 847898 - Ulsan The Van Hotel 1001575 - Pohang Daejam-dong Route 422 1001590 - Pyeongtaek Hotel The Gray Songtan KR SCM에서 영문명 수정 후 재푸시 -> 영문으로 씨트립에 반영된 것 확인
D4: 매핑/콘텐츠 | E4: 469892 - Okinawa Harborview Hotel 플랜 노출확인 | F4: 기존에 생성된 플랜이 많아서 신규생성이 안됨. 씨트립과 오마이 판매플랜 대조 후 판매가능한 플랜만 표기해서 전달함
C5: 티켓패스 | D5: 요금/물량 이슈 | E5: 티켓상품 노출도 확인 | F5: 네이버 가격비교 검색 후 몇 페이지에 노출되는지 확인
D6: 요금/물량 이슈 | E6: 간사이리무진 실물티켓 교환가능여부 확인 | F6: 성우님 확인중 (교환가능하며 간사이리무진업체에 먼저 확인중) 이후 JTR 담당자와 교환방법 확인할 예정
D7: 요금/물량 이슈 | E7: E티켓 최저가 비교 75 | F7: 네이버 가격비교 검색 후 최저가 비교
C8: 11번가 | D8: 매핑/콘텐츠 | E8: 매핑이슈 확인 Odays Osiria Residence 오마이객실타입 파셜오션뷰인데 11번가에 오션뷰객실로 그룹핑되어있어서 SCM에서 수정요청함 | F8: 11번가 매니저에게 재차 수정요청했으나, 현재 숙세페 기간으로 확인 및 수정이 어렵다는 답변을 받음. 혹시 모를 컴플레인 방지를 위해 SCM에 해당 호텔 블럭요청하였고, 추후 회신이 올 경우 매핑 수정 후 오픈처리하기로 함
C9: 매뉴얼 생성 | D9: 이상 없음(No Issue) | E9: 탑셀링 리스트 생성 매뉴얼 | F9: 영문본 Vicky에게 전달
A10: 4/20 ~ 4/24 | B10: Jasmine | C10: 씨트립 | D10: 매핑/콘텐츠 | E10: JP000072/344271 Holiday Inn Osaka Namba | F10: 기존에 생성된 플랜이 많아서 신규생성이 안됨. 씨트립과 오마이 판매플랜 대조 후 판매가능한 플랜만 표기해서 전달함
D11: 요금/물량 이슈 | E11: 씨트립에 재고/요금 없는걸로 보인다고 확인요청주신 호텔 6곳 KR000552 Golden Seoul Hotel 738638 KR002883 SR Hotel Sadang 717783 KR003355 Take Hotel Seoul Gwangmyeong 730925 KR003260 Golden City Hotel Dongdaemun 850992 KR000835 SR Hotel Magok 852990 KR002281 Kolon Seacloud Hotel 176653 | F11: KR003355 Take Hotel Seoul Gwangmyeong 730925 -> 브랜드변경으로 호텔 판매중지로 확인 KR002281 Kolon Seacloud Hotel 176653 ->블랙리스트로 확인 상기 2곳 제외하고는 정상노출 확인
D12: 요금/물량 이슈 | E12: KR003019/811623 Kwangsu Hotel 플랜 노출 확인 Deluxw Family Twin 객실에서 룸온리가 노출안된다고 확인요청 | F12: 씨트립 Yoana 매니저와 확인 오마이에서 룸온리 플랜을 3인만 보내고 있어서 2인검색시 노출이 안되었음. 호세님에게 컨텐츠팀과 추가 팔로업 필요한 점 안내
D13: 매핑/콘텐츠 | E13: KR002909 Yeosu Hotel First City 마스터호텔 확인 | F13: 트립닷컴에 비슷한 호텔이 2개가 운영되고 있고 호텔에서는 계정을 합치려고 함. First city hotel Yeosu 기존 매핑된 마스터호텔에서 Yeosu first city hotel (first land)로 변경요청을 컨텐츠팀에서 진행함 이름이 비슷해서 Yoana매니저가 한 번 더 체크요청하였음. 관련하여 처리방법 Grace님에게 인계 및 처리완료
C14: 티켓패스 | D14: 프로모션제안 | E14: 트래블쇼 간사이리무진 판매 관련 확인중 | F14: 온라인 최저가 확인 후 판매가 결정 박람회 티켓소지량 계산 현장결제 방법 재확인 필요 - 카드단말기 티켓소지 담당자 확인 필요 - 차주 월요일 A4 용지 스텐딩홀더 4개 준비 - 차주 월요일 마케팅 전달필요
D15: 프로모션제안 | E15: 간사이 리무진 실물티켓 교환 절차 확인중 | F15: 베스트제이코리아에서 JTR로 전환 가능함 다만 공항->목적지 한 방향으로만 가능하며, 전환 신청했고 베스트제이코리아에서 JTR과 간사이리무진 확인중. 진행 시 상품번호 발급 등 절차가 많아서 시간이 다소 소요될 것이라고 함(0424)
D16: 이상 없음(No Issue) | E16: 티켓 주간마감 | F16: 판매량 : 12매 수탁고 : 342,620원 수익 : 6,912원 디파짓 현황 링크티비티 : 69,335엔 JTR : 256,262엔
C17: 매뉴얼 생성 | D17: 이상 없음(No Issue) | E17: 11번가 정산 매뉴얼 작성중 | F17: 드래프트 작성 후 클로드 진행 국문본 컨펌 받고 영문본 번역진행예정
D18: 이상 없음(No Issue) | E18: 씨트립 플랜 작업 매뉴얼 작성 | F18: 드래프트-클로드 국문 완료 에이든님 컨펌 후 영문본 Vicky와 Nancy 전달완료
A19: 4/27~4/30 | B19: Jasmine | C19: 씨트립 | D19: 이상 없음(No Issue) | E19: 씨트립 실적정리 (2025년 대비 2026년) | F19: YOY, MOM, 주요 이슈 최신 매핑 현황 업데이트
D20: 매핑/콘텐츠 | E20: JP000072 - Holiday Inn Osaka Namba 344271 노출확인 | F20: 플랜 재정비 후 노출확인완료
D21: 매핑/콘텐츠 | E21: JP002973/717930 - Oriental Hotel Universal City 노출확인 | F21: 플랜 재정비 후 노출확인완료
C22: 티켓패스 | D22: 프로모션제안 | E22: 간사이리무진 티켓 교환방법 2차 확인 | F22: JTR로 변환할 경우 전용상품구성이 필요하며, 이에 대한 시스템이용료 20만엔 + 티켓 수수료 535엔 발생한다고 함. 관련하여 에이든님께 보고완료
D23: 프로모션제안 | E23: 티켓패스 박람회 판매 확인 | F23: 결제방법 확인 - 조시님 박람회 전날 교육예정 A4스탠딩홀더+출력이미지 4부 - 마케팅보관 최저가 비교후 가격 컨펌 실물티켓 포장용 편지봉투 100매 준비
D24: 이상 없음(No Issue) | E24: 티켓 주간마감 + 월마감 + 스마트스토어 월정산 | F24: 주간 판매 : 4매 / 수탁고 78,610원 / 수익 2,072원 월마감 : 34매 / 수탁고 1,220,850원 / 수익 10,044원
D25: 이상 없음(No Issue) | E25: USJ 상품 변경 | F25: 당일 티켓 마감시간 변경으로 상품페이지 변경
C26: 매뉴얼 | D26: 이상 없음(No Issue) | E26: 먼쓸리브리프 매뉴얼 정리 | F26: 에이든님 검토 후 수기 말고 AI변환예정 우선 당분간은 기존방법대로 진행
D27: 이상 없음(No Issue) | E27: KKDAY 국문 매뉴얼 정리 | F27: 정산관련 매뉴얼 정리 검토 후 영문본 공유예정
A28: 5/4~5/8 | B28: Jasmine | C28: 티켓패스 | D28: 프로모션제안 | E28: 간사이리무진 티켓 교환방법 2차 확인 | F28: 시스템이용료 20만엔 비용발생으로 인해 잠시 홀딩. 박람회 때 최대한 실물티켓 소진목표로 진행
D29: 이상 없음(No Issue) | E29: USJ 상품 변경 | F29: 최대 구매수량 변경으로 스마트스토어 업데이트
C30: 트립토파즈 | D30: 이상 없음(No Issue) | E30: 2025/2026 실적파일 | F30: YOY, MOM 클로드로 PPT생성
D31: 프로모션제안 | E31: 숙박세일페스타 인벤토리체크 | F31: 6월 숙박세일페스타 참여를 위한 지역별 인벤토리 수 취합이 필요하다고 하시어, SCM에 요청 후 전달완료 서울 179, 경기 91, 인천 55, 강원 95, 경상 123, 전라 79, 충청 54, 부산 139, 제주 121
C32: KKDAY | D32: 이상 없음(No Issue) | E32: 내역확인 및 인보이스 발송 | F32: 9,421,910원 청구 및 입금확인 내역서에 업데이트 완료
C33: 매뉴얼 | D33: 이상 없음(No Issue) | E33: Bookable 매뉴얼 관련 확인 | F33: 기존 매뉴얼보다 컨텐츠팀에서 발송하는게 더 간단한 것으로 VNCT Karl과 확인하여 별도공유하지 않는 것으로 정리
D34: 이상 없음(No Issue) | E34: KKDAY 영문매뉴얼 변환 | F34: 국문매뉴얼 영문으로 변환완료
C35: 기타 | D35: 이상 없음(No Issue) | E35: 먼쓸리브리프 통계자료 | F35: 방문자통계, 광고키워드 취합하여 대표님께 전달
A36: 5/11~5/15 | B36: Jasmine | C36: 트래블쇼 | D36: 이상 없음(No Issue) | E36: 실물티켓, 상품권 판매 확인 | F36: 수량정리, 안내문 출력 실물티켓, 상품권 판매대장 정리
C37: B2C | D37: 매핑/콘텐츠 | E37: 886662 - Wyndham Garden Grandworld Phu Quoc 컨텐츠 및 소아세팅 관련 고객 문의 | F37: VN팀 확인 결과, 해당 호텔 한국마켓 제외로 설정해야하는데 비투씨에 노출이 된 것 같다고 함. 오기재된 컨텐츠 수정요청하였으며 KR마켓 제외로 수정한다고 함
D38: 이상 없음(No Issue) | E38: 숙박권 예약진행 | F38: ANA Crowne Plaza Sapporo
C39: 일본만 | D39: 이상 없음(No Issue) | E39: 소아 입력시 예약진행이 안된다고 하심 | F39: 본인이 테스트했을 땐 예약진행이 되어서, 일시적 오류로 예상됨. 일본만 담당자에게 고객/예약정보 받아서 예약진행완료
C40: 히카리글로벌 | D40: 이상 없음(No Issue) | E40: 서울 밀리오레호텔 이름변경 관련 컴플레인 | F40: 호텔에서 특정날짜에 예약이 생성되었다가 투숙객 변경요청건이 많고, 무료취소가능기한내에 대량으로 취소되는 경우가 많아서 업무에 지장이 생긴다고 함. 의심되는 예약리스트로 히카리가 많아서 호텔요청에 따라 히카리에 밀리오레 서울호텔은 이름변경 불가한 점 안내함
C41: 에어텔닷컴 | D41: 요금/물량 이슈 | E41: K26031811329H01 디다 서드파티 인원 이슈 | F41: 성인1+소아1인으로 조회 후 예약된 건이나, 호텔에서 해당 건은 소아1인도 추가비용 필요하다고 함. 디다에 재차 컴플레인 후 2차 채널링에서 세팅오류가 있었던 것으로 확인. 처음엔 현장지불만 가능하다고 했으나 JP SCM에서 호텔에 직접 교섭하여 해당 건 현장지불없이 디다에서 파트너사, 호텔과 선결제 진행하는 것으로 종결
C42: 티켓패스 | D42: 이상 없음(No Issue) | E42: 주간마감 | F42: 판매량 8, 수탁고 278,920원, 수익 1,367원
A43: 5/18~5/22 | B43: Jasmine | C43: 웹베즈DMC | D43: 이상 없음(No Issue) | E43: 하드블럭 판매 호텔체크 | F43: 요금 추가해야할 호텔들 정리
C44: 트립토파즈 | D44: 이상 없음(No Issue) | E44: 탑리스트 네이버호텔 최저가 확인 | F44: Boma Resort Nha Trang, Alibu Resort Nha Trang, InterContinental Nha Trang, an IHG Hotel
C45: KKDAY | D45: 이상 없음(No Issue) | E45: KKDAY 매출분석 | F45: 2025/2026 YOY, MOM 매출분석
C46: 히카리글로벌 | D46: 매핑/콘텐츠 | E46: K26051410529H01 채널링 매핑 오류 | F46: 호텔에서 아고다-환불불가 테스트부킹했는데 오마이-히카리상품으로 확인됨. 히카리에 연락하여 해당 예약 취소요청 및 채널링 수정요청 -> 완료
C47: 트래블쇼 | D47: 이상 없음(No Issue) | E47: 티켓/상품권 정리 | F47: 판매용 분출리스트+판매대장 정리 반납 후 재고 더블체크
C48: 티켓패스 | D48: 이상 없음(No Issue) | E48: 주간마감 | F48: 판매량 21, 수탁고 475,020원, 수익 140원
D49: 이상 없음(No Issue) | E49: 티켓 매출분석 | F49: 티켓 수익분석 및 실제적 투입 리소스 대비 업무 필요성 분석
D50: 이상 없음(No Issue) | E50: 티켓패스 디파짓 환불 확인 | F50: JTR 252,262엔 / 링크티비티 9,025엔 잔액 환불가능여부 확인 두 공급사 다 환불가능하여 인보이스 청구한 상태 현재 스마트스토어+오마이트립 티켓상품은 실물 리무진티켓 제외 전부 중지상태
D51: 이상 없음(No Issue) | E51: 간사이리무진 티켓 시장조사 | F51: 클로드 통하여 kkday, klook, myrealtrip 판매페이지 및 블로그 등 취합을 통해 라피트와 리무진 티켓 시장조사진행 라피트가 압도적으로 많은 것으로 확인되었음
A52: 5/25~5/29 | B52: Jasmine | C52: 티켓패스 | D52: 이상 없음(No Issue) | E52: 티켓 수익구조 변동보고서 | F52: 온라인 최저가로 변경시 티켓 수익구조 분석 4종 티켓 잔여수량으로 계산시 플러스 구조로 확인되어 티켓 금액 온라인 최저가로 변경완료
D53: API 연동 진행 | E53: 링크티비티 연동가능여부 확인 | F53: 개발문서 개발팀에 전달할 수 있으며, 메신저는 슬랙으로 이용한다고 함. 우선 연동가능한 점 확인 후 보류
D54: 이상 없음(No Issue) | E54: 티켓 월마감 | F54: 판매량 29 / 수탁고 753,940 / 수익 1,507 *e티켓 판매종료 실물티켓만 판매로 변경
D55: 이상 없음(No Issue) | E55: JTR 디파짓 잔액 환불확인 | F55: 잔액환불 확인 후 이카운트 시스템수정
C56: 기타 | D56: 이상 없음(No Issue) | E56: 먼쓸리브리프 매뉴얼 영문변환 | F56: 먼쓸리브리프 매뉴얼 영문변환
D57: 이상 없음(No Issue) | E57: 11번가, KKDAY 정산매뉴얼 교육자료 정리 | F57: VNOP 교육용 자료 재정리
D58: 이상 없음(No Issue) | E58: 11번가, KKDAY 정산 교육 | F58: Vicky, Peter 대상으로 매뉴얼 배포 후 교육
D59: 이상 없음(No Issue) | E59: B2C 고객 취소확인 | F59: 트래블쇼에서 48시간 개런티 예약하신 고객님 취소건 팔로업
A60: 6/1~6/5 | B60: Jasmine | C60: 웹베즈DMC | D60: 요금/물량 이슈 | E60: Daiwa Roynet Hotel Osaka Sakaisuji Honmachi PREMIER 요금표 | F60: 컨텐츠팀에 요금표 전송완료. 업데이트 완료되면 재고업데이트 예정
D61: 요금/물량 이슈 | E61: DEL style Osaka Shinsaibashi by Daiwaroynet 요금표 | F61: 컨텐츠팀에 요금표 전송완료. 업데이트 완료되면 재고업데이트 예정
D62: 요금/물량 이슈 | E62: Hotel Monte Hermana Fukuoka 요금표 생성 | F62: 컨텐츠팀에 요금표 전송완료. 업데이트 완료되면 재고업데이트 예정
D63: 요금/물량 이슈 | E63: Hotel Monterey La Soeur Fukuoka 요금표 생성 | F63: 컨텐츠팀에 요금표 전송완료. 업데이트 완료되면 재고업데이트 예정
D64: 요금/물량 이슈 | E64: 취소규정 업데이트 | F64: 체크인 전 9일로 세팅되어있는지 전체 체크 후 수정
C65: 티켓패스 | D65: 이상 없음(No Issue) | E65: 마감방식 변경 | F65: 기존 데일리/주간/월간에서 데일리로 축소 클로드로 파일변경중
D66: 이상 없음(No Issue) | E66: 주간마감 | F66: 수량 6 / 수탁고 67,8,00원 / 수익 -2,772원
C67: 11번가 | D67: 이상 없음(No Issue) | E67: 정산매뉴얼 수정 | F67: 수정 후 Vicky에게 공유완료
C68: 기타 | D68: 이상 없음(No Issue) | E68: 먼쓸리브리프 인수인계 | F68: 그레이스에게 인수인계완료

Sheet Ben
A1: 날짜 (Date) | B1: 작성자 (Reporter) | C1: 채널명 (Channel) | D1: 유형 (Type) | E1: 내용 (Details) | F1: 대응/액션 (Action Plan) | G1: 비고 (Remarks)
A2: 예: 04/07 e.g. MM/DD | B2: 이름 Name | C2: 채널/업체명 Channel/Company Name | D2: ▼ 선택 ▼ Select | E2: 상세 내용 기재 Describe in detail | F2: "무엇을, 언제까지" 명시 Specify "What, by When"
A3: April 13-17 | B3: Ben | C3: VN:Mustgo | D3: 신규 계약 | E3: Mustgo Under internally discussion after sale call | F3: Waiting for Mustgo provide Portal Test | G3: cross selling
B4: Ben | C4: VN:Vietravel | D4: 신규 계약 | E4: Under NDA Contract, VTV is internally reviewing | F4: On board on Q2 | G4: API
B5: Ben | C5: VN:Gotadi | D5: 신규 계약 | E5: Under reviewing 2 agreements + NDA | F5: On board on Q2 | G5: API
B6: Ben | C6: VN:BestPrice | D6: 신규 계약 | E6: Under discussion about Payment T&C | F6: Deposit: offer decrease amount of deposit or no need: depending on booking volume | G6: API
B7: Ben | C7: VN:Travelotels | D7: 신규 계약 | E7: Request payment method: credit card Rate will be higher ~ 4%, but they said to high, normally is ~1% | F7: Suggest meeting & prefer API | G7: Dotbiz
B8: Ben | C8: VN: Ctrip VN | D8: 프로모션제안 | E8: CT: Recheck unmapped room mapping: ~7000 rooms compared to Open Ctrip Platform 24th April will identify the final unmapped room number and recheck with VN SCM | F8: 24th will coordinate with SCM to priority request map room list prefered from Ctrip & VN SCM List | G8: Room mapping
B9: Ben | C9: VN: Chudu24 | D9: 인증/테스트 완료 | E9: Follow up to receive back Agreement via EMS & Amendment of Bank Account | G9: Dotbiz
B10: Ben | C10: Indo: TVLK | D10: 프로모션제안 | E10: Enroll Epic Sale Day: 5.5 Follow up Bank Account Changed Increase QPS from 80 to -150 / CUG to B2C feed | F10: Observe booking volume after activing B2C feed & Epic Sale. | G10: API
B11: Ben | C11: Indo: MG | D11: 프로모션제안 | E11: Follow up the Bank Account Changed Hotel Mapping now is 62% -> aim to 90% | F11: Coordinate with CT to push mapping % | G11: Hotel Mapping
B12: Ben | C12: Indo: Hotelinx | D12: 신규 계약 | E12: Receiving Hotelinx's NDA Asking switching company contact Technoheaven to check first | F12: Contact to Technoheaven if we connect with potential clients through this switching or not | G12: Cross Selling 3rd Company IT
B13: Ben | C13: India: MMT | D13: 신규 계약 | E13: After Meeting with MMT Waiting to their response about moving forward next step after Test ID checked. | F13: Keep following up
B14: Ben | C14: India: Cleartrip | D14: 신규 계약 | E14: Send Portal ID Account + Top list they want use dotbiz first with credit card payment method | F14: Prefer API Direct Connectivity
B15: Ben | C15: Russia: Emerging Travel Group | D15: 신규 계약 | E15: Request Cross Selling and currently working with Ms. Sophia | F15: Follow up with Sophia & will arrange e-meeting
A16: April 20-24 | B16: Ben | C16: VN: Gotadi | D16: 프로모션제안 | E16: Under Agreement & SLA: Discussion -> Taxes, Clause | F16: Handle Inquires - expect active on Q2 | G16: Gotadi miss understand about Commission & Mark up rate. already explain
B17: Ben | C17: Indo: OYO Indonesia | D17: 프로모션제안 | E17: OMH Introduction | F17: Arrange e-meeting to better understand business
B18: Ben | C18: Indo: Airpaz | D18: 프로모션제안 | E18: OMH Introduction | F18: Arrange e-meeting to better understand business
B19: Ben | C19: Indo: Gloden Rama Tour | D19: 프로모션제안 | E19: OMH Introduction | F19: Arrange e-meeting to better understand business
B20: Ben | C20: Indi: Travelguru | D20: 프로모션제안 | E20: OMH Introduction | F20: Arrange e-meeting to better understand business
B21: Ben | C21: VN: Vietravel | D21: 프로모션제안 | E21: Reminder & follow up NDA | F21: Follow up & keep contact // expect active on Q2
B22: Ben | C22: VN: Momo | D22: 프로모션제안 | E22: OMH Introduction & Momo Structure Rate | F22: Internal reviewing Momo Structure Solution | G22: Rate Proposal
B23: Ben | C23: Russia: Tutu.ru | D23: 프로모션제안 | E23: OMH Introduction | F23: Arrange e-meeting to better understand business
B24: Ben | C24: Indo: Traveloka | D24: 기타 | E24: Bank Account Changed | F24: Waiting for Traveloka review the final verion of agreement
B25: Ben | C25: Indo: Room Dea | D25: 기타 | E25: Bank Account Changed | F25: Coordinate with Ms Sophia to check MG feedback
B26: Ben | C26: Indo: Tiket.com | D26: 프로모션제안 | E26: Confirmation the coordination timeline | F26: Agreement for both selling & buying first API will be developed once Selling side can be confirmed exact date.
B27: Ben | C27: Russia: Travelata.ru | D27: 프로모션제안 | E27: E-meeting Confirmation | F27: Waiting for confirm meeting time
B28: Ben | C28: VN: Ctrip VN | D28: 기타 | E28: Recheck: ~7200 unmapped room by CT team | F28: On 24th report: 304 room mapping manually **2669 unmapped room should be checked by VN SCM Others are belongs to Black list. | G28: Room mapping ~62% with 2669 unmapped rooms are waiting for VN SCM check with hotel again
A29: April 28-29 | B29: Ben | C29: Russia: Smartway | D29: API이슈 | E29: Arrange Meeting to discuss more | F29: 4PM at 6th april
B30: Ben | C30: Russia: Travelata.ru | D30: API이슈 | E30: Recap meeting: Timeline:: Q4 2026 can develop API Deposit should be negotiates Payment Method go through offshore bank (Kazakhstan Bank) (Bank details waiting email) RUB/USD | F30: Test ID + Top List Travelata checking | G30: Expected On Board on Q4 2026
B31: Ben | C31: Indo: Tiket.com | D31: 기타 | E31: Cross selling: Purchasing Contract: Ms. Sophia will internal review Selling Contract & NDA: Wait for Tiket sending | F31: Follow up with Ms. Sophia
B32: Ben | C32: VN: Gotadi | D32: 요금문제 | E32: Misunderstanding about FCT E-meeting with Gotadi and Accountant to explain and discuss | F32: 10AM at 7th April | G32: VN Taxes: FCT
B33: Ben | C33: India: Via.com | D33: API이슈 | E33: Arrange meeting to explore corpoation | F33: Wait for meeting confirmation
B34: Ben | C34: Indo: Room Deal MG | D34: 기타 | E34: Citibank Account changed: The amended Agreement related to Purchasing Contract Ms. Sophia will internally review and feedback to MG | G34: Citibank Changed
B35: Ben | C35: Indo: TVLK | D35: 기타 | E35: Citibank Account Changed: TVLK is internally reviewing the OMH's feedback | G35: Citibank Changed
A36: May 4-8 | B36: Ben | C36: VN: Momo | D36: 기타 | E36: Signed NDA & API Doc | F36: Due to lack of IT staff on Momo end. The system should developed done on Q4 2026, after that they can start to move forward the next step with us. | G36: Keep in Touch
B37: Ben | C37: Indonesia: OYO | D37: 기타 | E37: OMH Introduction | F37: Arrange e-meeting to better understand business
B38: Ben | C38: Indonesia: TVLK | D38: 프로모션제안 | E38: -Epic Sale Campaige from 4-8 May -TVLK Inquiries -After discussion new claude for Amended Contract, TVLK will sign and send back on next week | F38: - Compared The Campaigne Rate with Our Rate to Identify the Gap - Coordinate with VNOP to support Inquery - Follow up to receive back the amended Contract next Week
B39: Ben | C39: India: SOTC | D39: 기타 | E39: Arrange e-meeting to proposal partnership
B40: Ben | C40: Malaysia: MHholidays | D40: 기타 | E40: OMH Introduction | F40: Arrange e-meeting to better understand business
B41: Ben | C41: Malaysia: AsiaAir Move | D41: 기타 | E41: OMH Introduction | F41: Arrange e-meeting to better understand business
B42: Ben | C42: 101hotels.com | D42: 기타 | E42: OMH Introduction | F42: Arrange e-meeting to better understand business | G42: Russia Clients
C43: Bronevik.com | D43: 기타 | E43: OMH Introduction | F43: Arrange e-meeting to better understand business
C44: Yandex Travel | D44: 기타 | E44: OMH Introduction | F44: Arrange e-meeting to better understand business
C45: Otello belong to 2GIS | D45: 기타 | E45: OMH Introduction | F45: Arrange e-meeting to better understand business
C46: HBpro.expert belong to hotelbook.ru | D46: 기타 | E46: OMH Introduction | F46: Arrange e-meeting to better understand business
C47: Aeroclub | D47: 기타 | E47: OMH Introduction | F47: Arrange e-meeting to better understand business
C48: FUN&SUN (ex-TUI Russia) | D48: 기타 | E48: OMH Introduction | F48: Arrange e-meeting to better understand business
C49: Sunmar | D49: 기타 | E49: OMH Introduction | F49: Arrange e-meeting to better understand business
B50: Ben | C50: Russia: Smartway | D50: 기타 | E50: E-Meeting (Done) Test ID & Rate Checking Internally
B51: Ben | C51: VN: Vietravel | D51: 기타 | E51: NDA done & API Doc | F51: Request Credential Key and send API Doc to VTV next week
B52: Ben | C52: VN: Gotadi | D52: 기타 | E52: Meeting: confused about Foreign Contractor Tax (Done) API DOC sent Follow up agreement
B53: Ben | C53: Thailand: Gother | D53: 기타 | E53: OMH Introduction | F53: Arrange e-meeting to better understand business
B54: Ben | C54: India: EaseMyTrip | D54: 기타 | E54: Arranged E-Meeting next week to discuss partnership corporation
A55: 11-15 May | B55: Ben | C55: India: EaseMyTrip | D55: 기타 | E55: Meeting done | F55: Test ID + Top List
B56: Ben | C56: VN: Vietravel | D56: 기타 | E56: Agreement Internally Review | F56: Key Credential + API Doc | G56: 1 API - 2 Accounts
B57: Ben | C57: VN: Gotadi | D57: 기타 | E57: Agreement Internally Review | F57: Key Credential + API Doc
B58: Ben | C58: Agoda | D58: 시스템장애 | E58: Connection Suspension No Rate Availability Check
B59: Ben | C59: Russia: Bronevik | D59: 기타 | E59: Confirm Meeting at ITB China
B60: Ben | C60: RateHawk | D60: 기타 | E60: Preparation for 2nd round rate checking
A61: 18-22 May | B61: Ben | C61: Agoda | D61: 기타 | E61: Turnoff & No Rate Issue | F61: Coordinate w IT to identify issue | G61: Lack of Inventories exchange rate fluctuations
